Workbook

Sheet Acceso
A1: Platform or Equipment | B1: Associated Services to the platform | C1: Income / Dismount | D1: Responsable Technical Area | E1: Responsable Technician | F1: Year | G1: Technical Site | H1: City | I1: Regional | J1: Additional m2? Yes/No | K1: If Yes: # Racks? | L1: Quantity Equipment DC | M1: Average Power (W) | N1: Máx. Power DC (W) | O1: Potencia a liberar | P1: Voltage (AC or DC) | Q1: Air DissipationBTU | R1: Power sources | S1: Quantity Equipment AC | T1: Máx. Power AC (W) | U1: Voltage (AC or DC) | V1: Requested Area (M2) | W1: Instalation date | X1: Priority | Y1: Comments (Área Ingeniería)
A4: Plataforma OLT Equipo Nuevo | B4: BBI-TV-TOIP | C4: Income | D4: ACCESO FIJO | E4: Henry Campos | F4: 2023 | G4: Centro EDATEL | H4: Puerto Berrio | J4: Yes | K4: 2 | L4: 1 | M4: 842 | N4: 1403 | P4: DC | R4: 2 | S4: 0 | T4: 0 | U4: DC | V4: 3 | W4: Q2
A5: Plataforma OLT Equipo Nuevo | B5: BBI-TV-TOIP | C5: Income | D5: ACCESO FIJO | E5: Henry Campos | F5: 2023 | G5: Centro EDATEL | H5: Segovia | J5: Yes | K5: 2 | L5: 1 | M5: 842 | N5: 1403 | P5: DC | R5: 2 | S5: 0 | T5: 0 | U5: DC | V5: 3 | W5: Q2
A6: Plataforma OLT Equipo Nuevo | B6: BBI-TV-TOIP | C6: Income | D6: ACCESO FIJO | E6: Henry Campos | F6: 2023 | G6: Centro EDATEL | H6: Chigorodó | J6: Yes | K6: 2 | L6: 1 | M6: 842 | N6: 1403 | P6: DC | R6: 2 | S6: 0 | T6: 0 | U6: DC | V6: 3 | W6: Q2
A7: Plataforma OLT Equipo Nuevo | B7: BBI-TV-TOIP | C7: Income | D7: ACCESO FIJO | E7: Henry Campos | F7: 2023 | G7: Castilla | H7: MEDELLÍN | J7: Yes | K7: 2 | L7: 1 | M7: 842 | N7: 1403 | P7: DC | R7: 2 | S7: 0 | T7: 0 | U7: DC | V7: 3 | W7: Q1
A8: Plataforma OLT Equipo Nuevo | B8: BBI-TV-TOIP | C8: Income | D8: ACCESO FIJO | E8: Henry Campos | F8: 2023 | G8: Berlín | H8: MEDELLÍN | J8: Yes | K8: 2 | L8: 1 | M8: 842 | N8: 1403 | P8: DC | R8: 2 | S8: 0 | T8: 0 | U8: DC | V8: 3 | W8: Q1
A9: Plataforma OLT Equipo Nuevo | B9: BBI-TV-TOIP | C9: Income | D9: ACCESO FIJO | E9: Henry Campos | F9: 2023 | G9: Villa Hermosa | H9: MEDELLÍN | J9: Yes | K9: 2 | L9: 1 | M9: 842 | N9: 1403 | P9: DC | R9: 2 | S9: 0 | T9: 0 | U9: DC | V9: 3 | W9: Q1
A10: Plataforma OLT Equipo Nuevo | B10: BBI-TV-TOIP | C10: Income | D10: ACCESO FIJO | E10: Henry Campos | F10: 2023 | G10: Florencia | H10: MEDELLÍN | J10: Yes | K10: 2 | L10: 1 | M10: 842 | N10: 1403 | P10: DC | R10: 2 | S10: 0 | T10: 0 | U10: DC | V10: 3 | W10: Q1
A11: Plataforma OLT Equipo Nuevo | B11: BBI-TV-TOIP | C11: Income | D11: ACCESO FIJO | E11: Henry Campos | F11: 2023 | G11: Bosque | H11: MEDELLÍN | J11: Yes | K11: 2 | L11: 1 | M11: 842 | N11: 1403 | P11: DC | R11: 2 | S11: 0 | T11: 0 | U11: DC | V11: 3 | W11: Q1
A12: Plataforma OLT Equipo Nuevo | B12: BBI-TV-TOIP | C12: Income | D12: ACCESO FIJO | E12: Henry Campos | F12: 2023 | G12: Belén | H12: MANIZALES | J12: Yes | K12: 2 | L12: 1 | M12: 842 | N12: 1403 | P12: DC | R12: 2 | S12: 0 | T12: 0 | U12: DC | V12: 3 | W12: Q2
A13: Plataforma OLT Equipo Nuevo | B13: BBI-TV-TOIP | C13: Income | D13: ACCESO FIJO | E13: Henry Campos | F13: 2023 | G13: Centro | H13: BUGA | J13: Yes | K13: 2 | L13: 1 | M13: 842 | N13: 1403 | P13: DC | R13: 2 | S13: 0 | T13: 0 | U13: DC | V13: 3 | W13: Q2
A14: Plataforma OLT Equipo Nuevo | B14: BBI-TV-TOIP | C14: Income | D14: ACCESO FIJO | E14: Henry Campos | F14: 2023 | G14: Álamos | H14: Pereira | J14: Yes | K14: 2 | L14: 1 | M14: 842 | N14: 1403 | P14: DC | R14: 2 | S14: 0 | T14: 0 | U14: DC | V14: 3 | W14: Q2
A15: Plataforma OLT Equipo Nuevo | B15: BBI-TV-TOIP | C15: Income | D15: ACCESO FIJO | E15: Henry Campos | F15: 2023 | G15: San Francisco | H15: Bucaramanga | J15: Yes | K15: 2 | L15: 1 | M15: 842 | N15: 1403 | P15: DC | R15: 2 | S15: 0 | T15: 0 | U15: DC | V15: 3 | W15: Q2
... A45: Plataforma CMTS Tradicional Equipo Nuevo | B45: BBI-TV-TOIP | C45: Income | D45: ACCESO FIJO | E45: Juan Valdes | F45: 2023 | G45: Engativá | H45: Bogotá | J45: Yes | K45: 1 | L45: 1 | M45: 6000 | N45: 1500 | P45: DC | R45: 4 | S45: 0 | T45: 0 | U45: DC | V45: 1.5 | W45: Q2
A46: Plataforma Óptica | B46: BBI-TV-TOIP | C46: Income | D46: Gerencia Acceso Fijo | E46: Jorge Ivan Pérez Cardona | F46: 2023 | G46: Cantalejo | H46: Bogotá | J46: Yes | K46: 1 | L46: 6 | M46: 475 | N46: 2850 | P46: DC | Q46: 1620.75 | R46: 2 | U46: 48 VDC | V46: 1.5 | W46: Q1-Q2 | Y46: Transmisores y Receptotes Ópticos
A47: Plataforma Óptica | B47: BBI-TV-TOIP | C47: Income | D47: Gerencia Acceso Fijo | E47: Jorge Ivan Pérez Cardona | F47: 2023 | G47: Quinta Camacho | H47: Bogotá | J47: Yes | K47: 1 | L47: 6 | M47: 475 | N47: 2850 | P47: DC | Q47: 1620.75 | R47: 2 | U47: 48 VDC | V47: 1.5 | W47: Q1-Q2 | Y47: Transmisores y Receptotes Ópticos
A48: Plataforma Óptica | B48: BBI-TV-TOIP | C48: Income | D48: Gerencia Acceso Fijo | E48: Jorge Ivan Pérez Cardona | F48: 2023 | G48: El Carmen | H48: Bogotá | J48: Yes | K48: 1 | L48: 6 | M48: 475 | N48: 2850 | P48: DC | Q48: 1620.75 | R48: 2 | U48: 48 VDC | V48: 1.5 | W48: Q1-Q2 | Y48: Transmisores y Receptotes Ópticos
A49: Plataforma Óptica | B49: BBI-TV-TOIP | C49: Income | D49: Gerencia Acceso Fijo | E49: Jorge Ivan Pérez Cardona | F49: 2023 | G49: Engativa | H49: Bogotá | J49: Yes | K49: 1 | L49: 6 | M49: 475 | N49: 2850 | P49: DC | Q49: 1620.75 | R49: 2 | U49: 48 VDC | V49: 1.5 | W49: Q1-Q2 | Y49: Transmisores y Receptotes Ópticos
A50: Plataforma Óptica | B50: BBI-TV-TOIP | C50: Income | D50: Gerencia Acceso Fijo | E50: Jorge Ivan Pérez Cardona | F50: 2023 | G50: La Fragua | H50: Bogotá | J50: Yes | K50: 1 | L50: 6 | M50: 475 | N50: 2850 | P50: DC | Q50: 1620.75 | R50: 2 | U50: 48 VDC | V50: 1.5 | W50: Q1-Q2 | Y50: Transmisores y Receptotes Ópticos
A51: Plataforma Óptica | B51: BBI-TV-TOIP | C51: Income | D51: Gerencia Acceso Fijo | E51: Jorge Ivan Pérez Cardona | F51: 2023 | G51: La Paz (Bosa) | H51: Bogotá | J51: Yes | K51: 1 | L51: 6 | M51: 475 | N51: 2850 | P51: DC | Q51: 1620.75 | R51: 2 | U51: 48 VDC | V51: 1.5 | W51: Q1-Q2 | Y51: Transmisores y Receptotes Ópticos
A52: Plataforma Óptica | B52: BBI-TV-TOIP | C52: Income | D52: Gerencia Acceso Fijo | E52: Jorge Ivan Pérez Cardona | F52: 2023 | G52: Suba | H52: Bogotá | J52: Yes | K52: 1 | L52: 6 | M52: 475 | N52: 2850 | P52: DC | Q52: 1620.75 | R52: 2 | U52: 48 VDC | V52: 1.5 | W52: Q1-Q2 | Y52: Transmisores y Receptotes Ópticos
A53: Plataforma Óptica | B53: BBI-TV-TOIP | C53: Income | D53: Gerencia Acceso Fijo | E53: Jorge Ivan Pérez Cardona | F53: 2023 | G53: Timiza | H53: Bogotá | J53: Yes | K53: 1 | L53: 6 | M53: 475 | N53: 2850 | P53: DC | Q53: 1620.75 | R53: 2 | U53: 48 VDC | V53: 1.5 | W53: Q1-Q2 | Y53: Transmisores y Receptotes Ópticos
A54: Plataforma Óptica | B54: BBI-TV-TOIP | C54: Income | D54: Gerencia Acceso Fijo | E54: Jorge Ivan Pérez Cardona | F54: 2023 | G54: Montevídeo | H54: Bogotá | J54: Yes | K54: 1 | L54: 12 | M54: 475 | N54: 5700 | P54: DC | Q54: 1620.75 | R54: 2 | U54: 48 VDC | V54: 1.5 | W54: Q1-Q2 | Y54: Transmisores y Receptotes Ópticos
A55: Plataforma Óptica | B55: BBI-TV-TOIP | C55: Income | D55: Gerencia Acceso Fijo | E55: Jorge Ivan Pérez Cardona | F55: 2023 | G55: CAN | H55: Bogotá | J55: Yes | K55: 1 | L55: 6 | M55: 475 | N55: 2850 | P55: DC | Q55: 1620.75 | R55: 2 | U55: 48 VDC | V55: 1.5 | W55: Q1-Q2 | Y55: Transmisores y Receptotes Ópticos
A56: Plataforma Óptica | B56: BBI-TV-TOIP | C56: Income | D56: Gerencia Acceso Fijo | E56: Jorge Ivan Pérez Cardona | F56: 2023 | G56: Santa Bibiana | H56: Bogotá | J56: Yes | K56: 1 | L56: 6 | M56: 475 | N56: 2850 | P56: DC | Q56: 1620.75 | R56: 2 | U56: 48 VDC | V56: 1.5 | W56: Q1-Q2 | Y56: Transmisores y Receptotes Ópticos
A57: Plataforma Óptica | B57: BBI-TV-TOIP | C57: Income | D57: Gerencia Acceso Fijo | E57: Jorge Ivan Pérez Cardona | F57: 2023 | G57: Valladolid | H57: Bogotá | J57: Yes | K57: 1 | L57: 6 | M57: 475 | N57: 2850 | P57: DC | Q57: 1620.75 | R57: 2 | U57: 48 VDC | V57: 1.5 | W57: Q1-Q2 | Y57: Transmisores y Receptotes Ópticos
... A135: Plataforma Óptica | B135: BBI-TV-TOIP | C135: Income | D135: Gereencia Acceso Fijo | E135: Jorge Ivan Pérez Cardona | F135: 2023 | G135: Autopista | H135: Tunja | J135: Yes | K135: 1 | L135: 6 | M135: 475 | N135: 2850 | P135: DC | Q135: 1620.75 | R135: 2 | U135: 48 VDC | V135: 1.5 | W135: Q1-Q2 | Y135: Transmisores y Receptotes Ópticos

Sheet Transporte
A2: Platform or Equipment | B2: Associated Services to the platform | C2: Income / Dismount | D2: Responsable Technical Area | E2: Responsable Technician | F2: Year | G2: Technical Site | H2: City | I2: Regional | J2: Additional m2? Yes/No | K2: If Yes: # Racks? | L2: Quantity Equipment DC | M2: Average Power (W) | N2: Máx. Power DC (W) | O2: Potencia liberar | P2: Voltage (AC or DC) | Q2: Air DissipationBTU | R2: Power sources | S2: Quantity Equipment AC | T2: Máx. Power AC (W) | U2: Voltage (AC or DC) | V2: Requested Area (M2) | W2: Instalation date | X2: Prority | Y2: Comments
A3: DWDM Huawei | B3: Internet, datos, voz, B2B, TV | C3: Income | D3: Gerencia de Transporte | E3: Wilmar Moreno | F3: 2023 | G3: Bosque | H3: Cartagena | I3: Costa | J3: No | M3: 1191 | P3: DC | Q3: =M3*3.4121 -> 4063.8111 | U3: 48 VDC | Y3: Tarjetas en OSN9800U32 existente
A4: DWDM Huawei | B4: Internet, datos, voz, B2B, TV | C4: Income | D4: Gerencia de Transporte | E4: Wilmar Moreno | F4: 2023 | G4: Miraflores | H4: Medellín | I4: Nor occidente | J4: No | M4: 1898 | P4: DC | Q4: =M4*3.4121 -> 6476.1658 | U4: 48 VDC | Y4: Tarjetas en OSN9800U32 existente
A5: DWDM Huawei | B5: Internet, datos, voz, B2B, TV | C5: Income | D5: Gerencia de Transporte | E5: Wilmar Moreno | F5: 2023 | G5: Zona Sur MON004 | H5: Montería | I5: Costa | J5: No | M5: 858 | P5: DC | Q5: =M5*3.4121 -> 2927.5818 | U5: 48 VDC | Y5: Tarjetas en OSN9800U32 existente
A6: DWDM Huawei | B6: Internet, datos, voz, B2B, TV | C6: Income | D6: Gerencia de Transporte | E6: Wilmar Moreno | F6: 2023 | G6: 7 de agosto VAL005 | H6: Valledupar | I6: Costa | J6: Yes | K6: 1 | L6: 1 | M6: 1241 | N6: 2400 | P6: DC | Q6: =M6*3.4121 -> 4234.4161 | R6: 2+2 | U6: 48 VDC | V6: 0,3 x 0,6 | Y6: Tarjetas en OSN9800U32 existente 1 Rack y equipo OSN1800V nuevo
A7: DWDM Huawei | B7: Internet, datos, voz, B2B, TV | C7: Income | D7: Gerencia de Transporte | E7: Wilmar Moreno | F7: 2023 | G7: Anillo Vial | H7: Bucaramanga | I7: Oriente | J7: No | M7: 700 | P7: DC | Q7: =M7*3.4121 -> 2388.47 | U7: 48 VDC | Y7: Tarjetas en OSN9800U32 existente
A8: DWDM Huawei | B8: Internet, datos, voz, B2B, TV | C8: Income | D8: Gerencia de Transporte | E8: Wilmar Moreno | F8: 2023 | G8: Centro | H8: Manizales | I8: Eje Cafetero | J8: No | M8: =2328-1464 -> 864 | P8: DC | Q8: =M8*3.4121 -> 2948.0544 | U8: 48 VDC | Y8: Tarjetas en OSN9800U32 existente
A9: DWDM Huawei | B9: Internet, datos, voz, B2B, TV | C9: Income | D9: Gerencia de Transporte | E9: Wilmar Moreno | F9: 2023 | G9: Coliseo | H9: Pereira | I9: Eje Cafetero | J9: No | M9: 383 | P9: DC | Q9: =M9*3.4121 -> 1306.8343 | U9: 48 VDC | Y9: Tarjetas en OSN9800M24 existente
A10: DWDM Huawei | B10: Internet, datos, voz, B2B, TV | C10: Income | D10: Gerencia de Transporte | E10: Wilmar Moreno | F10: 2023 | G10: Centro | H10: Pereira | I10: Eje Cafetero | J10: No | M10: 766 | P10: DC | Q10: =M10*3.4121 -> 2613.6686 | U10: 48 VDC | Y10: Tarjetas en OSN9800M24 existente
A11: DWDM Huawei | B11: Internet, datos, voz, B2B, TV | C11: Income | D11: Gerencia de Transporte | E11: Wilmar Moreno | F11: 2023 | G11: Vasquez Cobo | H11: Cali | I11: Sur occidente | J11: No | M11: 542 | P11: DC | Q11: =M11*3.4121 -> 1849.3582 | U11: 48 VDC | Y11: Tarjetas en OSN9800M24 existente
A12: DWDM Huawei | B12: Internet, datos, voz, B2B, TV | C12: Income | D12: Gerencia de Transporte | E12: Wilmar Moreno | F12: 2023 | G12: Belén | H12: Manizales | I12: Eje Cafetero | J12: Yes | K12: 1 | L12: 1 | M12: 1788 | N12: 3874 | P12: DC | Q12: =M12*3.4121 -> 6100.8348 | R12: 2+2 | U12: 48 VDC | V12: 0,3 x 0,6 | Y12: 1 rack y equipo OSN9800M24 nuevo
A13: DWDM Huawei | B13: Internet, datos, voz, B2B, TV | C13: Income | D13: Gerencia de Transporte | E13: Wilmar Moreno | F13: 2023 | G13: La Ceja | H13: La Ceja | I13: Nor occidente | J13: No | L13: 1 | M13: =440+78 -> 518 | N13: 800 | P13: DC | Q13: =M13*3.4121 -> 1767.4678 | U13: 48 VDC | Y13: Tarjetas en OSN1800VPro existente 1 equipo OSN1800II TP Nuevo
A14: DWDM Huawei | B14: Internet, datos, voz, B2B, TV | C14: Income | D14: Gerencia de Transporte | E14: Wilmar Moreno | F14: 2023 | G14: El Burro CES0017 | H14: El Burro | I14: Costa | J14: No | M14: 172 | P14: DC | Q14: =M14*3.4121 -> 586.8812 | U14: 48 VDC | Y14: Tarjetas en 1800V existente
A15: DWDM Huawei | B15: Internet, datos, voz, B2B, TV | C15: Income | D15: Gerencia de Transporte | E15: Wilmar Moreno | F15: 2023 | G15: Caldas | H15: Caldas | I15: Nor occidente | J15: Yes | K15: 1 | L15: 1 | M15: 483 | N15: 2400 | P15: DC | Q15: =M15*3.4121 -> 1648.0443 | R15: 2+2 | U15: 48 VDC | V15: 0,3 x 0,6 | Y15: 1 rack y equipo OSN1800V nuevo
A16: DWDM Huawei | B16: Internet, datos, voz, B2B, TV | C16: Income | D16: Gerencia de Transporte | E16: Wilmar Moreno | F16: 2023 | G16: Host-EDATEL | H16: Sincelejo | I16: Costa | J16: No | M16: 208.4 | P16: DC | Q16: =M16*3.4121 -> 711.08164 | U16: 48 VDC | Y16: Tarjetas en OSN1800VPro existente
A17: DWDM Huawei | B17: Internet, datos, voz, B2B, TV | C17: Income | D17: Gerencia de Transporte | E17: Wilmar Moreno | F17: 2023 | G17: Host-EDATEL | H17: Corozal | I17: Costa | J17: No | M17: 74 | P17: DC | Q17: =M17*3.4121 -> 252.4954 | U17: 48 VDC | Y17: Tarjetas en OSN1800VPro existente
A18: DWDM Huawei | B18: Internet, datos, voz, B2B, TV | C18: Income | D18: Gerencia de Transporte | E18: Wilmar Moreno | F18: 2023 | G18: Host-EDATEL | H18: Magangué | I18: Costa | J18: No | M18: 172 | P18: DC | Q18: =M18*3.4121 -> 586.8812 | U18: 48 VDC | Y18: Tarjetas en OSN1800VPro existente
A19: DWDM Huawei | B19: Internet, datos, voz, B2B, TV | C19: Income | D19: Gerencia de Transporte | E19: Wilmar Moreno | F19: 2023 | G19: BOL0065 | H19: Mompox | I19: Costa | J19: No | M19: 172 | P19: DC | Q19: =M19*3.4121 -> 586.8812 | U19: 48 VDC | Y19: Tarjetas en OSN1800VPro existente
A20: DWDM Huawei | B20: Internet, datos, voz, B2B, TV | C20: Income | D20: Gerencia de Transporte | E20: Wilmar Moreno | F20: 2023 | G20: MAG0102 | H20: El Banco | I20: Costa | J20: No | M20: 172 | P20: DC | Q20: =M20*3.4121 -> 586.8812 | U20: 48 VDC | Y20: Tarjetas en OSN1800VPro existente
A21: DWDM Huawei | B21: Internet, datos, voz, B2B, TV | C21: Income | D21: Gerencia de Transporte | E21: Wilmar Moreno | F21: 2023 | G21: Host-EDATEL | H21: La Pintada | I21: Nor occidente | J21: No | M21: 572 | P21: DC | Q21: =M21*3.4121 -> 1951.7212 | U21: 48 VDC | Y21: Tarjetas en OSN1800VPro existente
A22: DWDM Huawei | B22: Internet, datos, voz, B2B, TV | C22: Income | D22: Gerencia de Transporte | E22: Wilmar Moreno | F22: 2023 | G22: Host-EDATEL | H22: Valparaiso | I22: Nor occidente | J22: No | M22: 74 | P22: DC | Q22: =M22*3.4121 -> 252.4954 | U22: 48 VDC | Y22: Tarjetas en OSN1800VPro existente
A23: DWDM Huawei | B23: Internet, datos, voz, B2B, TV | C23: Income | D23: Gerencia de Transporte | E23: Wilmar Moreno | F23: 2023 | G23: Host-EDATEL | H23: Tamesis | I23: Nor occidente | J23: No | M23: 74 | P23: DC | Q23: =M23*3.4121 -> 252.4954 | U23: 48 VDC | Y23: Tarjetas en OSN1800VPro existente
A24: DWDM Huawei | B24: Internet, datos, voz, B2B, TV | C24: Income | D24: Gerencia de Transporte | E24: Wilmar Moreno | F24: 2023 | G24: Host-EDATEL | H24: Jericó | I24: Nor occidente | J24: No | M24: 74 | P24: DC | Q24: =M24*3.4121 -> 252.4954 | U24: 48 VDC | Y24: Tarjetas en OSN1800VPro existente
A25: DWDM Huawei | B25: Internet, datos, voz, B2B, TV | C25: Income | D25: Gerencia de Transporte | E25: Wilmar Moreno | F25: 2023 | G25: Host-EDATEL | H25: Jardin | I25: Nor occidente | J25: No | M25: 74 | P25: DC | Q25: =M25*3.4121 -> 252.4954 | U25: 48 VDC | Y25: Tarjetas en OSN1800VPro existente
A26: DWDM Huawei | B26: Internet, datos, voz, B2B, TV | C26: Income | D26: Gerencia de Transporte | E26: Wilmar Moreno | F26: 2023 | G26: Host-EDATEL | H26: Andes | I26: Nor occidente | J26: No | M26: 74 | P26: DC | Q26: =M26*3.4121 -> 252.4954 | U26: 48 VDC | Y26: Tarjetas en OSN1800VPro existente
A27: DWDM Huawei | B27: Internet, datos, voz, B2B, TV | C27: Income | D27: Gerencia de Transporte | E27: Wilmar Moreno | F27: 2023 | G27: Host-EDATEL | H27: Amaga | I27: Nor occidente | J27: No | M27: 508 | P27: DC | Q27: =M27*3.4121 -> 1733.3468 | U27: 48 VDC | Y27: Tarjetas en OSN1800VPro existente
... A51: DWDM Nokia | B51: Internet, datos, voz, B2B, TV | C51: Income | D51: Gerencia de Transporte | E51: Wilmar Moreno | F51: 2023 | G51: Vasquez Cobo | H51: Cali | I51: Sur occidente | J51: No | M51: 530 | P51: DC | Q51: =M51*3.4121 -> 1808.413 | U51: 48 VDC | Y51: Tarjetas en equipos PSS32/36/64 existentes

Sheet MPLS
A1: Platform or Equipment | B1: Associated Services to the platform | C1: Income / Dismount | D1: Responsable Technical Area | E1: Responsable Technician | F1: Year | G1: Technical Site | H1: City | I1: Regional | J1: Additional m2? Yes/No | K1: If Yes: # Racks? | L1: Quantity Equipment DC | M1: Average Power (W) | N1: Máx. Power DC (W) | O1: Potencia liberar | P1: Voltage (AC or DC) | Q1: Air DissipationBTU | R1: Power sources | S1: Quantity Equipment AC | T1: Máx. Power AC (W) | U1: Voltage (AC or DC) | V1: Requested Area (M2) | W1: Instalation date | X1: Prority | Y1: Comments
A2: MPLS | B2: MPLS | C2: INCOME | D2: Cloud IP/MPLS | E2: José Alejandro Arcila | F2: 2023 | G2: Miraflores | H2: Medellín | J2: no | K2: 0 | L2: 0 | M2: 400 | N2: 600 | P2: dc | Q2: 682 BTU/hour | Y2: Tarjeta 2*100
A3: MPLS | B3: MPLS | C3: INCOME | D3: Cloud IP/MPLS | E3: José Alejandro Arcila | F3: 2023 | G3: Apartadó | H3: Apartadó | J3: no | K3: 0 | L3: 0 | M3: 400 | N3: 600 | P3: dc | Q3: 682 BTU/hour | Y3: Tarjeta 2*100
A4: MPLS | B4: MPLS | C4: INCOME | D4: Cloud IP/MPLS | E4: José Alejandro Arcila | F4: 2023 | G4: Montería | H4: Montería | J4: no | K4: 0 | L4: 0 | M4: 400 | N4: 600 | P4: dc | Q4: 682 BTU/hour | Y4: Tarjeta 24*10
A5: MPLS | B5: MPLS | C5: INCOME | D5: Cloud IP/MPLS | E5: José Alejandro Arcila | F5: 2023 | G5: Centro ejecutivo | H5: Santa Martha | J5: no | K5: 0 | L5: 0 | M5: 400 | N5: 600 | P5: dc | Q5: 682 BTU/hour | Y5: Tarjeta 24*10
A6: MPLS | B6: MPLS | C6: INCOME | D6: Cloud IP/MPLS | E6: José Alejandro Arcila | F6: 2023 | G6: Bello | H6: Bello | J6: no | K6: 0 | L6: 0 | M6: 400 | N6: 600 | P6: dc | Q6: 682 BTU/hour | Y6: Tarjeta 2*100G
A7: MPLS | B7: MPLS | C7: INCOME | D7: Cloud IP/MPLS | E7: José Alejandro Arcila | F7: 2023 | G7: Engativá | H7: Bogotá | J7: no | K7: 0 | L7: 0 | M7: 400 | N7: 600 | P7: dc | Q7: 682 BTU/hour | Y7: Tarjeta 2*100G
A8: MPLS | B8: MPLS | C8: INCOME | D8: Cloud IP/MPLS | E8: José Alejandro Arcila | F8: 2023 | G8: Buenos aires | H8: Medellín | J8: no | K8: 0 | L8: 0 | M8: 400 | N8: 600 | P8: dc | Q8: 682 BTU/hour | Y8: Tarjeta 2*100G
A9: MPLS | B9: MPLS | C9: INCOME | D9: Cloud IP/MPLS | E9: José Alejandro Arcila | F9: 2023 | G9: Bosque | H9: Medellín | J9: no | K9: 0 | L9: 0 | M9: 400 | N9: 600 | P9: dc | Q9: 682 BTU/hour | Y9: Tarjeta 2*100G
A10: MPLS | B10: MPLS | C10: INCOME | D10: Cloud IP/MPLS | E10: José Alejandro Arcila | F10: 2023 | G10: Miraflores | H10: Medellín | J10: no | K10: 0 | L10: 0 | M10: 400 | N10: 600 | P10: dc | Q10: 682 BTU/hour | Y10: Tarjeta 2*100G
A11: MPLS | B11: MPLS | C11: INCOME | D11: Cloud IP/MPLS | E11: José Alejandro Arcila | F11: 2023 | G11: Sabaneta | H11: Medellín | J11: no | K11: 0 | L11: 0 | M11: 400 | N11: 600 | P11: dc | Q11: 682 BTU/hour | Y11: Tarjeta 2*100G
A12: MPLS | B12: MPLS | C12: INCOME | D12: Cloud IP/MPLS | E12: José Alejandro Arcila | F12: 2023 | G12: Colón | H12: Medellín | J12: no | K12: 0 | L12: 0 | M12: 400 | N12: 600 | P12: dc | Q12: 682 BTU/hour | Y12: Tarjeta 2*100G
A13: MPLS | B13: MPLS | C13: INCOME | D13: Cloud IP/MPLS | E13: José Alejandro Arcila | F13: 2023 | G13: Miraflores | H13: Medellín | J13: no | K13: 0 | L13: 0 | M13: 400 | N13: 600 | P13: dc | Q13: 682 BTU/hour | Y13: Tarjeta 2*100G
... A16: MPLS | B16: MPLS | C16: INCOME | D16: Cloud IP/MPLS | E16: José Alejandro Arcila | F16: 2023 | G16: Gama | H16: Pereira | J16: no | K16: 0 | L16: 0 | M16: 400 | N16: 600 | P16: dc | Q16: 682 BTU/hour | Y16: Tarjeta 2*100G
A17: MPLS | B17: MPLS | C17: INCOME | D17: Cloud IP/MPLS | E17: José Alejandro Arcila | F17: 2023 | G17: Castilla | H17: Medellín | J17: si | K17: 1 | L17: 0 | M17: 400 | N17: 600 | P17: dc | Q17: 992 BTU/hour | R17: 2 | Y17: Swiche DAAS
A18: MPLS | B18: MPLS | C18: INCOME | D18: Cloud IP/MPLS | E18: José Alejandro Arcila | F18: 2023 | G18: Florencia | H18: Medellín | J18: si | K18: 1 | L18: 0 | M18: 400 | N18: 600 | P18: dc | Q18: 992 BTU/hour | R18: 2 | Y18: Swiche DAAS
A19: MPLS | B19: MPLS | C19: INCOME | D19: Cloud IP/MPLS | E19: José Alejandro Arcila | F19: 2023 | G19: Copacabana | H19: Medellín | J19: si | K19: 1 | L19: 0 | M19: 400 | N19: 600 | P19: dc | Q19: 992 BTU/hour | R19: 2 | Y19: Swiche DAAS
A20: MPLS | B20: MPLS | C20: INCOME | D20: Cloud IP/MPLS | E20: José Alejandro Arcila | F20: 2023 | G20: Colón | H20: Medellín | J20: si | K20: 1 | L20: 0 | M20: 400 | N20: 600 | P20: dc | Q20: 992 BTU/hour | R20: 2 | Y20: Swiche DAAS
A21: MPLS | B21: MPLS | C21: INCOME | D21: Cloud IP/MPLS | E21: José Alejandro Arcila | F21: 2023 | G21: Estrella | H21: Medellín | J21: si | K21: 1 | L21: 0 | M21: 400 | N21: 600 | P21: dc | Q21: 992 BTU/hour | R21: 2 | Y21: Swiche DAAS
A22: MPLS | B22: MPLS | C22: INCOME | D22: Cloud IP/MPLS | E22: José Alejandro Arcila | F22: 2023 | G22: Otrabanda | H22: Medellín | J22: si | K22: 1 | L22: 0 | M22: 400 | N22: 600 | P22: dc | Q22: 992 BTU/hour | R22: 2 | Y22: Swiche DAAS
A23: MPLS | B23: MPLS | C23: INCOME | D23: Cloud IP/MPLS | E23: José Alejandro Arcila | F23: 2023 | G23: San Cristóbal | H23: Medellín | J23: si | K23: 1 | L23: 0 | M23: 400 | N23: 600 | P23: dc | Q23: 992 BTU/hour | R23: 2 | Y23: Swiche DAAS
A24: MPLS | B24: MPLS | C24: INCOME | D24: Cloud IP/MPLS | E24: José Alejandro Arcila | F24: 2023 | G24: Villa hermosa | H24: Medellín | J24: si | K24: 1 | L24: 0 | M24: 400 | N24: 600 | P24: dc | Q24: 992 BTU/hour | R24: 2 | Y24: Swiche DAAS
A25: MPLS | B25: MPLS | C25: INCOME | D25: Cloud IP/MPLS | E25: José Alejandro Arcila | F25: 2023 | G25: La ceja | H25: Medellín | J25: si | K25: 1 | L25: 0 | M25: 400 | N25: 600 | P25: dc | Q25: 992 BTU/hour | R25: 2 | Y25: Swiche DAAS
A26: MPLS | B26: MPLS | C26: INCOME | D26: Cloud IP/MPLS | E26: José Alejandro Arcila | F26: 2023 | G26: Girardota | H26: Medellín | J26: si | K26: 1 | L26: 0 | M26: 400 | N26: 600 | P26: dc | Q26: 992 BTU/hour | R26: 2 | Y26: Swiche DAAS
A27: MPLS | B27: MPLS | C27: INCOME | D27: Cloud IP/MPLS | E27: José Alejandro Arcila | F27: 2023 | G27: Nodo Nuevo | H27: Santa Marha | J27: si | K27: 1 | L27: 0 | M27: 400 | N27: 600 | P27: dc | Q27: 992 BTU/hour | R27: 2 | Y27: Swiche DAAS
A28: MPLS | B28: MPLS | C28: INCOME | D28: Cloud IP/MPLS | E28: José Alejandro Arcila | F28: 2023 | G28: La Paz | H28: Bogotá | J28: si | K28: 1 | L28: 0 | M28: 400 | N28: 600 | P28: dc | Q28: 992 BTU/hour | R28: 2 | Y28: Swiche DAAS
... A36: MPLS | B36: MPLS | C36: INCOME | D36: Cloud IP/MPLS | E36: José Alejandro Arcila | F36: 2023 | G36: Centro | H36: Manizales | J36: si | K36: 1 | L36: 0 | M36: 400 | N36: 600 | P36: dc | Q36: 992 BTU/hour | R36: 2 | Y36: Swiche DAAS
A37: MPLS | B37: MPLS | C37: INCOME | D37: Cloud IP/MPLS | E37: José Alejandro Arcila | F37: 2023 | G37: San Cristóbal | H37: Medellín | J37: no | K37: 0 | L37: 0 | M37: 400 | N37: 600 | P37: dc | Q37: 682 BTU/hour | Y37: Tarjeta 12*10G
A38: MPLS | B38: MPLS | C38: INCOME | D38: Cloud IP/MPLS | E38: José Alejandro Arcila | F38: 2023 | G38: Santa Helena | H38: Medellín | J38: no | K38: 0 | L38: 0 | M38: 400 | N38: 600 | P38: dc | Q38: 682 BTU/hour | Y38: Tarjeta 12*10G
A39: MPLS | B39: MPLS | C39: INCOME | D39: Cloud IP/MPLS | E39: José Alejandro Arcila | F39: 2023 | G39: La Fe | H39: Medellín | J39: no | K39: 0 | L39: 0 | M39: 400 | N39: 600 | P39: dc | Q39: 682 BTU/hour | Y39: Tarjeta 12*10G
A40: MPLS | B40: MPLS | C40: INCOME | D40: Cloud IP/MPLS | E40: José Alejandro Arcila | F40: 2023 | G40: San Francisco | H40: Bucaramanga | J40: no | K40: 0 | L40: 0 | M40: 400 | N40: 600 | P40: dc | Q40: 682 BTU/hour | Y40: Tarjeta 12*10G
A41: MPLS | B41: MPLS | C41: INCOME | D41: Cloud IP/MPLS | E41: José Alejandro Arcila | F41: 2023 | G41: Chinchiná | H41: Caldas | J41: no | K41: 0 | L41: 0 | M41: 400 | N41: 600 | P41: dc | Q41: 682 BTU/hour | Y41: Tarjeta 12*10G
A42: MPLS | B42: MPLS | C42: INCOME | D42: Cloud IP/MPLS | E42: José Alejandro Arcila | F42: 2023 | G42: Miraflores | H42: Medellín | J42: no | K42: 0 | L42: 0 | M42: 400 | N42: 600 | P42: dc | Q42: 682 BTU/hour | Y42: Tarjeta 12*10G
A43: MPLS | B43: MPLS | C43: INCOME | D43: Cloud IP/MPLS | E43: José Alejandro Arcila | F43: 2023 | G43: Engativá | H43: Bogotá | J43: no | K43: 0 | L43: 0 | M43: 400 | N43: 600 | P43: dc | Q43: 682 BTU/hour | Y43: Tarjeta 12*10G
A44: MPLS | B44: MPLS | C44: INCOME | D44: Cloud IP/MPLS | E44: José Alejandro Arcila | F44: 2023 | G44: Centro ejecutivo | H44: Santa marta | J44: no | K44: 0 | L44: 0 | M44: 400 | N44: 600 | P44: dc | Q44: 682 BTU/hour | Y44: Tarjeta 12*10G
A45: MPLS | B45: MPLS | C45: INCOME | D45: Cloud IP/MPLS | E45: José Alejandro Arcila | F45: 2023 | G45: Valledupar | H45: Valledupar | J45: no | K45: 0 | L45: 0 | M45: 400 | N45: 600 | P45: dc | Q45: 682 BTU/hour | Y45: Tarjeta 12*10G
A46: MPLS | B46: MPLS | C46: INCOME | D46: Cloud IP/MPLS | E46: José Alejandro Arcila | F46: 2023 | G46: Montería | H46: Montería | J46: no | K46: 0 | L46: 0 | M46: 400 | N46: 600 | P46: dc | Q46: 682 BTU/hour | Y46: Tarjeta 12*10G
A47: MPLS | B47: MPLS | C47: INCOME | D47: Cloud IP/MPLS | E47: José Alejandro Arcila | F47: 2023 | G47: Buenos aires | H47: Medellín | J47: no | K47: 0 | L47: 0 | M47: 400 | N47: 600 | P47: dc | Q47: 682 BTU/hour | Y47: Tarjeta 12*10G
A48: MPLS | B48: MPLS | C48: INCOME | D48: Cloud IP/MPLS | E48: José Alejandro Arcila | F48: 2023 | G48: Itagüí | H48: Medellín | J48: no | K48: 0 | L48: 0 | M48: 400 | N48: 600 | P48: dc | Q48: 682 BTU/hour | Y48: Tarjeta 12*10G
... A69: MPLS | B69: MPLS | C69: INCOME | D69: Cloud IP/MPLS | E69: José Alejandro Arcila | F69: 2023 | G69: Carrera | H69: Bogotá | J69: yes | K69: 2 | L69: 2 | M69: 3800 | N69: 4100 | P69: dc | Q69: 13290 BTU/hour | Y69: Router 7750
A70: MPLS | B70: MPLS | C70: Dismount | D70: Cloud IP/MPLS | E70: José Alejandro Arcila | F70: 2023 | G70: Carrera | H70: Bogotá | J70: no | L70: 2 | M70: 1500 | N70: 2000 | P70: dc | Q70: 7000 BTU/hour | Y70: DEsmonte Sw9303
A71: MPLS | B71: MPLS | C71: INCOME | D71: Cloud IP/MPLS | E71: José Alejandro Arcila | F71: 2023 | G71: BCC | H71: Bogotá | J71: yes | K71: 2 | L71: 2 | M71: 3800 | N71: 4100 | P71: dc | Q71: 13290 BTU/hour | Y71: Router 7750
A72: MPLS | B72: MPLS | C72: Dismount | D72: Cloud IP/MPLS | E72: José Alejandro Arcila | F72: 2023 | G72: BCC | H72: Bogotá | J72: no | L72: 2 | M72: 1500 | N72: 2000 | P72: dc | Q72: 7000 BTU/hour | Y72: DEsmonte Sw9303
A73: MPLS | B73: MPLS | C73: INCOME | D73: Cloud IP/MPLS | E73: José Alejandro Arcila | F73: 2023 | G73: Dorado | H73: Bogotá | J73: yes | K73: 2 | L73: 2 | M73: 3800 | N73: 4100 | P73: dc | Q73: 13290 BTU/hour | Y73: Router 7750
A74: MPLS | B74: MPLS | C74: Dismount | D74: Cloud IP/MPLS | E74: José Alejandro Arcila | F74: 2023 | G74: Dorado | H74: Bogotá | J74: no | L74: 2 | M74: 1500 | N74: 2000 | P74: dc | Q74: 7000 BTU/hour | Y74: DEsmonte Sw9303
A75: MPLS | B75: MPLS | C75: INCOME | D75: Cloud IP/MPLS | E75: José Alejandro Arcila | F75: 2023 | G75: Atlas | H75: Bogotá | J75: yes | K75: 2 | L75: 2 | M75: 3800 | N75: 4100 | P75: dc | Q75: 13290 BTU/hour | Y75: Router 7750
A76: MPLS | B76: MPLS | C76: Dismount | D76: Cloud IP/MPLS | E76: José Alejandro Arcila | F76: 2023 | G76: Atlas | H76: Bogotá | J76: no | L76: 2 | M76: 1500 | N76: 2000 | P76: dc | Q76: 7000 BTU/hour | Y76: DEsmonte Sw9303
A77: MPLS | B77: MPLS | C77: INCOME | D77: Cloud IP/MPLS | E77: José Alejandro Arcila | F77: 2023 | G77: Valladolid | H77: Bogotá | J77: yes | K77: 2 | L77: 2 | M77: 3800 | N77: 4100 | P77: dc | Q77: 13290 BTU/hour | Y77: Router 7750
A78: MPLS | B78: MPLS | C78: Dismount | D78: Cloud IP/MPLS | E78: José Alejandro Arcila | F78: 2023 | G78: Valladolid | H78: Bogotá | J78: no | L78: 2 | M78: 3300 | N78: 4100 | P78: dc | Q78: 13290 BTU/hour | Y78: DEsmonte Ne40E obsoleto
A79: MPLS | B79: MPLS | C79: INCOME | D79: Cloud IP/MPLS | E79: José Alejandro Arcila | F79: 2023 | G79: Castellana | H79: Bogotá | J79: no | K79: 0 | L79: 0 | M79: 400 | N79: 600 | P79: dc | Q79: 682 BTU/hour | Y79: Tarjeta 12*10G
A80: MPLS | B80: MPLS | C80: INCOME | D80: Cloud IP/MPLS | E80: José Alejandro Arcila | F80: 2023 | G80: Guane | H80: Bogotá | J80: no | K80: 0 | L80: 0 | M80: 400 | N80: 600 | P80: dc | Q80: 682 BTU/hour | Y80: Tarjeta 12*10G
A81: MPLS | B81: MPLS | C81: INCOME | D81: Cloud IP/MPLS | E81: José Alejandro Arcila | F81: 2023 | G81: La estrada | H81: Bogotá | J81: yes | K81: 2 | L81: 2 | M81: 3800 | N81: 4100 | P81: dc | Q81: 13290 BTU/hour | Y81: Router 7750
A82: MPLS | B82: MPLS | C82: Dismount | D82: Cloud IP/MPLS | E82: José Alejandro Arcila | F82: 2023 | G82: La estrada | H82: Bogotá | J82: no | L82: 2 | M82: 1500 | N82: 2000 | P82: dc | Q82: 7000 BTU/hour | Y82: DEsmonte Sw9303
A83: MPLS | B83: MPLS | C83: INCOME | D83: Cloud IP/MPLS | E83: José Alejandro Arcila | F83: 2023 | G83: Quinta Camacho | H83: Bogotá | J83: no | K83: 0 | L83: 0 | M83: 400 | N83: 600 | P83: dc | Q83: 682 BTU/hour | Y83: Tarjeta 12*10G
A84: MPLS | B84: MPLS | C84: INCOME | D84: Cloud IP/MPLS | E84: José Alejandro Arcila | F84: 2023 | G84: Engativá | H84: Bogotá | J84: no | K84: 0 | L84: 0 | M84: 400 | N84: 600 | P84: dc | Q84: 682 BTU/hour | Y84: Tarjeta 12*10G
A85: MPLS | B85: MPLS | C85: INCOME | D85: Cloud IP/MPLS | E85: José Alejandro Arcila | F85: 2023 | G85: Suba | H85: Bogotá | J85: no | K85: 0 | L85: 0 | M85: 400 | N85: 600 | P85: dc | Q85: 682 BTU/hour | Y85: Tarjeta 12*10G
A86: MPLS | B86: MPLS | C86: INCOME | D86: Cloud IP/MPLS | E86: José Alejandro Arcila | F86: 2023 | G86: Centro | H86: Bogotá | J86: no | K86: 0 | L86: 0 | M86: 400 | N86: 600 | P86: dc | Q86: 682 BTU/hour | Y86: Tarjeta 12*10G
A87: MPLS | B87: MPLS | C87: INCOME | D87: Cloud IP/MPLS | E87: José Alejandro Arcila | F87: 2023 | G87: La fragua | H87: Bogotá | J87: no | K87: 0 | L87: 0 | M87: 400 | N87: 600 | P87: dc | Q87: 682 BTU/hour | Y87: Tarjeta 12*10G
A88: MPLS | B88: MPLS | C88: INCOME | D88: Cloud IP/MPLS | E88: José Alejandro Arcila | F88: 2023 | G88: Montevideo | H88: Bogotá | J88: no | K88: 0 | L88: 0 | M88: 400 | N88: 600 | P88: dc | Q88: 682 BTU/hour | Y88: Tarjeta 12*10G
A89: MPLS | B89: MPLS | C89: INCOME | D89: Cloud IP/MPLS | E89: José Alejandro Arcila | F89: 2023 | G89: Fontanar | H89: Bogotá | J89: no | K89: 0 | L89: 0 | M89: 400 | N89: 600 | P89: dc | Q89: 682 BTU/hour | Y89: Tarjeta 12*10G
A90: MPLS | B90: MPLS | C90: INCOME | D90: Cloud IP/MPLS | E90: José Alejandro Arcila | F90: 2023 | G90: WTC (World Trade Center) | H90: Bogotá | J90: yes | K90: 2 | L90: 2 | M90: 3800 | N90: 4100 | P90: dc | Q90: 13290 BTU/hour | Y90: Router 7750
A91: MPLS | B91: MPLS | C91: Dismount | D91: Cloud IP/MPLS | E91: José Alejandro Arcila | F91: 2023 | G91: WTC (World Trade Center) | H91: Bogotá | J91: no | L91: 2 | M91: 3300 | N91: 4100 | P91: dc | Q91: 13290 BTU/hour | Y91: DEsmonte Ne40E obsoleto
A92: MPLS | B92: MPLS | C92: INCOME | D92: Cloud IP/MPLS | E92: José Alejandro Arcila | F92: 2023 | G92: Timiza | H92: Bogotá | J92: no | K92: 0 | L92: 0 | M92: 400 | N92: 600 | P92: dc | Q92: 682 BTU/hour | Y92: Tarjeta 12*10G
A93: MPLS | B93: MPLS | C93: INCOME | D93: Cloud IP/MPLS | E93: José Alejandro Arcila | F93: 2023 | G93: Santa Bibiana | H93: Bogotá | J93: no | K93: 0 | L93: 0 | M93: 400 | N93: 600 | P93: dc | Q93: 682 BTU/hour | Y93: Tarjeta 12*10G
A94: MPLS | B94: MPLS | C94: INCOME | D94: Cloud IP/MPLS | E94: José Alejandro Arcila | F94: 2023 | G94: CAN | H94: Bogotá | J94: no | K94: 0 | L94: 0 | M94: 400 | N94: 600 | P94: dc | Q94: 682 BTU/hour | Y94: Tarjeta 12*10G
A95: MPLS | B95: MPLS | C95: INCOME | D95: Cloud IP/MPLS | E95: José Alejandro Arcila | F95: 2023 | G95: La Paz | H95: Bogotá | J95: no | K95: 0 | L95: 0 | M95: 400 | N95: 600 | P95: dc | Q95: 682 BTU/hour | Y95: Tarjeta 12*10G
A96: MPLS | B96: MPLS | C96: INCOME | D96: Cloud IP/MPLS | E96: José Alejandro Arcila | F96: 2023 | G96: Visión Colombia | H96: Bogotá | J96: no | K96: 0 | L96: 0 | M96: 400 | N96: 600 | P96: dc | Q96: 682 BTU/hour | Y96: Tarjeta 12*10G
A97: MPLS | B97: MPLS | C97: INCOME | D97: Cloud IP/MPLS | E97: José Alejandro Arcila | F97: 2023 | G97: El Carmen | H97: Bogotá | J97: no | K97: 0 | L97: 0 | M97: 400 | N97: 600 | P97: dc | Q97: 682 BTU/hour | Y97: Tarjeta 12*10G
A98: MPLS | B98: MPLS | C98: INCOME | D98: Cloud IP/MPLS | E98: José Alejandro Arcila | F98: 2023 | G98: Cantalejo | H98: Bogotá | J98: no | K98: 0 | L98: 0 | M98: 400 | N98: 600 | P98: dc | Q98: 682 BTU/hour | Y98: Tarjeta 12*10G
A99: MPLS | B99: MPLS | C99: INCOME | D99: Cloud IP/MPLS | E99: José Alejandro Arcila | F99: 2023 | G99: Envigado | H99: Medellín | J99: no | K99: 0 | L99: 0 | M99: 400 | N99: 600 | P99: dc | Q99: 682 BTU/hour | Y99: Tarjeta 12*10G
A100: MPLS | B100: MPLS | C100: INCOME | D100: Cloud IP/MPLS | E100: José Alejandro Arcila | F100: 2023 | G100: Buenos aires | H100: Medellín | J100: no | K100: 0 | L100: 0 | M100: 400 | N100: 600 | P100: dc | Q100: 682 BTU/hour | Y100: Tarjeta 12*10G
A101: MPLS | B101: MPLS | C101: INCOME | D101: Cloud IP/MPLS | E101: José Alejandro Arcila | F101: 2023 | G101: Bosque | H101: Medellín | J101: no | K101: 0 | L101: 0 | M101: 400 | N101: 600 | P101: dc | Q101: 682 BTU/hour | Y101: Tarjeta 12*10G
A102: MPLS | B102: MPLS | C102: INCOME | D102: Cloud IP/MPLS | E102: José Alejandro Arcila | F102: 2023 | G102: Castilla | H102: Medellín | J102: no | K102: 0 | L102: 0 | M102: 400 | N102: 600 | P102: dc | Q102: 682 BTU/hour | Y102: Tarjeta 12*10G
A103: MPLS | B103: MPLS | C103: INCOME | D103: Cloud IP/MPLS | E103: José Alejandro Arcila | F103: 2023 | G103: Centro | H103: Medellín | J103: no | K103: 0 | L103: 0 | M103: 400 | N103: 600 | P103: dc | Q103: 682 BTU/hour | Y103: Tarjeta 12*10G
... A125: MPLS | B125: MPLS | C125: INCOME | D125: Cloud IP/MPLS | E125: José Alejandro Arcila | F125: 2023 | G125: Puerto berrío | H125: Puerto berrío | J125: yes | K125: 2 | L125: 2 | M125: 3800 | N125: 4100 | P125: dc | Q125: 13290 BTU/hour | Y125: Router smalla
A126: MPLS | B126: MPLS | C126: Dismount | D126: Cloud IP/MPLS | E126: José Alejandro Arcila | F126: 2023 | G126: Puerto berrío | H126: Puerto berrío | J126: no | L126: 2 | M126: 1500 | N126: 2000 | P126: dc | Q126: 7000 BTU/hour | Y126: DEsmonte Ne40 X1
A127: MPLS | B127: MPLS | C127: INCOME | D127: Cloud IP/MPLS | E127: José Alejandro Arcila | F127: 2023 | G127: Santafé de antioquia | H127: Santafé de antioquia | J127: yes | K127: 2 | L127: 2 | M127: 3800 | N127: 4100 | P127: dc | Q127: 13290 BTU/hour | Y127: Router smalla
A128: MPLS | B128: MPLS | C128: Dismount | D128: Cloud IP/MPLS | E128: José Alejandro Arcila | F128: 2023 | G128: Santafé de antioquia | H128: Santafé de antioquia | J128: no | L128: 2 | M128: 1500 | N128: 2000 | P128: dc | Q128: 7000 BTU/hour | Y128: DEsmonte Ne40 X3
A129: MPLS | B129: MPLS | C129: INCOME | D129: Cloud IP/MPLS | E129: José Alejandro Arcila | F129: 2023 | G129: Anillo vial | H129: Bucaramanga | J129: no | K129: 0 | L129: 0 | M129: 400 | N129: 600 | P129: dc | Q129: 682 BTU/hour | Y129: 24*10G
A130: MPLS | B130: MPLS | C130: INCOME | D130: Cloud IP/MPLS | E130: José Alejandro Arcila | F130: 2023 | G130: Girón | H130: Bucaramanga | J130: no | K130: 0 | L130: 0 | M130: 400 | N130: 600 | P130: dc | Q130: 682 BTU/hour | Y130: tarjetas 48*1
A131: MPLS | B131: MPLS | C131: INCOME | D131: Cloud IP/MPLS | E131: José Alejandro Arcila | F131: 2023 | G131: CAN | H131: Bogotá | J131: no | K131: 0 | L131: 0 | M131: 400 | N131: 600 | P131: dc | Q131: 682 BTU/hour | Y131: 24*10G
A132: MPLS | B132: MPLS | C132: INCOME | D132: Cloud IP/MPLS | E132: José Alejandro Arcila | F132: 2023 | G132: Dorado | H132: Bogotá | J132: no | K132: 0 | L132: 0 | M132: 400 | N132: 600 | P132: dc | Q132: 682 BTU/hour | Y132: tarjetas 48*1
A133: MPLS | B133: MPLS | C133: INCOME | D133: Cloud IP/MPLS | E133: José Alejandro Arcila | F133: 2023 | G133: Fusa | H133: Bogotá | J133: no | K133: 0 | L133: 0 | M133: 400 | N133: 600 | P133: dc | Q133: 682 BTU/hour | Y133: tarjetas 48*1
A134: MPLS | B134: MPLS | C134: INCOME | D134: Cloud IP/MPLS | E134: José Alejandro Arcila | F134: 2023 | G134: Santa Bibiana | H134: Bogotá | J134: no | K134: 0 | L134: 0 | M134: 400 | N134: 600 | P134: dc | Q134: 682 BTU/hour | Y134: tarjetas 48*1
A135: MPLS | B135: MPLS | C135: INCOME | D135: Cloud IP/MPLS | E135: José Alejandro Arcila | F135: 2023 | G135: Santa bibiana | H135: Bogotá | J135: no | K135: 0 | L135: 0 | M135: 400 | N135: 600 | P135: dc | Q135: 682 BTU/hour | Y135: tarjetas 48*1
A136: MPLS | B136: MPLS | C136: INCOME | D136: Cloud IP/MPLS | E136: José Alejandro Arcila | F136: 2023 | G136: Vásquez Cobo | H136: Cali | J136: no | K136: 0 | L136: 0 | M136: 400 | N136: 600 | P136: dc | Q136: 682 BTU/hour | Y136: 24*10G Para 1G se esta montando e SW 12700
A137: MPLS | B137: MPLS | C137: INCOME | D137: Cloud IP/MPLS | E137: José Alejandro Arcila | F137: 2023 | G137: Bosque | H137: Cartagena | J137: no | K137: 0 | L137: 0 | M137: 400 | N137: 600 | P137: dc | Q137: 682 BTU/hour | Y137: Se crece en el X16A para 10 G Tarjeta de 48*1G
A138: MPLS | B138: MPLS | C138: INCOME | D138: Cloud IP/MPLS | E138: José Alejandro Arcila | F138: 2023 | G138: Zaragocilla | H138: Cartagena | J138: no | K138: 0 | L138: 0 | M138: 400 | N138: 600 | P138: dc | Q138: 682 BTU/hour | Y138: 24*10G
A139: MPLS | B139: MPLS | C139: INCOME | D139: Cloud IP/MPLS | E139: José Alejandro Arcila | F139: 2023 | G139: La Flor | H139: Sincelejo | J139: no | K139: 0 | L139: 0 | M139: 400 | N139: 600 | P139: dc | Q139: 682 BTU/hour | Y139: tarjetas 48*1
A140: MPLS | B140: MPLS | C140: INCOME | D140: Cloud IP/MPLS | E140: José Alejandro Arcila | F140: 2023 | G140: Apartadó | H140: Apartadó | J140: no | K140: 0 | L140: 0 | M140: 400 | N140: 600 | P140: dc | Q140: 682 BTU/hour | Y140: 24*10G + tarjeta 48*1G
... A195: MPLS | B195: MPLS | C195: INCOME | D195: Cloud IP/MPLS | E195: José Alejandro Arcila | F195: 2023 | G195: Prados del Norte | H195: Popayán | J195: no | K195: 0 | L195: 0 | M195: 400 | N195: 600 | P195: dc | Q195: 682 BTU/hour | Y195: 2*Tarjeta de 10*10G

Sheet IAP
A1: Platform or Equipment | B1: Associated Services to the platform | C1: Income / Dismount | D1: Responsable Technical Area | E1: Responsable Technician | F1: Year | G1: Technical Site | H1: City | I1: Regional | J1: Additional m2? Yes/No | K1: If Yes: # Racks? | L1: Quantity Equipment DC | M1: Average Power (W) | N1: Máx. Power DC (W) | O1: Potencia liberar | P1: Voltage (AC or DC) | Q1: Air DissipationBTU | R1: Power sources | S1: Quantity Equipment AC | T1: Máx. Power AC (W) | U1: Voltage (AC or DC) | V1: Requested Area (M2) | W1: Instalation date | X1: Prority | Y1: Comments
A2: IAP | B2: Internet, datos, voz, B2B, TV | C2: Income | D2: Gerencia Cloud, IP y DC | E2: Sandra Prieto | F2: 2023 | G2: Montevideo | H2: Bogotá | J2: Yes | K2: 1 | M2: 6802.5 | N2: 9070 | P2: DC | Q2: 23210.81 | R2: 2 | T2: 48 VDC | U2: DC | W2: 45078 | Y2: 1 rack y equipo MX10k8 nuevo (PDU en rack 26kw)
A3: IAP | B3: Internet, datos, voz, B2B, TV | C3: Income | D3: Gerencia Cloud, IP y DC | E3: Sandra Prieto | F3: 2023 | G3: Miraflores | H3: Medellín | J3: No | M3: 1327.5 | N3: 1770 | P3: DC | Q3: 4529.56 | T3: 48 VDC | U3: DC | W3: 45078 | Y3: Tarjetas en router MX960/10k8 existente
A4: IAP | B4: Internet, datos, voz, B2B, TV | C4: Income | D4: Gerencia Cloud, IP y DC | E4: Sandra Prieto | F4: 2023 | G4: Bosque | H4: Cartagena | J4: No | M4: 1327.5 | N4: 1770 | P4: DC | Q4: 4529.56 | T4: 48 VDC | U4: DC | W4: 45078 | Y4: Tarjetas en router MX960/10k8 existente
A5: IAP | B5: Internet, datos, voz, B2B, TV | C5: Income | D5: Gerencia Cloud, IP y DC | E5: Sandra Prieto | F5: 2023 | G5: Anillo Vial | H5: Bucaramanga | J5: No | M5: 1177.5 | N5: 1570 | P5: DC | Q5: 4017.75 | T5: 48 VDC | U5: DC | W5: 45078 | Y5: Tarjetas en router MX960/10k8 existente
A6: IAP | B6: Internet, datos, voz, B2B, TV | C6: Income | D6: Gerencia Cloud, IP y DC | E6: Sandra Prieto | F6: 2023 | G6: Centro | H6: Manizales | J6: No | M6: 1177.5 | N6: 1570 | P6: DC | Q6: 4017.75 | T6: 48 VDC | U6: DC | W6: 45078 | Y6: Tarjetas en router MX960/10k8 existente
A7: IAP | B7: Internet, datos, voz, B2B, TV | C7: Income | D7: Gerencia Cloud, IP y DC | E7: Sandra Prieto | F7: 2023 | G7: Alamos | H7: Pereira | J7: No | M7: 1177.5 | N7: 1570 | P7: DC | Q7: 4017.75 | T7: 48 VDC | U7: DC | W7: 45078 | Y7: Tarjetas en router MX960/10k8 existente
A8: IAP | B8: Internet, datos, voz, B2B, TV | C8: Income | D8: Gerencia Cloud, IP y DC | E8: Sandra Prieto | F8: 2023 | G8: Centro | H8: Pereira | J8: No | M8: 1177.5 | N8: 1570 | P8: DC | Q8: 4017.75 | T8: 48 VDC | U8: DC | W8: 45078 | Y8: Tarjetas en router MX960/10k8 existente
A9: IAP | B9: Internet, datos, voz, B2B, TV | C9: Income | D9: Gerencia Cloud, IP y DC | E9: Sandra Prieto | F9: 2023 | G9: Vasquez Cobo | H9: Cali | J9: No | M9: 2355 | N9: 3140 | P9: DC | Q9: 8035.5 | T9: 48 VDC | U9: DC | W9: 45078 | Y9: Tarjetas en router MX960/10k8 existente
A10: IAP | B10: Internet | C10: INCOME | D10: Cloud IP Data Center | E10: Alex Orrego | F10: 2023 | G10: Bosque | H10: Cartagena | J10: yes | K10: 1 | M10: 4500 | N10: 5000 | P10: DC | Q10: 24000 | R10: 2 | T10: 48 VDC | U10: DC | W10: 45078 | Y10: CDNs
A11: IAP | B11: Internet | C11: INCOME | D11: Cloud IP Data Center | E11: Alex Orrego | F11: 2023 | G11: Host | H11: Monteria | J11: yes | K11: 1 | M11: 4500 | N11: 5000 | P11: DC | Q11: 24000 | R11: 2 | T11: 48 VDC | U11: DC | W11: 45078 | Y11: CDNs
A12: IAP | B12: Internet | C12: INCOME | D12: Cloud IP Data Center | E12: Alex Orrego | F12: 2023 | G12: Vasquez cobo | H12: Cali | J12: yes | K12: 1 | M12: 4500 | N12: 5000 | P12: DC | Q12: 24000 | R12: 2 | T12: 48 VDC | U12: DC | W12: 45078 | Y12: CDNs
A13: IAP | B13: Internet | C13: INCOME | D13: Cloud IP Data Center | E13: Alex Orrego | F13: 2023 | G13: Anillo vial | H13: Bucaramanga | J13: yes | K13: 1 | M13: 4500 | N13: 5000 | P13: DC | Q13: 24000 | R13: 2 | T13: 48 VDC | U13: DC | W13: 45078 | Y13: CDNs
A14: IAP | B14: Internet | C14: INCOME | D14: Cloud IP Data Center | E14: Alex Orrego | F14: 2023 | G14: Centro | H14: Manizales | J14: yes | K14: 1 | M14: 4500 | N14: 5000 | P14: DC | Q14: 24000 | R14: 2 | T14: 48 VDC | U14: DC | W14: 45078 | Y14: CDNs
A15: IAP | B15: Internet | C15: INCOME | D15: Cloud IP Data Center | E15: Alex Orrego | F15: 2023 | G15: Centro | H15: Pereira | J15: yes | K15: 1 | M15: 4500 | N15: 5000 | P15: DC | Q15: 33600 | R15: 2 | T15: 48 VDC | U15: DC | W15: 45078 | Y15: CDNs
A16: IAP | B16: Internet | C16: INCOME | D16: Cloud IP Data Center | E16: Alex Orrego | F16: 2023 | G16: Alamos | H16: Pereira | J16: yes | K16: 1 | M16: 4500 | N16: 5000 | P16: DC | Q16: 33600 | R16: 2 | T16: 48 VDC | U16: DC | W16: 45078 | Y16: CDNs

Sheet Hoja2
A1: Equipment | B1: Income / Dismount | C1: Technical Site | D1: Additional m2? Yes/No | E1: If Yes: # Racks? | F1: Tipo de racks | G1: Quantity Equipment DC | H1: Average Power (W) | I1: Máx. Power DC (W) | J1: Es ampliación de tarjeta en equipo existente? | K1: Potencia a liberar | L1: Sitio y equipo con el que se libero la potencia | M1: Voltage (AC or DC) | N1: Air DissipationBTU | O1: Power sources | P1: PRE-Factibilidad Infraestructura (Si / No)

Sheet BU FACILITIES
D1: TRM | G1: 4100
A3: Descripción | B3: Capacidad | C3: Cantidad | D3: Valor Suministro | E3: Valor Inst | F3: Valor acometidas | G3: Valor Total
A4: Rectificador | B4: 300 | C4: 1 | D4: 6132 | E4: 352.43902 | F4: 4878.0488 | G4: 11362.488 | AS4: =IF(AR4=300,AQ4*'BU FACILITIES'!$G$4, IF(AND(AR4>=300,AR4<500), AQ4*#REF!, IF(AND(AR4>=500,AR4<1250), AQ4*#REF!, IF(AND(AR4>=1250,AR4<2000),AQ4*#REF!, IF(AR4>=2000,AQ4*#REF!, "")))))
A5: Rectificador | B5: 500 | C5: 1 | D5: 7227 | E5: 352.43902 | F5: 4878.0488 | G5: 12457.488
A6: Rectificador | B6: 1250 | C6: 1 | D6: 13352 | E6: 352.43902 | F6: 4878.0488 | G6: 18582.488
A7: Rectificador | B7: 2000 | C7: 1 | D7: 18632 | E7: 352.43902 | F7: 4878.0488 | G7: 23862.488
A8: Baterías | B8: 100 | C8: 1 | D8: 1230 | E8: 975.60976 | F8: 121.95122 | G8: 2327.561
A9: Baterías | B9: 500 | C9: 1 | D9: 4517.1487 | E9: 975.60976 | F9: 3658.5366 | G9: 9151.2951
A10: Baterías | B10: 800 | C10: 1 | D10: 10064.295 | E10: 975.60976 | F10: 3658.5366 | G10: 14698.441
A11: Baterías | B11: 1000 | C11: 1 | D11: 8197.7641 | E11: 975.60976 | F11: 3658.5366 | G11: 12831.91
A12: Baterías | B12: 1400 | C12: 1 | D12: 18807.5 | E12: 975.60976 | F12: 3658.5366 | G12: 23441.646
A13: Baterías | B13: 2000 | C13: 1 | D13: 16817.86 | E13: 975.60976 | F13: 3658.5366 | G13: 21452.006
A14: Motogenerador | B14: 45 | C14: 1 | D14: 8806 | E14: 9756.0976 | F14: 0 | G14: 18562.098
A15: Motogenerador | B15: 30 | C15: 1 | D15: 8020 | E15: 9756.0976 | F15: 0 | G15: 17776.098
A16: Motogenerador | B16: 450 | C16: 1 | G16: 75800.829
A17: Equipos de AA | B17: 5 | C17: 1 | D17: 5400 | E17: 8126.8293 | F17: 0 | G17: 13526.829
A18: Equipos de AA | B18: 10 | C18: 1 | D18: 6400 | E18: 8126.8293 | F18: 0 | G18: 14526.829
A19: Equipos de AA | B19: 20 | C19: 1 | D19: 14500 | E19: 8126.8293 | F19: 0 | G19: 22626.829
A20: Rediseño ductos de AA | C20: 1 | D20: 9756.0976 | E20: 0 | F20: 0 | G20: 9756.0976
A21: Tablero PDB | C21: 1 | D21: 1714.6341 | F21: 0 | G21: =+F21+D21 -> 1714.6341
A22: Energización equipos | C22: 1 | D22: 870.73171 | G22: 870.73171
A23: Obra civil | C23: 1 | D23: 24390.244 | G23: 24390.244
A24: Obra electrica complementaria | C24: 1 | D24: 9756.0976 | G24: 9756.0976
D25: TOTAL | G25: =SUM(G4:G24) -> 359475.13

Sheet Prefactibilidad negativa
A1: Platform or Equipment | B1: Associated Services to the platform | C1: Income / Dismount | D1: Responsable Technical Area | E1: Responsable Technician | F1: Year | G1: Technical Site | H1: City | I1: Regional | J1: Additional m2? Yes/No | K1: If Yes: # Racks? | L1: Quantity Equipment DC | M1: Average Power (W) | N1: Máx. Power DC (W) | O1: Potencia liberar | P1: Sumatoria W | Q1: %Potencia | R1: Valor por porcentaje de potencia | S1: Voltage (AC or DC) | T1: Air DissipationBTU | U1: Power sources | V1: Quantity Equipment AC | W1: Máx. Power AC (W) | X1: Voltage (AC or DC) | Y1: Requested Area (M2) | Z1: Instalation date | AA1: Prority | AB1: Comments | AC1: OBSERVACIÓN GERENCIA INFRAESTRUCTURA | AD1: tipo de NODO | AE1: PRE-Factibilidad Infraestructura (Si / No)
A2: Plataforma OLT Equipo Nuevo | B2: BBI-TV-TOIP | C2: Income | D2: Gerencia Acceso Fijo | E2: Henry Campos | F2: 2023 | G2: Jamundi | H2: Jamundí | J2: Yes | K2: 2 | L2: 1 | M2: 842 | N2: 1403 | P2: =SUMIF($G$3:$G$360,G2,$N$3:$N$360) -> 4209 | Q2: =N2/P2 -> 0.33333333 | R2: =VLOOKUP(G2,#REF!,11,0)*Q2 -> #REF! | S2: DC | U2: 2 | V2: 0 | W2: 0 | X2: DC | Y2: 3 | Z2: Q2 | AC2: El sitio no cuenta con espacio, ni AA ni rectificador para soportar la carga, debe construirse un sitio nuevo ya que el actual no tiene forma de expandirse. Se revisó sitios propios en Jamundí para revisar posibilidad de instalar OLT intemperie y el sitio que más se ajusta a las necesiddes de la zona requiere adecuaciones por aproximadamente 45 millones para volverlo confiable para la instalación de una OLT intemperie. | AD2: 5 | AE2: NO
A3: Plataforma OLT Equipo Nuevo | B3: BBI-TV-TOIP | C3: Income | D3: Gerencia Acceso Fijo | E3: Henry Campos | F3: 2023 | G3: Nuevo Nodo (Reemplzao ECE) | H3: Santa Marta | J3: Yes | K3: 2 | L3: 1 | M3: 842 | N3: 1403 | P3: =SUMIF($G$3:$G$360,G3,$N$3:$N$360) -> 7340 | Q3: =N3/P3 -> 0.19114441 | R3: =VLOOKUP(G3,#REF!,11,0)*Q3 -> #REF! | S3: DC | U3: 2 | V3: 0 | W3: 0 | X3: DC | Y3: 3 | Z3: Q2 | AB3: OLT nueva | AC3: Sitio por conseguir | AE3: NO
A4: Plataforma OLT Equipo Nuevo | B4: BBI-TV-TOIP | C4: Income | D4: Gerencia Acceso Fijo | E4: Henry Campos | F4: 2023 | G4: Chinchiná | H4: Chinchiná | J4: Yes | K4: 2 | L4: 1 | M4: 842 | N4: 1403 | P4: =SUMIF($G$3:$G$360,G4,$N$3:$N$360) -> 2806 | Q4: =N4/P4 -> 0.5 | R4: =VLOOKUP(G4,#REF!,11,0)*Q4 -> #REF! | S4: DC | U4: 2 | V4: 0 | W4: 0 | X4: DC | Y4: 3 | Z4: Q3 | AB4: OLT nueva | AC4: Sitio sin espacio, requiere obra civil. (35 millones aprox). Se debe negociar con la estación de Policia. | AD4: Urbano | AE4: No
A5: Plataforma OLT Equipo Nuevo | B5: BBI-TV-TOIP | C5: Income | D5: Gerencia Acceso Fijo | E5: Henry Campos | F5: 2023 | G5: Puerto Colombia | H5: Puerto Colombia | J5: Yes | K5: 2 | L5: 1 | M5: 842 | N5: 1403 | P5: =SUMIF($G$3:$G$360,G5,$N$3:$N$360) -> 2806 | Q5: =N5/P5 -> 0.5 | R5: =VLOOKUP(G5,#REF!,11,0)*Q5 -> #REF! | S5: DC | U5: 2 | V5: 0 | W5: 0 | X5: DC | Y5: 3 | Z5: Q3 | AB5: OLT nueva | AC5: Se buscará mejor sitio por seguridad, sitios movil han sido vandalizados | AE5: NO
A6: Plataforma OLT Equipo Nuevo | B6: BBI-TV-TOIP | C6: Income | D6: Gerencia Acceso Fijo | E6: Henry Campos | F6: 2023 | G6: Jamundi | H6: Jamundí | J6: Yes | K6: 2 | L6: 1 | M6: 842 | N6: 1403 | P6: =SUMIF($G$3:$G$360,G6,$N$3:$N$360) -> 4209 | Q6: =N6/P6 -> 0.33333333 | R6: =VLOOKUP(G6,#REF!,11,0)*Q6 -> #REF! | S6: DC | U6: 2 | V6: 0 | W6: 0 | X6: DC | Y6: 3 | Z6: Q2 | AB6: OLT nueva | AC6: No se tiene esapcio ni capacidad en rectificadores y AA | AD6: 5 | AE6: NO
A7: Plataforma RemotePhy Equipo Nuevo | B7: BBI-TV-TOIP | C7: Income | D7: Gerencia Acceso Fijo | E7: Jorge Mauricio | F7: 2023 | G7: Nuevo Nodo (Reemplzao ECE) | H7: Santa Marta | J7: Yes | K7: 1 | L7: 4 | M7: 2267 | N7: 2267 | P7: =SUMIF($G$3:$G$360,G7,$N$3:$N$360) -> 7340 | Q7: =N7/P7 -> 0.30885559 | R7: =VLOOKUP(G7,#REF!,11,0)*Q7 -> #REF! | S7: DC | U7: 8 | V7: 0 | W7: 0 | X7: DC | Y7: 1.5 | Z7: Q2 | AC7: Por conseguir el sitio | AE7: NO
A8: Plataforma Óptica | B8: BBI-TV-TOIP | C8: Income | D8: Gerencia Acceso Fijo | E8: Jorge Ivan Pérez Cardona | F8: 2023 | G8: La Paz (Bosa) | H8: Bogotá | J8: Yes | K8: 1 | L8: 6 | M8: 475 | N8: 2850 | P8: =SUMIF($G$3:$G$360,G8,$N$3:$N$360) -> 5700 | Q8: =N8/P8 -> 0.5 | R8: =VLOOKUP(G8,#REF!,11,0)*Q8 -> #REF! | S8: DC | T8: 1620.75 | U8: 2 | X8: 48 VDC | Y8: 1.5 | Z8: Q1-Q2 | AB8: Transmisores y Receptotes Ópticos | AC8: No se tiene capacidad AC. Se debe realizar proyecto de aumento de capacidad con CODENSA | AE8: NO
A9: Plataforma Óptica | B9: BBI-TV-TOIP | C9: Income | D9: Gerencia Acceso Fijo | E9: Jorge Ivan Pérez Cardona | F9: 2023 | G9: Linda Vista | H9: Barranquilla | J9: Yes | K9: 1 | L9: 2 | M9: 475 | N9: 950 | P9: =SUMIF($G$3:$G$360,G9,$N$3:$N$360) -> 1900 | Q9: =N9/P9 -> 0.5 | R9: =VLOOKUP(G9,#REF!,11,0)*Q9 -> #REF! | S9: DC | T9: 1620.75 | U9: 2 | X9: 48 VDC | Y9: 1.5 | Z9: Q1-Q2 | AB9: Transmisores y Receptotes Ópticos | AC9: Este nodo está en proceso de desmonte | AD9: 5 | AE9: NO
A10: Plataforma Óptica | B10: BBI-TV-TOIP | C10: Income | D10: Gerencia Acceso Fijo | E10: Jorge Ivan Pérez Cardona | F10: 2023 | G10: Centro Ejecutivo | H10: Santa Marta | J10: Yes | K10: 1 | L10: 6 | M10: 475 | N10: 2850 | P10: =SUMIF($G$3:$G$360,G10,$N$3:$N$360) -> 8100 | Q10: =N10/P10 -> 0.35185185 | R10: =VLOOKUP(G10,#REF!,11,0)*Q10 -> #REF! | S10: DC | T10: 1620.75 | U10: 2 | X10: 48 VDC | Y10: 1.5 | Z10: Q1-Q2 | AB10: Transmisores y Receptotes Ópticos | AC10: Sitio sobrecargado energía y refrigeración | AD10: 4 | AE10: NO
A11: Plataforma Óptica | B11: BBI-TV-TOIP | C11: Income | D11: Gerencia Acceso Fijo | E11: Jorge Ivan Pérez Cardona | F11: 2023 | G11: Camara de Comercio | H11: Armenia | K11: 1 | L11: 6 | M11: 475 | N11: 2850 | P11: =SUMIF($G$3:$G$360,G11,$N$3:$N$360) -> 5700 | Q11: =N11/P11 -> 0.5 | R11: =VLOOKUP(G11,#REF!,11,0)*Q11 -> #REF! | S11: DC | T11: 1620.75 | U11: 2 | X11: 48 VDC | Y11: 1.5 | Z11: Q1-Q2 | AB11: Transmisores y Receptotes Ópticos | AC11: Sitio sin espacio. No hay forma de ampliación. | AD11: 4 | AE11: No
A12: Plataforma Óptica | B12: BBI-TV-TOIP | C12: Income | D12: Gerencia Acceso Fijo | E12: Jorge Ivan Pérez Cardona | F12: 2023 | G12: Cabecera | H12: Armenia | J12: Yes | K12: 1 | L12: 6 | M12: 475 | N12: 2850 | P12: =SUMIF($G$3:$G$360,G12,$N$3:$N$360) -> 2850 | Q12: =N12/P12 -> 1 | R12: =VLOOKUP(G12,#REF!,11,0)*Q12 -> #REF! | S12: DC | T12: 1620.75 | U12: 2 | X12: 48 VDC | Y12: 1.5 | Z12: Q1-Q2 | AB12: Transmisores y Receptotes Ópticos | AC12: Sitio sin espacio. No hay forma de ampliación. | AD12: 4 | AE12: No
A13: MPLS | B13: MPLS | C13: INCOME | D13: Gerencia Cloud, IP y DC | E13: José Alejandro Arcila | F13: 2023 | G13: Centro ejecutivo | H13: Santa Marta | J13: no | K13: 0 | L13: 0 | M13: 400 | N13: 600 | P13: =SUMIF($G$3:$G$360,G13,$N$3:$N$360) -> 8100 | Q13: =N13/P13 -> 0.074074074 | R13: =VLOOKUP(G13,#REF!,11,0)*Q13 -> #REF! | S13: dc | T13: 682 BTU/hour | AB13: Tarjeta 24*10 | AC13: Sitio sobrecargado energía y refrigeración | AD13: 4 | AE13: NO
A14: MPLS | B14: MPLS | C14: INCOME | D14: Gerencia Cloud, IP y DC | E14: José Alejandro Arcila | F14: 2023 | G14: Nodo Nuevo | H14: Santa Marta | J14: si | K14: 1 | L14: 0 | M14: 400 | N14: 600 | P14: =SUMIF($G$3:$G$360,G14,$N$3:$N$360) -> 2400 | Q14: =N14/P14 -> 0.25 | R14: =VLOOKUP(G14,#REF!,11,0)*Q14 -> #REF! | S14: dc | T14: 992 BTU/hour | U14: 2 | AB14: Swiche DAAS | AC14: Por conseguir el sitio | AE14: NO
A15: MPLS | B15: MPLS | C15: INCOME | D15: Gerencia Cloud, IP y DC | E15: José Alejandro Arcila | F15: 2023 | G15: La Paz | H15: Bogotá | J15: si | K15: 1 | L15: 0 | M15: 400 | N15: 600 | P15: =SUMIF($G$3:$G$360,G15,$N$3:$N$360) -> 3600 | Q15: =N15/P15 -> 0.16666667 | R15: =VLOOKUP(G15,#REF!,11,0)*Q15 -> #REF! | S15: dc | T15: 992 BTU/hour | U15: 2 | AB15: Swiche DAAS | AC15: No se tiene capacidad AC. Se debe realizar proyecto de aumento de capacidad con CODENSA | AE15: NO
A16: MPLS | B16: MPLS | C16: INCOME | D16: Gerencia Cloud, IP y DC | E16: José Alejandro Arcila | F16: 2023 | G16: Quinta Camacho | H16: Cúcuta | J16: si | K16: 1 | L16: 0 | M16: 400 | N16: 600 | P16: =SUMIF($G$3:$G$360,G16,$N$3:$N$360) -> 2400 | Q16: =N16/P16 -> 0.25 | R16: =VLOOKUP(G16,#REF!,11,0)*Q16 -> #REF! | S16: dc | T16: 992 BTU/hour | U16: 2 | AB16: Swiche DAAS | AC16: No se tiene un nodo con el nombre Quinta Camacho en el gobierno de Facilities para Cucuta | AE16: NO
A17: MPLS | B17: MPLS | C17: INCOME | D17: Gerencia Cloud, IP y DC | E17: José Alejandro Arcila | F17: 2023 | G17: Centro ejecutivo | H17: Santa Marta | J17: no | K17: 0 | L17: 0 | M17: 400 | N17: 600 | P17: =SUMIF($G$3:$G$360,G17,$N$3:$N$360) -> 8100 | Q17: =N17/P17 -> 0.074074074 | R17: =VLOOKUP(G17,#REF!,11,0)*Q17 -> #REF! | S17: dc | T17: 682 BTU/hour | AB17: Tarjeta 12*10G | AC17: Sitio sobrecargado energía y refrigeración | AD17: 4 | AE17: NO
A18: MPLS | B18: MPLS | C18: INCOME | D18: Gerencia Cloud, IP y DC | E18: José Alejandro Arcila | F18: 2023 | G18: Nodo Nuevo | H18: Santa Marta | J18: no | K18: 0 | L18: 0 | M18: 400 | N18: 600 | P18: =SUMIF($G$3:$G$360,G18,$N$3:$N$360) -> 2400 | Q18: =N18/P18 -> 0.25 | R18: =VLOOKUP(G18,#REF!,11,0)*Q18 -> #REF! | S18: dc | T18: 682 BTU/hour | AB18: Tarjeta 12*10G | AC18: Sitio por conseguir | AE18: NO
A19: MPLS | B19: MPLS | C19: INCOME | D19: Gerencia Cloud, IP y DC | E19: José Alejandro Arcila | F19: 2023 | G19: La Paz | H19: Bogotá | J19: no | K19: 0 | L19: 0 | M19: 400 | N19: 600 | P19: =SUMIF($G$3:$G$360,G19,$N$3:$N$360) -> 3600 | Q19: =N19/P19 -> 0.16666667 | R19: =VLOOKUP(G19,#REF!,11,0)*Q19 -> #REF! | S19: dc | T19: 682 BTU/hour | AB19: Tarjeta 12*10G | AC19: No se tiene capacidad AC. Se debe realizar proyecto de aumento de capacidad con CODENSA | AE19: NO
A20: MPLS | B20: MPLS | C20: INCOME | D20: Gerencia Cloud, IP y DC | E20: José Alejandro Arcila | F20: 2023 | G20: Quinta Camacho | H20: Cúcuta | J20: no | K20: 0 | L20: 0 | M20: 400 | N20: 600 | P20: =SUMIF($G$3:$G$360,G20,$N$3:$N$360) -> 2400 | Q20: =N20/P20 -> 0.25 | R20: =VLOOKUP(G20,#REF!,11,0)*Q20 -> #REF! | S20: dc | T20: 682 BTU/hour | AB20: Tarjeta 12*10G | AC20: No se tiene un nodo con el nombre Quinta Camacho en el gobierno de Facilities para Cucuta | AE20: NO
A21: MPLS | B21: MPLS | C21: INCOME | D21: Gerencia Cloud, IP y DC | E21: José Alejandro Arcila | F21: 2023 | G21: Carrera | H21: Bogotá | J21: yes | K21: 2 | L21: 2 | M21: 3800 | N21: 4100 | P21: =SUMIF($G$3:$G$360,G21,$N$3:$N$360) -> 12200 | Q21: =N21/P21 -> 0.33606557 | R21: =VLOOKUP(G21,#REF!,11,0)*Q21 -> #REF! | S21: dc | T21: 13290 BTU/hour | AB21: Router 7750 | AC21: El nodo se migrará al sitios GALAN. Se debe solicitar el despliegue en este nuevo sitio. | AD21: N5 | AE21: NO
A22: MPLS | B22: MPLS | C22: Dismount | D22: Gerencia Cloud, IP y DC | E22: José Alejandro Arcila | F22: 2023 | G22: Carrera | H22: Bogotá | J22: no | L22: 2 | M22: 1500 | N22: 2000 | P22: =SUMIF($G$3:$G$360,G22,$N$3:$N$360) -> 12200 | Q22: =N22/P22 -> 0.16393443 | R22: =VLOOKUP(G22,#REF!,11,0)*Q22 -> #REF! | S22: dc | T22: 7000 BTU/hour | AB22: DEsmonte Sw9303 | AC22: El nodo se migrará al sitios GALAN. Se debe solicitar el despliegue en este nuevo sitio. | AD22: N5 | AE22: NO
A23: MPLS | B23: MPLS | C23: INCOME | D23: Gerencia Cloud, IP y DC | E23: José Alejandro Arcila | F23: 2023 | G23: BCC | H23: Bogotá | J23: yes | K23: 2 | L23: 2 | M23: 3800 | N23: 4100 | P23: =SUMIF($G$3:$G$360,G23,$N$3:$N$360) -> 4100 | Q23: =N23/P23 -> 1 | R23: =VLOOKUP(G23,#REF!,11,0)*Q23 -> #REF! | S23: dc | T23: 13290 BTU/hour | AB23: Router 7750 | AC23: No se cuenta con espacio disponibile para instalación de Rack, se debe validar en sitio si hay unidades de rack disponible para reutilizar. No se tiene disponibilidad en DC. Sitio Cerrado | AD23: N5 | AE23: NO
A24: MPLS | B24: MPLS | C24: INCOME | D24: Gerencia Cloud, IP y DC | E24: José Alejandro Arcila | F24: 2023 | G24: WTC (World Trade Center) | H24: Bogotá | J24: yes | K24: 2 | L24: 2 | M24: 3800 | N24: 4100 | P24: =SUMIF($G$3:$G$360,G24,$N$3:$N$360) -> 4100 | Q24: =N24/P24 -> 1 | R24: =VLOOKUP(G24,#REF!,11,0)*Q24 -> #REF! | S24: dc | T24: 13290 BTU/hour | AB24: Router 7750 | AC24: No se cuenta con espacio disponibile para instalación de Rack, se debe validar en sitio si hay unidades de rack disponible para reutilizar. No se tiene disponibilidad en DC. Sitio Cerrado | AD24: N5 | AE24: NO
A25: MPLS | B25: MPLS | C25: INCOME | D25: Gerencia Cloud, IP y DC | E25: José Alejandro Arcila | F25: 2023 | G25: La Paz | H25: Bogotá | J25: no | K25: 0 | L25: 0 | M25: 400 | N25: 600 | P25: =SUMIF($G$3:$G$360,G25,$N$3:$N$360) -> 3600 | Q25: =N25/P25 -> 0.16666667 | R25: =VLOOKUP(G25,#REF!,11,0)*Q25 -> #REF! | S25: dc | T25: 682 BTU/hour | AB25: Tarjeta 12*10G | AC25: No se tiene capacidad AC. Se debe realizar proyecto de aumento de capacidad con CODENSA | AE25: NO
A26: Plataforma Óptica | B26: BBI-TV-TOIP | C26: Income | D26: Gerencia Acceso Fijo | E26: Jorge Ivan Pérez Cardona | F26: 2023 | G26: La Florida | H26: Florida Blanca | J26: Yes | K26: 2 | L26: 4 | M26: 475 | N26: 1403 | P26: =SUMIF($G$3:$G$360,G26,$N$3:$N$360) -> 2806 | Q26: =N26/P26 -> 0.5 | R26: =VLOOKUP(G26,#REF!,11,0)*Q26 -> #REF! | S26: DC | T26: 1620.75 | U26: 4 | X26: 48 VDC | Y26: 3 | Z26: Q1-Q2 | AB26: Transmisores y Receptotes Ópticos | AC26: No se tiene espacio en Piso ni disponible para crecer. Esto se había dialogado en su momento cuando se instaló la OLT | AD26: N5 | AE26: NO
A27: MPLS | B27: MPLS | C27: INCOME | D27: Gerencia Cloud, IP y DC | E27: José Alejandro Arcila | F27: 2023 | G27: Cuestesitas | H27: Riohacha | J27: no | K27: 0 | L27: 0 | M27: 400 | N27: 600 | P27: =SUMIF($G$3:$G$360,G27,$N$3:$N$360) -> 1200 | Q27: =N27/P27 -> 0.5 | R27: =VLOOKUP(G27,#REF!,11,0)*Q27 -> #REF! | S27: dc | T27: 682 BTU/hour | AB27: 12*10G | AC27: Sitio Internexa, no hay datos Facilities | AE27: NO
A29: Plataforma OLT Equipo Nuevo | B29: BBI-TV-TOIP | C29: Income | D29: Gerencia Acceso Fijo | E29: Henry Campos | F29: 2023 | G29: Jamundi | H29: Jamundí | J29: Yes | K29: 2 | L29: 1 | M29: 842 | N29: 1403 | P29: =SUMIF($G$3:$G$316,G29,$N$3:$N$316) -> 4209 | Q29: =IF(N29<>0,N29/P29,"0") -> 0.33333333 | R29: =VLOOKUP(G29,#REF!,11,0)*Q29 -> #REF! | S29: DC | U29: 2 | V29: 0 | W29: 0 | X29: DC | Y29: 3 | Z29: Q2 | AC29: El sitio no cuenta con espacio, ni AA ni rectificador para soportar la carga, debe construirse un sitio nuevo ya que el actual no tiene forma de expandirse. Se revisó sitios propios en Jamundí para revisar posibilidad de instalar OLT intemperie y el sitio que más se ajusta a las necesiddes de la zona requiere adecuaciones por aproximadamente 45 millones para volverlo confiable para la instalación de una OLT intemperie. | AD29: 5 | AE29: NO | AF29: Sitio nuevo | AI29: Sitio nuevo | AK29: =AJ29*'BU FACILITIES'!$G$21 -> 0 | AL29: 0 | AM29: =PRODUCT( AL29,'BU FACILITIES'!$G$22) -> 0 | AN29: sitio nuevo | AP29: =IF(AO29=1,'BU FACILITIES'!$G$23,"") | AQ29: 0 | AR29: 1200 | AT29: 0 | AU29: 800 | AW29: 0 | AX29: 45 | AZ29: 0 | BA29: 5
A30: Plataforma OLT Equipo Nuevo | B30: BBI-TV-TOIP | C30: Income | D30: Gerencia Acceso Fijo | E30: Henry Campos | F30: 2023 | G30: Nuevo Nodo (Reemplzao ECE) | H30: Santa Marta | J30: Yes | K30: 2 | L30: 1 | M30: 842 | N30: 1403 | P30: =SUMIF($G$3:$G$316,G30,$N$3:$N$316) -> 7340 | Q30: =IF(N30<>0,N30/P30,"0") -> 0.19114441 | R30: =VLOOKUP(G30,#REF!,11,0)*Q30 -> #REF! | S30: DC | U30: 2 | V30: 0 | W30: 0 | X30: DC | Y30: 3 | Z30: Q2 | AB30: OLT nueva | AC30: Sitio por conseguir | AE30: NO | AF30: No | AI30: No | AK30: =AJ30*'BU FACILITIES'!$G$21 -> 0 | AL30: 0 | AM30: =PRODUCT( AL30,'BU FACILITIES'!$G$22) -> 0 | AN30: No | AP30: =IF(AO30=1,'BU FACILITIES'!$G$23,"") | AQ30: =2*0 -> 0 | AR30: =300*0 -> 0 | AT30: =8*0 -> 0 | AU30: =100*0 -> 0 | AW30: =1*0 -> 0 | AX30: =30*0 -> 0 | AZ30: =2*0 -> 0 | BA30: =3*0 -> 0
A31: Plataforma OLT Equipo Nuevo | B31: BBI-TV-TOIP | C31: Income | D31: Gerencia Acceso Fijo | E31: Henry Campos | F31: 2023 | G31: Chinchiná | H31: Chinchiná | J31: Yes | K31: 2 | L31: 1 | M31: 842 | N31: 1403 | P31: =SUMIF($G$3:$G$316,G31,$N$3:$N$316) -> 2806 | Q31: =IF(N31<>0,N31/P31,"0") -> 0.5 | R31: =VLOOKUP(G31,#REF!,11,0)*Q31 -> #REF! | S31: DC | U31: 2 | V31: 0 | W31: 0 | X31: DC | Y31: 3 | Z31: Q3 | AB31: OLT nueva | AC31: Sitio sin espacio, requiere obra civil. (35 millones aprox). Se debe negociar con la estación de Policia. | AD31: Urbano | AE31: No | AI31: PDB | AJ31: 0 | AK31: =AJ31*'BU FACILITIES'!$G$21 -> 0 | AL31: 0 | AM31: =PRODUCT( AL31,'BU FACILITIES'!$G$22) -> 0 | AN31: Si | AP31: =IF(AO31=1,'BU FACILITIES'!$G$23,"") | AQ31: 0 | AR31: 500 | AT31: 0 | AU31: 500 | AZ31: 0 | BA31: 3
A32: Plataforma OLT Equipo Nuevo | B32: BBI-TV-TOIP | C32: Income | D32: Gerencia Acceso Fijo | E32: Henry Campos | F32: 2023 | G32: Puerto Colombia | H32: Puerto Colombia | J32: Yes | K32: 2 | L32: 1 | M32: 842 | N32: 1403 | P32: =SUMIF($G$3:$G$316,G32,$N$3:$N$316) -> 2806 | Q32: =IF(N32<>0,N32/P32,"0") -> 0.5 | R32: =VLOOKUP(G32,#REF!,11,0)*Q32 -> #REF! | S32: DC | U32: 2 | V32: 0 | W32: 0 | X32: DC | Y32: 3 | Z32: Q3 | AB32: OLT nueva | AC32: Se buscará mejor sitio por seguridad, sitios movil han sido vandalizados | AE32: NO | AF32: SI | AI32: SI | AJ32: 0 | AK32: =AJ32*'BU FACILITIES'!$G$21 -> 0 | AL32: 0 | AM32: =PRODUCT( AL32,'BU FACILITIES'!$G$22) -> 0 | AN32: SI | AP32: =IF(AO32=1,'BU FACILITIES'!$G$23,"") | AQ32: 0 | AR32: 300 | AT32: 0 | AU32: 100 | AW32: 0 | AX32: 20
A33: Plataforma OLT Equipo Nuevo | B33: BBI-TV-TOIP | C33: Income | D33: Gerencia Acceso Fijo | E33: Henry Campos | F33: 2023 | G33: Jamundi | H33: Jamundí | J33: Yes | K33: 2 | L33: 1 | M33: 842 | N33: 1403 | P33: =SUMIF($G$3:$G$316,G33,$N$3:$N$316) -> 4209 | Q33: =IF(N33<>0,N33/P33,"0") -> 0.33333333 | R33: =VLOOKUP(G33,#REF!,11,0)*Q33 -> #REF! | S33: DC | U33: 2 | V33: 0 | W33: 0 | X33: DC | Y33: 3 | Z33: Q2 | AB33: OLT nueva | AC33: No se tiene esapcio ni capacidad en rectificadores y AA | AD33: 5 | AE33: NO | AK33: =AJ33*'BU FACILITIES'!$G$21 -> 0 | AL33: 0 | AM33: =PRODUCT( AL33,'BU FACILITIES'!$G$22) -> 0 | AP33: =IF(AO33=1,'BU FACILITIES'!$G$23,"")
A34: Plataforma RemotePhy Equipo Nuevo | B34: BBI-TV-TOIP | C34: Income | D34: Gerencia Acceso Fijo | E34: Jorge Mauricio | F34: 2023 | G34: Nuevo Nodo (Reemplzao ECE) | H34: Santa Marta | J34: Yes | K34: 1 | L34: 4 | M34: 2267 | N34: 2267 | P34: =SUMIF($G$3:$G$316,G34,$N$3:$N$316) -> 7340 | Q34: =IF(N34<>0,N34/P34,"0") -> 0.30885559 | R34: =VLOOKUP(G34,#REF!,11,0)*Q34 -> #REF! | S34: DC | U34: 8 | V34: 0 | W34: 0 | X34: DC | Y34: 1.5 | Z34: Q2 | AC34: Por conseguir el sitio | AE34: NO | AF34: No | AI34: No | AK34: =AJ34*'BU FACILITIES'!$G$21 -> 0 | AL34: 0 | AM34: =PRODUCT( AL34,'BU FACILITIES'!$G$22) -> 0 | AN34: No | AP34: =IF(AO34=1,'BU FACILITIES'!$G$23,"") | AQ34: =2*0 -> 0 | AR34: =300*0 -> 0
A35: Plataforma Óptica | B35: BBI-TV-TOIP | C35: Income | D35: Gerencia Acceso Fijo | E35: Jorge Ivan Pérez Cardona | F35: 2023 | G35: La Paz (Bosa) | H35: Bogotá | J35: Yes | K35: 1 | L35: 6 | M35: 475 | N35: 2850 | P35: =SUMIF($G$3:$G$316,G35,$N$3:$N$316) -> 5700 | Q35: =IF(N35<>0,N35/P35,"0") -> 0.5 | R35: =VLOOKUP(G35,#REF!,11,0)*Q35 -> #REF! | S35: DC | T35: 1620.75 | U35: 2 | X35: 48 VDC | Y35: 1.5 | Z35: Q1-Q2 | AB35: Transmisores y Receptotes Ópticos | AC35: No se tiene capacidad AC. Se debe realizar proyecto de aumento de capacidad con CODENSA | AE35: NO | AK35: =AJ35*'BU FACILITIES'!$G$21 -> 0 | AL35: 0 | AM35: =PRODUCT( AL35,'BU FACILITIES'!$G$22) -> 0 | AP35: =IF(AO35=1,'BU FACILITIES'!$G$23,"")
A36: Plataforma Óptica | B36: BBI-TV-TOIP | C36: Income | D36: Gerencia Acceso Fijo | E36: Jorge Ivan Pérez Cardona | F36: 2023 | G36: Linda Vista | H36: Barranquilla | J36: Yes | K36: 1 | L36: 2 | M36: 475 | N36: 950 | P36: =SUMIF($G$3:$G$316,G36,$N$3:$N$316) -> 1900 | Q36: =IF(N36<>0,N36/P36,"0") -> 0.5 | R36: =VLOOKUP(G36,#REF!,11,0)*Q36 -> #REF! | S36: DC | T36: 1620.75 | U36: 2 | X36: 48 VDC | Y36: 1.5 | Z36: Q1-Q2 | AB36: Transmisores y Receptotes Ópticos | AC36: Este nodo está en proceso de desmonte | AD36: 5 | AE36: NO | AK36: =AJ36*'BU FACILITIES'!$G$21 -> 0 | AL36: 0 | AM36: =PRODUCT( AL36,'BU FACILITIES'!$G$22) -> 0 | AP36: =IF(AO36=1,'BU FACILITIES'!$G$23,"")
A37: Plataforma Óptica | B37: BBI-TV-TOIP | C37: Income | D37: Gerencia Acceso Fijo | E37: Jorge Ivan Pérez Cardona | F37: 2023 | G37: Centro Ejecutivo | H37: Santa Marta | J37: Yes | K37: 1 | L37: 6 | M37: 475 | N37: 2850 | P37: =SUMIF($G$3:$G$316,G37,$N$3:$N$316) -> 8100 | Q37: =IF(N37<>0,N37/P37,"0") -> 0.35185185 | R37: =VLOOKUP(G37,#REF!,11,0)*Q37 -> #REF! | S37: DC | T37: 1620.75 | U37: 2 | X37: 48 VDC | Y37: 1.5 | Z37: Q1-Q2 | AB37: Transmisores y Receptotes Ópticos | AC37: Sitio sobrecargado energía y refrigeración | AD37: 4 | AE37: NO | AK37: =AJ37*'BU FACILITIES'!$G$21 -> 0 | AL37: 0 | AM37: =PRODUCT( AL37,'BU FACILITIES'!$G$22) -> 0 | AP37: =IF(AO37=1,'BU FACILITIES'!$G$23,"")
A38: Plataforma Óptica | B38: BBI-TV-TOIP | C38: Income | D38: Gerencia Acceso Fijo | E38: Jorge Ivan Pérez Cardona | F38: 2023 | G38: Camara de Comercio | H38: Armenia | K38: 1 | L38: 6 | M38: 475 | N38: 2850 | P38: =SUMIF($G$3:$G$316,G38,$N$3:$N$316) -> 5700 | Q38: =IF(N38<>0,N38/P38,"0") -> 0.5 | R38: =VLOOKUP(G38,#REF!,11,0)*Q38 -> #REF! | S38: DC | T38: 1620.75 | U38: 2 | X38: 48 VDC | Y38: 1.5 | Z38: Q1-Q2 | AB38: Transmisores y Receptotes Ópticos | AC38: Sitio sin espacio. No hay forma de ampliación. | AD38: 4 | AE38: No | AI38: Si | AJ38: 0 | AK38: =AJ38*'BU FACILITIES'!$G$21 -> 0 | AL38: 0 | AM38: =PRODUCT( AL38,'BU FACILITIES'!$G$22) -> 0 | AP38: =IF(AO38=1,'BU FACILITIES'!$G$23,"")
A39: Plataforma Óptica | B39: BBI-TV-TOIP | C39: Income | D39: Gerencia Acceso Fijo | E39: Jorge Ivan Pérez Cardona | F39: 2023 | G39: Cabecera | H39: Armenia | J39: Yes | K39: 1 | L39: 6 | M39: 475 | N39: 0 | P39: =SUMIF($G$3:$G$316,G39,$N$3:$N$316) -> 2850 | Q39: =IF(N39<>0,N39/P39,"0") -> 0 | R39: =VLOOKUP(G39,#REF!,11,0)*Q39 -> #REF! | S39: DC | T39: 1620.75 | U39: 2 | X39: 48 VDC | Y39: 1.5 | Z39: Q1-Q2 | AB39: Transmisores y Receptotes Ópticos | AC39: Sitio sin espacio. No hay forma de ampliación. | AD39: 4 | AE39: No | AK39: =AJ39*'BU FACILITIES'!$G$21 -> 0 | AL39: 0 | AM39: =PRODUCT( AL39,'BU FACILITIES'!$G$22) -> 0 | AP39: =IF(AO39=1,'BU FACILITIES'!$G$23,"")
A40: MPLS | B40: MPLS | C40: INCOME | D40: Gerencia Cloud, IP y DC | E40: José Alejandro Arcila | F40: 2023 | G40: Centro ejecutivo | H40: Santa Marta | J40: no | K40: 0 | L40: 0 | M40: 400 | N40: 600 | P40: =SUMIF($G$3:$G$316,G40,$N$3:$N$316) -> 8100 | Q40: =IF(N40<>0,N40/P40,"0") -> 0.074074074 | R40: =VLOOKUP(G40,#REF!,11,0)*Q40 -> #REF! | S40: dc | T40: 682 BTU/hour | AB40: Tarjeta 24*10 | AC40: Sitio sobrecargado energía y refrigeración | AD40: 4 | AE40: NO | AK40: =AJ40*'BU FACILITIES'!$G$21 -> 0 | AL40: 0 | AM40: =PRODUCT( AL40,'BU FACILITIES'!$G$22) -> 0 | AP40: =IF(AO40=1,'BU FACILITIES'!$G$23,"")
A41: MPLS | B41: MPLS | C41: INCOME | D41: Gerencia Cloud, IP y DC | E41: José Alejandro Arcila | F41: 2023 | G41: Nodo Nuevo | H41: Santa Marta | J41: si | K41: 1 | L41: 0 | M41: 400 | N41: 600 | P41: =SUMIF($G$3:$G$316,G41,$N$3:$N$316) -> 2400 | Q41: =IF(N41<>0,N41/P41,"0") -> 0.25 | R41: =VLOOKUP(G41,#REF!,11,0)*Q41 -> #REF! | S41: dc | T41: 992 BTU/hour | U41: 2 | AB41: Swiche DAAS | AC41: Por conseguir el sitio | AE41: NO | AK41: =AJ41*'BU FACILITIES'!$G$21 -> 0 | AL41: 0 | AM41: =PRODUCT( AL41,'BU FACILITIES'!$G$22) -> 0 | AP41: =IF(AO41=1,'BU FACILITIES'!$G$23,"")
A42: MPLS | B42: MPLS | C42: INCOME | D42: Gerencia Cloud, IP y DC | E42: José Alejandro Arcila | F42: 2023 | G42: La Paz | H42: Bogotá | J42: si | K42: 1 | L42: 0 | M42: 400 | N42: 600 | P42: =SUMIF($G$3:$G$316,G42,$N$3:$N$316) -> 3600 | Q42: =IF(N42<>0,N42/P42,"0") -> 0.16666667 | R42: =VLOOKUP(G42,#REF!,11,0)*Q42 -> #REF! | S42: dc | T42: 992 BTU/hour | U42: 2 | AB42: Swiche DAAS | AC42: No se tiene capacidad AC. Se debe realizar proyecto de aumento de capacidad con CODENSA | AE42: NO | AK42: =AJ42*'BU FACILITIES'!$G$21 -> 0 | AL42: 0 | AM42: =PRODUCT( AL42,'BU FACILITIES'!$G$22) -> 0 | AP42: =IF(AO42=1,'BU FACILITIES'!$G$23,"")
A43: MPLS | B43: MPLS | C43: INCOME | D43: Gerencia Cloud, IP y DC | E43: José Alejandro Arcila | F43: 2023 | G43: Quinta Camacho | H43: Cúcuta | J43: si | K43: 1 | L43: 0 | M43: 400 | N43: 600 | P43: =SUMIF($G$3:$G$316,G43,$N$3:$N$316) -> 2400 | Q43: =IF(N43<>0,N43/P43,"0") -> 0.25 | R43: =VLOOKUP(G43,#REF!,11,0)*Q43 -> #REF! | S43: dc | T43: 992 BTU/hour | U43: 2 | AB43: Swiche DAAS | AC43: No se tiene un nodo con el nombre Quinta Camacho en el gobierno de Facilities para Cucuta | AE43: NO | AH43: =IF(AG43=1,'BU FACILITIES'!$G$24,"") | AK43: =AJ43*'BU FACILITIES'!$G$21 -> 0 | AL43: 0 | AM43: =PRODUCT( AL43,'BU FACILITIES'!$G$22) -> 0 | AP43: =IF(AO43=1,'BU FACILITIES'!$G$23,"") | AS43: =IF(AR43=300,AQ43*'BU FACILITIES'!$G$4, IF(AND(AR43>300,AR43<=500), AQ43*'BU FACILITIES'!$G$5, IF(AND(AR43>500,AR43<=1250), AQ43*'BU FACILITIES'!$G$6, IF(AND(AR43>1250,AR43<=2000),AQ43*'BU FACILITIES'!$G$7, "")))) | AV43: =IF(AU43=100,AT43*'BU FACILITIES'!$G$8, IF(AND(AU43>100,AU43<=500), AT43*'BU FACILITIES'!$G$9, IF(AND(AU43>500,AU43<=800), AT43*'BU FACILITIES'!$G$10, IF(AND(AU43>800,AU43<=1000),AT43*'BU FACILITIES'!$G$11, IF(AND(AU43>1000,AU43<=1400),AT43*'BU FACILITIES'!$G$12, IF(AND(AU43>1400,AU43<=2000),AT43*'BU FACILITIES'!$G$13,"")))))) | AY43: =IF(AX43=30,AW43*'BU FACILITIES'!$G$14, IF(AX43=45, AW43*'BU FACILITIES'!$G$15, IF(AX43=450, AW43*'BU FACILITIES'!$G$16, ""))) | BB43: =IF(AND(BA43>=1,BA43<=5),'BU FACILITIES'!$G$17, IF(AND(BA43>5, BA43<=10), 'BU FACILITIES'!$G$18, IF(AND(BA43>10,BA43<=20),'BU FACILITIES'!$G$19,""))) | BD43: =IF(AND(AZ43="Modificar ductería de AA",BC43=1), 'BU FACILITIES'!$G$20, "")
A44: MPLS | B44: MPLS | C44: INCOME | D44: Gerencia Cloud, IP y DC | E44: José Alejandro Arcila | F44: 2023 | G44: Centro ejecutivo | H44: Santa Marta | J44: no | K44: 0 | L44: 0 | M44: 400 | N44: 600 | P44: =SUMIF($G$3:$G$316,G44,$N$3:$N$316) -> 8100 | Q44: =IF(N44<>0,N44/P44,"0") -> 0.074074074 | R44: =VLOOKUP(G44,#REF!,11,0)*Q44 -> #REF! | S44: dc | T44: 682 BTU/hour | AB44: Tarjeta 12*10G | AC44: Sitio sobrecargado energía y refrigeración | AD44: 4 | AE44: NO | AK44: =AJ44*'BU FACILITIES'!$G$21 -> 0 | AL44: 0 | AM44: =PRODUCT( AL44,'BU FACILITIES'!$G$22) -> 0 | AP44: =IF(AO44=1,'BU FACILITIES'!$G$23,"")
A45: MPLS | B45: MPLS | C45: INCOME | D45: Gerencia Cloud, IP y DC | E45: José Alejandro Arcila | F45: 2023 | G45: Nodo Nuevo | H45: Santa Marta | J45: no | K45: 0 | L45: 0 | M45: 400 | N45: 600 | P45: =SUMIF($G$3:$G$316,G45,$N$3:$N$316) -> 2400 | Q45: =IF(N45<>0,N45/P45,"0") -> 0.25 | R45: =VLOOKUP(G45,#REF!,11,0)*Q45 -> #REF! | S45: dc | T45: 682 BTU/hour | AB45: Tarjeta 12*10G | AC45: Sitio por conseguir | AE45: NO | AK45: =AJ45*'BU FACILITIES'!$G$21 -> 0 | AL45: 0 | AM45: =PRODUCT( AL45,'BU FACILITIES'!$G$22) -> 0 | AP45: =IF(AO45=1,'BU FACILITIES'!$G$23,"")
A46: MPLS | B46: MPLS | C46: INCOME | D46: Gerencia Cloud, IP y DC | E46: José Alejandro Arcila | F46: 2023 | G46: La Paz | H46: Bogotá | J46: no | K46: 0 | L46: 0 | M46: 400 | N46: 600 | P46: =SUMIF($G$3:$G$316,G46,$N$3:$N$316) -> 3600 | Q46: =IF(N46<>0,N46/P46,"0") -> 0.16666667 | R46: =VLOOKUP(G46,#REF!,11,0)*Q46 -> #REF! | S46: dc | T46: 682 BTU/hour | AB46: Tarjeta 12*10G | AC46: No se tiene capacidad AC. Se debe realizar proyecto de aumento de capacidad con CODENSA | AE46: NO | AK46: =AJ46*'BU FACILITIES'!$G$21 -> 0 | AL46: 0 | AM46: =PRODUCT( AL46,'BU FACILITIES'!$G$22) -> 0 | AP46: =IF(AO46=1,'BU FACILITIES'!$G$23,"")
A47: MPLS | B47: MPLS | C47: INCOME | D47: Gerencia Cloud, IP y DC | E47: José Alejandro Arcila | F47: 2023 | G47: Quinta Camacho | H47: Cúcuta | J47: no | K47: 0 | L47: 0 | M47: 400 | N47: 600 | P47: =SUMIF($G$3:$G$316,G47,$N$3:$N$316) -> 2400 | Q47: =IF(N47<>0,N47/P47,"0") -> 0.25 | R47: =VLOOKUP(G47,#REF!,11,0)*Q47 -> #REF! | S47: dc | T47: 682 BTU/hour | AB47: Tarjeta 12*10G | AC47: No se tiene un nodo con el nombre Quinta Camacho en el gobierno de Facilities para Cucuta | AE47: NO | AH47: =IF(AG47=1,'BU FACILITIES'!$G$24,"") | AK47: =AJ47*'BU FACILITIES'!$G$21 -> 0 | AL47: 0 | AM47: =PRODUCT( AL47,'BU FACILITIES'!$G$22) -> 0 | AP47: =IF(AO47=1,'BU FACILITIES'!$G$23,"") | AS47: =IF(AR47=300,AQ47*'BU FACILITIES'!$G$4, IF(AND(AR47>300,AR47<=500), AQ47*'BU FACILITIES'!$G$5, IF(AND(AR47>500,AR47<=1250), AQ47*'BU FACILITIES'!$G$6, IF(AND(AR47>1250,AR47<=2000),AQ47*'BU FACILITIES'!$G$7, "")))) | AV47: =IF(AU47=100,AT47*'BU FACILITIES'!$G$8, IF(AND(AU47>100,AU47<=500), AT47*'BU FACILITIES'!$G$9, IF(AND(AU47>500,AU47<=800), AT47*'BU FACILITIES'!$G$10, IF(AND(AU47>800,AU47<=1000),AT47*'BU FACILITIES'!$G$11, IF(AND(AU47>1000,AU47<=1400),AT47*'BU FACILITIES'!$G$12, IF(AND(AU47>1400,AU47<=2000),AT47*'BU FACILITIES'!$G$13,"")))))) | AY47: =IF(AX47=30,AW47*'BU FACILITIES'!$G$14, IF(AX47=45, AW47*'BU FACILITIES'!$G$15, IF(AX47=450, AW47*'BU FACILITIES'!$G$16, ""))) | BB47: =IF(AND(BA47>=1,BA47<=5),'BU FACILITIES'!$G$17, IF(AND(BA47>5, BA47<=10), 'BU FACILITIES'!$G$18, IF(AND(BA47>10,BA47<=20),'BU FACILITIES'!$G$19,""))) | BD47: =IF(AND(AZ47="Modificar ductería de AA",BC47=1), 'BU FACILITIES'!$G$20, "")
A48: MPLS | B48: MPLS | C48: INCOME | D48: Gerencia Cloud, IP y DC | E48: José Alejandro Arcila | F48: 2023 | G48: Carrera | H48: Bogotá | J48: yes | K48: 2 | L48: 2 | M48: 3800 | N48: 4100 | P48: =SUMIF($G$3:$G$316,G48,$N$3:$N$316) -> 12200 | Q48: =IF(N48<>0,N48/P48,"0") -> 0.33606557 | R48: =VLOOKUP(G48,#REF!,11,0)*Q48 -> #REF! | S48: dc | T48: 13290 BTU/hour | AB48: Router 7750 | AC48: El nodo se migrará al sitios GALAN. Se debe solicitar el despliegue en este nuevo sitio. | AD48: N5 | AE48: NO | AH48: =IF(AG48=1,'BU FACILITIES'!$G$24,"") | AK48: =AJ48*'BU FACILITIES'!$G$21 -> 0 | AL48: 0 | AM48: =PRODUCT( AL48,'BU FACILITIES'!$G$22) -> 0 | AP48: =IF(AO48=1,'BU FACILITIES'!$G$23,"") | AS48: =IF(AR48=300,AQ48*'BU FACILITIES'!$G$4, IF(AND(AR48>300,AR48<=500), AQ48*'BU FACILITIES'!$G$5, IF(AND(AR48>500,AR48<=1250), AQ48*'BU FACILITIES'!$G$6, IF(AND(AR48>1250,AR48<=2000),AQ48*'BU FACILITIES'!$G$7, "")))) | AV48: =IF(AU48=100,AT48*'BU FACILITIES'!$G$8, IF(AND(AU48>100,AU48<=500), AT48*'BU FACILITIES'!$G$9, IF(AND(AU48>500,AU48<=800), AT48*'BU FACILITIES'!$G$10, IF(AND(AU48>800,AU48<=1000),AT48*'BU FACILITIES'!$G$11, IF(AND(AU48>1000,AU48<=1400),AT48*'BU FACILITIES'!$G$12, IF(AND(AU48>1400,AU48<=2000),AT48*'BU FACILITIES'!$G$13,"")))))) | AY48: =IF(AX48=30,AW48*'BU FACILITIES'!$G$14, IF(AX48=45, AW48*'BU FACILITIES'!$G$15, IF(AX48=450, AW48*'BU FACILITIES'!$G$16, ""))) | BB48: =IF(AND(BA48>=1,BA48<=5),'BU FACILITIES'!$G$17, IF(AND(BA48>5, BA48<=10), 'BU FACILITIES'!$G$18, IF(AND(BA48>10,BA48<=20),'BU FACILITIES'!$G$19,""))) | BD48: =IF(AND(AZ48="Modificar ductería de AA",BC48=1), 'BU FACILITIES'!$G$20, "")
A49: MPLS | B49: MPLS | C49: Dismount | D49: Gerencia Cloud, IP y DC | E49: José Alejandro Arcila | F49: 2023 | G49: Carrera | H49: Bogotá | J49: no | L49: 2 | M49: 1500 | N49: 2000 | P49: =SUMIF($G$3:$G$316,G49,$N$3:$N$316) -> 12200 | Q49: =IF(N49<>0,N49/P49,"0") -> 0.16393443 | R49: =VLOOKUP(G49,#REF!,11,0)*Q49 -> #REF! | S49: dc | T49: 7000 BTU/hour | AB49: DEsmonte Sw9303 | AC49: El nodo se migrará al sitios GALAN. Se debe solicitar el despliegue en este nuevo sitio. | AD49: N5 | AE49: NO | AH49: =IF(AG49=1,'BU FACILITIES'!$G$24,"") | AK49: =AJ49*'BU FACILITIES'!$G$21 -> 0 | AL49: 0 | AM49: =PRODUCT( AL49,'BU FACILITIES'!$G$22) -> 0 | AP49: =IF(AO49=1,'BU FACILITIES'!$G$23,"") | AS49: =IF(AR49=300,AQ49*'BU FACILITIES'!$G$4, IF(AND(AR49>300,AR49<=500), AQ49*'BU FACILITIES'!$G$5, IF(AND(AR49>500,AR49<=1250), AQ49*'BU FACILITIES'!$G$6, IF(AND(AR49>1250,AR49<=2000),AQ49*'BU FACILITIES'!$G$7, "")))) | AV49: =IF(AU49=100,AT49*'BU FACILITIES'!$G$8, IF(AND(AU49>100,AU49<=500), AT49*'BU FACILITIES'!$G$9, IF(AND(AU49>500,AU49<=800), AT49*'BU FACILITIES'!$G$10, IF(AND(AU49>800,AU49<=1000),AT49*'BU FACILITIES'!$G$11, IF(AND(AU49>1000,AU49<=1400),AT49*'BU FACILITIES'!$G$12, IF(AND(AU49>1400,AU49<=2000),AT49*'BU FACILITIES'!$G$13,"")))))) | AY49: =IF(AX49=30,AW49*'BU FACILITIES'!$G$14, IF(AX49=45, AW49*'BU FACILITIES'!$G$15, IF(AX49=450, AW49*'BU FACILITIES'!$G$16, ""))) | BB49: =IF(AND(BA49>=1,BA49<=5),'BU FACILITIES'!$G$17, IF(AND(BA49>5, BA49<=10), 'BU FACILITIES'!$G$18, IF(AND(BA49>10,BA49<=20),'BU FACILITIES'!$G$19,""))) | BD49: =IF(AND(AZ49="Modificar ductería de AA",BC49=1), 'BU FACILITIES'!$G$20, "")
A50: MPLS | B50: MPLS | C50: INCOME | D50: Gerencia Cloud, IP y DC | E50: José Alejandro Arcila | F50: 2023 | G50: La Paz | H50: Bogotá | J50: no | K50: 0 | L50: 0 | M50: 400 | N50: 600 | P50: =SUMIF($G$3:$G$316,G50,$N$3:$N$316) -> 3600 | Q50: =IF(N50<>0,N50/P50,"0") -> 0.16666667 | R50: =VLOOKUP(G50,#REF!,11,0)*Q50 -> #REF! | S50: dc | T50: 682 BTU/hour | AB50: Tarjeta 12*10G | AC50: No se tiene capacidad AC. Se debe realizar proyecto de aumento de capacidad con CODENSA | AE50: NO | AK50: =AJ50*'BU FACILITIES'!$G$21 -> 0 | AL50: 0 | AM50: =PRODUCT( AL50,'BU FACILITIES'!$G$22) -> 0 | AP50: =IF(AO50=1,'BU FACILITIES'!$G$23,"")
A51: Plataforma Óptica | B51: BBI-TV-TOIP | C51: Income | D51: Gerencia Acceso Fijo | E51: Jorge Ivan Pérez Cardona | F51: 2023 | G51: La Florida | H51: Florida Blanca | J51: Yes | K51: 2 | L51: 4 | M51: 475 | N51: 1403 | P51: =SUMIF($G$3:$G$316,G51,$N$3:$N$316) -> 2806 | Q51: =IF(N51<>0,N51/P51,"0") -> 0.5 | R51: =VLOOKUP(G51,#REF!,11,0)*Q51 -> #REF! | S51: DC | T51: 1620.75 | U51: 4 | X51: 48 VDC | Y51: 3 | Z51: Q1-Q2 | AB51: Transmisores y Receptotes Ópticos | AC51: No se tiene espacio en Piso ni disponible para crecer. Esto se había dialogado en su momento cuando se instaló la OLT | AD51: N5 | AE51: NO | AK51: =AJ51*'BU FACILITIES'!$G$21 -> 0 | AL51: 0 | AM51: =PRODUCT( AL51,'BU FACILITIES'!$G$22) -> 0 | AP51: =IF(AO51=1,'BU FACILITIES'!$G$23,"")
A52: MPLS | B52: MPLS | C52: INCOME | D52: Gerencia Cloud, IP y DC | E52: José Alejandro Arcila | F52: 2023 | G52: Cuestesitas | H52: Riohacha | J52: no | K52: 0 | L52: 0 | M52: 400 | N52: 600 | P52: =SUMIF($G$3:$G$316,G52,$N$3:$N$316) -> 1200 | Q52: =IF(N52<>0,N52/P52,"0") -> 0.5 | R52: =VLOOKUP(G52,#REF!,11,0)*Q52 -> #REF! | S52: dc | T52: 682 BTU/hour | AB52: 12*10G | AC52: Sitio Internexa, no hay datos Facilities | AE52: NO | AK52: =AJ52*'BU FACILITIES'!$G$21 -> 0 | AL52: 0 | AM52: =PRODUCT( AL52,'BU FACILITIES'!$G$22) -> 0 | AP52: =IF(AO52=1,'BU FACILITIES'!$G$23,"")

Sheet Sitios sin inversión
A1: Platform or Equipment | B1: Associated Services to the platform | C1: Income / Dismount | D1: Responsable Technical Area | E1: Responsable Technician | F1: Year | G1: Technical Site | H1: City | I1: Regional | J1: Additional m2? Yes/No | K1: If Yes: # Racks? | L1: Quantity Equipment DC | M1: Average Power (W) | N1: Máx. Power DC (W) | O1: Potencia liberar | P1: Sumatoria W por sitio | Q1: % potencia / gerencia | R1: Inversion por gerencia / sitio | S1: Voltage (AC or DC) | T1: Air DissipationBTU | U1: Power sources | V1: Quantity Equipment AC | W1: Máx. Power AC (W) | X1: Voltage (AC or DC) | Y1: Requested Area (M2) | Z1: Instalation date | AA1: Prority | AB1: Comments | AC1: OBSERVACIÓN GERENCIA INFRAESTRUCTURA | AD1: tipo de NODO | AE1: PRE-Factibilidad Infraestructura (Si / No) | AF1: Obra eléctrica AC | AG1: Requiere obra eléctrica AC | AH1: Valor Obra eléctrica AC | AI1: Obra eléctrica DC | AJ1: Requiere Tablero PDB | AK1: Valor PDB | AL1: Requiere Energización | AM1: Valor Energización | AN1: Obra civil | AO1: Requiere obra civil | AP1: Valor Obra civil | AQ1: Rect Cantidad | AR1: Capacidad [Amperios] | AS1: Valor Rectificador | AT1: Bat Cantidad | AU1: Capacidad [Ah] | AV1: Valor Baterías | AW1: MG Cantidad | AX1: Capacidad [kVA] | AY1: Valor MG | AZ1: AA Cantidad | BA1: Capacidad [TR] | BB1: Valor equipos AA | BC1: Requiere rediseño de ductos | BD1: Valor rediseño ductos | BE1: Presupuesto Estimado
A2: Plataforma OLT Equipo Nuevo | B2: BBI-TV-TOIP | C2: Income | D2: Gerencia Acceso Fijo | E2: Henry Campos | F2: 2023 | G2: Centro EDATEL Puerto Berrio | H2: Puerto Berrío | I2: NOROCCIDENTE | J2: Yes | K2: 2 | L2: 1 | M2: 842 | N2: 0 | P2: 0 | Q2: 0 | R2: 0 | S2: DC | U2: 2 | V2: 0 | W2: 0 | X2: DC | Y2: 3 | Z2: Q2 | AB2: OLT nueva | AC2: Requiere BB2000AH y PDB, tiene MG | AE2: SI CONDICIONADA | AI2: PDB | AJ2: 1 | AK2: 1714.6341 | AL2: 1 | AM2: 870.73171 | AT2: 1 | AU2: 2000 | AV2: 21452.006
A3: Plataforma OLT Equipo Nuevo | B3: BBI-TV-TOIP | C3: Income | D3: Gerencia Acceso Fijo | E3: Henry Campos | F3: 2023 | G3: Centro EDATEL Segovia | H3: Segovia | I3: NOROCCIDENTE | J3: Yes | K3: 2 | L3: 1 | M3: 842 | N3: 0 | P3: 0 | Q3: 0 | R3: 0 | S3: DC | U3: 2 | V3: 0 | W3: 0 | X3: DC | Y3: 3 | Z3: Q2 | AB3: OLT nueva | AC3: Este 2022 se va a instalar un rect 300 A nuevo (Rolluot). Requiere nuevo BB 1000AH, tiene MG | AE3: SI CONDICIONADA | AI3: PDB | AJ3: 1 | AK3: 1714.6341 | AL3: 1 | AM3: 870.73171 | AT3: 1 | AU3: 1000 | AV3: 12831.91
A4: Plataforma OLT Equipo Nuevo | B4: BBI-TV-TOIP | C4: Income | D4: Gerencia Acceso Fijo | E4: Henry Campos | F4: 2023 | G4: Centro EDATEL Chigorodó | H4: Chigorodó | I4: NOROCCIDENTE | J4: Yes | K4: 2 | L4: 1 | M4: 842 | N4: 0 | P4: 0 | Q4: 0 | R4: 0 | S4: DC | U4: 2 | V4: 0 | W4: 0 | X4: DC | Y4: 3 | Z4: Q2 | AB4: OLT nueva | AC4: Posee doble rectf, requiere BB1000AH. | AE4: SI CONDICIONADA | AI4: PDB | AJ4: 1 | AK4: 1714.6341 | AL4: 1 | AM4: 870.73171 | AT4: 1 | AU4: 1000 | AV4: 12831.91
A5: Plataforma OLT Equipo Nuevo | B5: BBI-TV-TOIP | C5: Income | D5: Gerencia Acceso Fijo | E5: Henry Campos | F5: 2023 | G5: Florencia | H5: Medellín | I5: NOROCCIDENTE | J5: Yes | K5: 2 | L5: 1 | M5: 842 | N5: 0 | P5: 0 | Q5: 0 | R5: 0 | S5: DC | U5: 2 | V5: 0 | W5: 0 | X5: DC | Y5: 3 | Z5: Q1 | AC5: Es un sitio de bajo crecimiento, se requiere acondionar un nuevo espacio o verificar si hay equipos o racks que se puedan desmontar. Rectificador como respaldo del Shindengen. | AD5: 4 | AE5: SI CONDICIONADA | AF5: Acondicionar nuevo espacio | AG5: 1 | AH5: 9756.0976 | AI5: PDB | AJ5: 1 | AK5: 1714.6341 | AL5: 1 | AM5: 870.73171 | AN5: Adecuar nuevo espacio | AO5: 1 | AP5: 24390.244 | AQ5: 1 | AR5: 1000 | AS5: 18582.488 | AT5: 2 | AU5: 1500 | AV5: 42904.013 | AZ5: Modificar ductería de AA | BC5: 1 | BD5: 9756.0976
A6: Plataforma OLT Equipo Nuevo | B6: BBI-TV-TOIP | C6: Income | D6: Gerencia Acceso Fijo | E6: Henry Campos | F6: 2023 | G6: Niquia | H6: Bello | I6: NOROCCIDENTE | J6: Yes | K6: 2 | L6: 1 | M6: 842 | N6: 0 | P6: 0 | Q6: 0 | R6: 0 | S6: DC | U6: 2 | V6: 0 | W6: 0 | X6: DC | Y6: 3 | Z6: Q1 | AC6: Factibilidad condicionada por posible desmonte del nodo debido a la baja carga y servicios que tiene. Se requiere rectificador de respaldo al Shibdenguen, condicionado a utilizar racks vacios existentes o retirarlos para ingresar nuevos. | AD6: 4 | AE6: SI CONDICIONADA | AK6: 0 | AL6: 1 | AM6: 870.73171 | AQ6: 0.2 | AR6: 1000 | AS6: 3716.4976 | AT6: 2 | AU6: 1500 | AV6: 42904.013 | AZ6: Modificar ductería de AA | BC6: 1 | BD6: 9756.0976
A7: Plataforma OLT Equipo Nuevo | B7: BBI-TV-TOIP | C7: Income | D7: Gerencia Acceso Fijo | E7: Henry Campos | F7: 2023 | G7: San Vicente | H7: Santa Rosa de Cabal | J7: Yes | K7: 2 | L7: 1 | M7: 842 | N7: 0 | P7: 0 | Q7: 0 | R7: 0 | S7: DC | U7: 2 | V7: 0 | W7: 0 | X7: DC | Y7: 3 | Z7: Q3 | AB7: OLT nueva | AC7: Sitio sin espacio, requiere obra civil. (25millones aprox) | AD7: Urbano | AE7: SI CONDICIONADA | AI7: Si | AJ7: 1 | AK7: 1714.6341 | AL7: 1 | AM7: 870.73171 | AN7: Si | AO7: 1 | AP7: 24390.244 | AT7: 1 | AU7: 500 | AV7: 9151.2951 | AZ7: 1 | BA7: 3 | BB7: 13526.829
A8: Plataforma Óptica | B8: BBI-TV-TOIP | C8: Income | D8: Gerencia Acceso Fijo | E8: Jorge Ivan Pérez Cardona | F8: 2023 | G8: Valladolid | H8: Bogotá | J8: Yes | K8: 1 | L8: 6 | M8: 475 | N8: 0 | P8: 0 | Q8: 0 | R8: 0 | S8: DC | T8: 1620.75 | U8: 2 | X8: 48 VDC | Y8: 1.5 | Z8: Q1-Q2 | AB8: Transmisores y Receptotes Ópticos | AC8: Se aprueba el requerimiento | AD8: N4 | AE8: SI | AK8: 0 | AL8: 1 | AM8: 870.73171 | AT8: 2 | AU8: 1400 | AV8: 46883.293
A9: Plataforma Óptica | B9: BBI-TV-TOIP | C9: Income | D9: Gerencia Acceso Fijo | E9: Jorge Ivan Pérez Cardona | F9: 2023 | G9: Centro Edatel Apartadó | H9: Apartadó | I9: NOROCCIDENTE | J9: Yes | K9: 1 | L9: 6 | M9: 475 | N9: 0 | P9: 0 | Q9: 0 | R9: 0 | S9: DC | T9: 1620.75 | U9: 2 | X9: 48 VDC | Y9: 1.5 | Z9: Q1-Q2 | AB9: Transmisores y Receptotes Ópticos | AC9: Posee doble rectif y BB, tiene MG, Requiere PDB y nuevo sistema de Aire Acondicionado (AA de 15TR o 20TR pendiente estudio) | AE9: SI CONDICIONADA | AI9: PDB | AJ9: 1 | AK9: 1714.6341 | AL9: 1 | AM9: 870.73171 | AZ9: 1 | BA9: 20 | BB9: 22626.829
A10: Plataforma Óptica | B10: BBI-TV-TOIP | C10: Income | D10: Gerencia Acceso Fijo | E10: Jorge Ivan Pérez Cardona | F10: 2023 | G10: Centro EDATEL Chigorodó | H10: Chigorodó | I10: NOROCCIDENTE | J10: Yes | K10: 1 | L10: 6 | M10: 475 | N10: 0 | P10: 0 | Q10: 0 | R10: 0 | S10: DC | T10: 1620.75 | U10: 2 | X10: 48 VDC | Y10: 1.5 | Z10: Q1-Q2 | AB10: Transmisores y Receptotes Ópticos | AC10: Posee doble rectf, requiere BB1000AH y PDB. | AE10: SI | AI10: PDB | AJ10: 0 | AK10: 0 | AL10: 0 | AM10: 0 | AT10: 1 | AU10: 1000 | AV10: 12831.91
A11: Plataforma Óptica | B11: BBI-TV-TOIP | C11: Income | D11: Gerencia Acceso Fijo | E11: Jorge Ivan Pérez Cardona | F11: 2023 | G11: Centro Edatel Turbo | H11: Turbo | I11: NOROCCIDENTE | J11: Yes | K11: 1 | L11: 6 | M11: 475 | N11: 0 | P11: 0 | Q11: 0 | R11: 0 | S11: DC | T11: 1620.75 | U11: 2 | X11: 48 VDC | Y11: 1.5 | Z11: Q1-Q2 | AB11: Transmisores y Receptotes Ópticos | AC11: Requiere nuevo rectificador de 500Amperios y PDB, tiene MG. | AE11: SI CONDICIONADA | AI11: PDB | AJ11: 1 | AK11: 1714.6341 | AL11: 1 | AM11: 870.73171 | AQ11: 1 | AR11: 500 | AS11: 12457.488
A12: Plataforma Óptica | B12: BBI-TV-TOIP | C12: Income | D12: Gerencia Acceso Fijo | E12: Jorge Ivan Pérez Cardona | F12: 2023 | G12: Copacabana | H12: Copacabana | I12: NOROCCIDENTE | J12: Yes | K12: 1 | L12: 6 | M12: 475 | N12: 0 | P12: 0 | Q12: 0 | R12: 0 | S12: DC | T12: 1620.75 | U12: 2 | X12: 48 VDC | Y12: 1.5 | Z12: Q1-Q2 | AB12: Transmisores y Receptotes Ópticos | AC12: Solo se puede instalar en antiguo salon Fetex | AD12: 5 | AE12: SI | AI12: PDB | AJ12: 1 | AK12: 1714.6341 | AL12: 1 | AM12: 870.73171 | AQ12: 0.2 | AR12: 1000 | AS12: 3716.4976 | AT12: 2 | AU12: 1500 | AV12: 42904.013 | AZ12: Modificar ductería de AA | BC12: 1 | BD12: 9756.0976
A13: Plataforma Óptica | B13: BBI-TV-TOIP | C13: Income | D13: Gerencia Acceso Fijo | E13: Jorge Ivan Pérez Cardona | F13: 2023 | G13: Niquia | H13: Bello | I13: NOROCCIDENTE | J13: Yes | K13: 1 | L13: 6 | M13: 475 | N13: 0 | P13: 0 | Q13: 0 | R13: 0 | S13: DC | T13: 1620.75 | U13: 2 | X13: 48 VDC | Y13: 1.5 | Z13: Q1-Q2 | AB13: Transmisores y Receptotes Ópticos | AD13: 4 | AE13: SI CONDICIONADA | AK13: 0 | AL13: 1 | AM13: 870.73171
A14: Plataforma Óptica | B14: BBI-TV-TOIP | C14: Income | D14: Gerencia Acceso Fijo | E14: Jorge Ivan Pérez Cardona | F14: 2023 | G14: Florencia | H14: Medellín | I14: NOROCCIDENTE | J14: Yes | K14: 1 | L14: 6 | M14: 475 | N14: 0 | P14: 0 | Q14: 0 | R14: 0 | S14: DC | T14: 1620.75 | U14: 2 | X14: 48 VDC | Y14: 1.5 | Z14: Q1-Q2 | AB14: Transmisores y Receptotes Ópticos | AC14: Es un sitio de bajo crecimiento, se requiere acondionar un nuevo espacio o verificar si hay equipos o racks que se puedan desmontar. Rectificador como respaldo del Shindengen. | AD14: 4 | AE14: SI CONDICIONADA | AK14: 0 | AL14: 1 | AM14: 870.73171 | BC14: 1 | BE14: Diseño de ductos para nueva zona
A15: Plataforma Óptica | B15: BBI-TV-TOIP | C15: Income | D15: Gerencia Acceso Fijo | E15: Jorge Ivan Pérez Cardona | F15: 2023 | G15: Tabor | H15: Barranquilla | J15: Yes | K15: 2 | L15: 6 | M15: 475 | N15: 0 | P15: 0 | Q15: 0 | R15: 0 | S15: DC | T15: 1620.75 | U15: 4 | X15: 48 VDC | Y15: 3 | Z15: Q1-Q2 | AB15: Transmisores y Receptotes Ópticos | AC15: Incluir cableado, protecciones, tendidos, canaletas, tuberías, etc. Aire In Row | AD15: 1 | AE15: SI | AF15: SI | AG15: 1 | AH15: 9756.0976 | AI15: SI | AJ15: 1 | AK15: 1714.6341 | AL15: 1 | AM15: 870.73171 | AZ15: 2 | BA15: 5 | BB15: 13526.829
A16: Plataforma Óptica | B16: BBI-TV-TOIP | C16: Income | D16: Gerencia Acceso Fijo | E16: Jorge Ivan Pérez Cardona | F16: 2023 | G16: Valenza | H16: Barranquilla | J16: Yes | K16: 1 | L16: 2 | M16: 475 | N16: 0 | P16: 0 | Q16: 0 | R16: 0 | S16: DC | T16: 1620.75 | U16: 2 | X16: 48 VDC | Y16: 1.5 | Z16: Q1-Q2 | AB16: Transmisores y Receptotes Ópticos | AC16: Incluir cableado, protecciones, tendidos, canaletas, tuberías, etc. Aire ACONDICIONADO | AD16: 5 | AE16: SI | AK16: 0 | AL16: 1 | AM16: 870.73171 | AZ16: 1 | BA16: 5 | BB16: 13526.829
A17: Plataforma Óptica | B17: BBI-TV-TOIP | C17: Income | D17: Gerencia Acceso Fijo | E17: Jorge Ivan Pérez Cardona | F17: 2023 | G17: San Vicente | H17: Santa Rosa de Cabal | J17: Yes | K17: 1 | L17: 6 | M17: 475 | N17: 0 | P17: 0 | Q17: 0 | R17: 0 | S17: DC | T17: 1620.75 | U17: 2 | X17: 48 VDC | Y17: 1.5 | Z17: Q1-Q2 | AB17: Transmisores y Receptotes Ópticos | AC17: Sitio sin espacio, requiere obra civil. (25millones aprox) | AD17: Urbano | AE17: SI CONDICIONADA | AI17: Si | AK17: 0 | AL17: 1 | AM17: 870.73171 | AN17: Si | AT17: 1 | AU17: 500 | AV17: 9151.2951
A18: Plataforma Óptica | B18: BBI-TV-TOIP | C18: Income | D18: Gerencia Acceso Fijo | E18: Jorge Ivan Pérez Cardona | F18: 2023 | G18: IDEO | H18: Cali | J18: Yes | K18: 3 | L18: 10 | M18: 475 | N18: 0 | P18: 0 | Q18: 0 | R18: 0 | S18: DC | T18: 1620.75 | U18: 6 | X18: 48 VDC | Y18: 4.5 | Z18: Q1-Q2 | AB18: Transmisores y Receptotes Ópticos | AC18: Sitio cuenta con espacio, capacidad en rectificadores y AA para soportar la nueva carga, indican que van a instalar 10 equipos y solo piden 6 fuentes, para estas habría caapcidad de protecciones en los PDB pero deberían ser 20 las posiciones a utilizar por lo que se da viabilidad positiva pero se solicita PDB nuevo | AD18: 4 | AE18: SI | AI18: Instalación nuevo PDB, requiere aproximadamente 40m de cable 4/0 AWG, para equipos 300m de cable 3x14 AWG y 20 protecciones para PDB de 10A | AJ18: 1 | AK18: 1714.6341 | AL18: 1 | AM18: 870.73171 | AN18: escalerilla para nuevo PDB, aproxiamdamente 3m | AO18: 1 | AP18: 24390.244 | AQ18: 0 | AR18: 0 | AT18: 0 | AU18: 0 | AW18: 0 | AX18: 0 | AZ18: 0 | BA18: 0
A19: MPLS | B19: MPLS | C19: INCOME | D19: Gerencia Cloud, IP y DC | E19: José Alejandro Arcila | F19: 2023 | G19: Apartadó | H19: Apartadó | I19: NOROCCIDENTE | J19: no | K19: 0 | L19: 0 | M19: 400 | N19: 0 | P19: 0 | Q19: 0 | R19: 0 | S19: dc | T19: 682 BTU/hour | AB19: Tarjeta 2*100 | AC19: Posee doble rectif y BB, tiene MG, Requiere PDB y nuevo sistema de Aire Acondicionado (AA de 15TR o 20TR pendiente estudio) | AE19: SI | AK19: 0 | AL19: 0 | AM19: 0
A20: MPLS | B20: MPLS | C20: INCOME | D20: Gerencia Cloud, IP y DC | E20: José Alejandro Arcila | F20: 2023 | G20: Florencia | H20: Medellín | I20: NOROCCIDENTE | J20: si | K20: 1 | L20: 0 | M20: 400 | N20: 0 | P20: 0 | Q20: 0 | R20: 0 | S20: dc | T20: 992 BTU/hour | U20: 2 | AB20: Swiche DAAS | AD20: 4 | AE20: SI | AK20: 0 | AL20: 1 | AM20: 870.73171
A21: MPLS | B21: MPLS | C21: INCOME | D21: Gerencia Cloud, IP y DC | E21: José Alejandro Arcila | F21: 2023 | G21: Copacabana | H21: Copacabana | I21: NOROCCIDENTE | J21: si | K21: 1 | L21: 0 | M21: 400 | N21: 0 | P21: 0 | Q21: 0 | R21: 0 | S21: dc | T21: 992 BTU/hour | U21: 2 | AB21: Swiche DAAS | AD21: 5 | AE21: SI | AK21: 0 | AL21: 1 | AM21: 870.73171
A22: MPLS | B22: MPLS | C22: INCOME | D22: Gerencia Cloud, IP y DC | E22: José Alejandro Arcila | F22: 2023 | G22: Florencia | H22: Medellín | I22: NOROCCIDENTE | J22: no | K22: 0 | L22: 0 | M22: 400 | N22: 0 | P22: 0 | Q22: 0 | R22: 0 | S22: dc | T22: 682 BTU/hour | AB22: Tarjeta 12*10G | AD22: 4 | AE22: SI | AK22: 0 | AL22: 0 | AM22: 0
A23: MPLS | B23: MPLS | C23: INCOME | D23: Gerencia Cloud, IP y DC | E23: José Alejandro Arcila | F23: 2023 | G23: Copacabana | H23: Copacabana | I23: NOROCCIDENTE | J23: no | K23: 0 | L23: 0 | M23: 400 | N23: 0 | P23: 0 | Q23: 0 | R23: 0 | S23: dc | T23: 682 BTU/hour | AB23: Tarjeta 12*10G | AD23: 5 | AE23: SI | AK23: 0 | AL23: 0 | AM23: 0
A24: MPLS | B24: MPLS | C24: INCOME | D24: Gerencia Cloud, IP y DC | E24: José Alejandro Arcila | F24: 2023 | G24: BCC | H24: Bogotá | J24: yes | K24: 2 | L24: 2 | M24: 3800 | N24: 0 | P24: 0 | Q24: 0 | R24: 0 | S24: dc | T24: 13290 BTU/hour | AB24: Router 7750 | AC24: No se cuenta con espacio disponibile para instalación de Rack, se debe validar en sitio si hay unidades de rack disponible para reutilizar. No se tiene disponibilidad en DC. Sitio Cerrado | AD24: N5 | AE24: NO | AK24: 0 | AL24: 0 | AM24: 0
A25: MPLS | B25: MPLS | C25: Dismount | D25: Gerencia Cloud, IP y DC | E25: José Alejandro Arcila | F25: 2023 | G25: BCC | H25: Bogotá | J25: no | L25: 2 | M25: 1500 | N25: 0 | P25: 0 | Q25: 0 | R25: 0 | S25: dc | T25: 7000 BTU/hour | AB25: DEsmonte Sw9303 | AC25: Se puede desmontar el equipo | AD25: N5 | AE25: SI | AK25: 0 | AM25: 870.73171
A26: MPLS | B26: MPLS | C26: INCOME | D26: Gerencia Cloud, IP y DC | E26: José Alejandro Arcila | F26: 2023 | G26: Atlas | H26: Bogotá | J26: yes | K26: 2 | L26: 2 | M26: 3800 | N26: 0 | P26: 0 | Q26: 0 | R26: 0 | S26: dc | T26: 13290 BTU/hour | AB26: Router 7750 | AC26: Se cuenta con disponibilidad. | AD26: N4 | AE26: SI | AK26: 0 | AL26: 1 | AM26: 870.73171
A27: MPLS | B27: MPLS | C27: Dismount | D27: Gerencia Cloud, IP y DC | E27: José Alejandro Arcila | F27: 2023 | G27: Atlas | H27: Bogotá | J27: no | L27: 2 | M27: 1500 | N27: 0 | P27: 0 | Q27: 0 | R27: 0 | S27: dc | T27: 7000 BTU/hour | AB27: DEsmonte Sw9303 | AC27: No se cuenta con disponibilidad DC | AD27: N4 | AE27: SI CONDICIONADA | AK27: 0 | AM27: 870.73171 | AQ27: 1 | AR27: 500 | AS27: 12457.488 | AT27: 1 | AU27: 1400 | AV27: 23441.646
A28: MPLS | B28: MPLS | C28: INCOME | D28: Gerencia Cloud, IP y DC | E28: José Alejandro Arcila | F28: 2023 | G28: Valladolid | H28: Bogotá | J28: yes | K28: 2 | L28: 2 | M28: 3800 | N28: 0 | P28: 0 | Q28: 0 | R28: 0 | S28: dc | T28: 13290 BTU/hour | AB28: Router 7750 | AC28: Se aprueba el requerimiento | AD28: N4 | AE28: SI | AK28: 0 | AL28: 1 | AM28: 870.73171
A29: MPLS | B29: MPLS | C29: Dismount | D29: Gerencia Cloud, IP y DC | E29: José Alejandro Arcila | F29: 2023 | G29: Valladolid | H29: Bogotá | J29: no | L29: 2 | M29: 3300 | N29: 0 | P29: 0 | Q29: 0 | R29: 0 | S29: dc | T29: 13290 BTU/hour | AB29: DEsmonte Ne40E obsoleto | AC29: Se aprueba el requerimiento | AD29: N4 | AE29: SI | AK29: 0 | AM29: 870.73171
A30: MPLS | B30: MPLS | C30: INCOME | D30: Gerencia Cloud, IP y DC | E30: José Alejandro Arcila | F30: 2023 | G30: Guarne | H30: Bogotá | J30: no | K30: 0 | L30: 0 | M30: 400 | N30: 0 | P30: 0 | Q30: 0 | R30: 0 | S30: dc | T30: 682 BTU/hour | AB30: Tarjeta 12*10G | AC30: Se aprueba la instalación | AD30: N5 | AE30: SI | AK30: 0 | AL30: 0 | AM30: 0 | AN30: Seguridad para gabinetes por vandalismo constante | AO30: 1 | AP30: 1219.5122 | AT30: 2 | AU30: 100 | AV30: 4655.122
A31: MPLS | B31: MPLS | C31: INCOME | D31: Gerencia Cloud, IP y DC | E31: José Alejandro Arcila | F31: 2023 | G31: La estrada | H31: Bogotá | J31: yes | K31: 2 | L31: 2 | M31: 3800 | N31: 0 | P31: 0 | Q31: 0 | R31: 0 | S31: dc | T31: 13290 BTU/hour | AB31: Router 7750 | AC31: Se debe realizar cambio de rectificador para garantizar capacidad. | AD31: N5 | AE31: SI, CONDICIONADA | AK31: 0 | AL31: 1 | AM31: 870.73171 | AQ31: 1 | AR31: 312 | AS31: 12457.488 | AT31: 2 | AU31: 200 | AV31: 18302.59
A32: MPLS | B32: MPLS | C32: Dismount | D32: Gerencia Cloud, IP y DC | E32: José Alejandro Arcila | F32: 2023 | G32: La estrada | H32: Bogotá | J32: no | L32: 2 | M32: 1500 | N32: 0 | P32: 0 | Q32: 0 | R32: 0 | S32: dc | T32: 7000 BTU/hour | AB32: DEsmonte Sw9303 | AC32: Se puede desmontar el equipo | AD32: N5 | AE32: SI | AK32: 0 | AM32: 870.73171
A33: MPLS | B33: MPLS | C33: INCOME | D33: Gerencia Cloud, IP y DC | E33: José Alejandro Arcila | F33: 2023 | G33: WTC (World Trade Center) | H33: Bogotá | J33: yes | K33: 2 | L33: 2 | M33: 3800 | N33: 0 | P33: 0 | Q33: 0 | R33: 0 | S33: dc | T33: 13290 BTU/hour | AB33: Router 7750 | AC33: No se cuenta con espacio disponibile para instalación de Rack, se debe validar en sitio si hay unidades de rack disponible para reutilizar. No se tiene disponibilidad en DC. Sitio Cerrado | AD33: N5 | AE33: NO | AK33: 0 | AL33: 0 | AM33: 0
A34: MPLS | B34: MPLS | C34: Dismount | D34: Gerencia Cloud, IP y DC | E34: José Alejandro Arcila | F34: 2023 | G34: WTC (World Trade Center) | H34: Bogotá | J34: no | L34: 2 | M34: 3300 | N34: 0 | P34: 0 | Q34: 0 | R34: 0 | S34: dc | T34: 13290 BTU/hour | AB34: DEsmonte Ne40E obsoleto | AC34: Se puede desmontar el equipo | AD34: N5 | AE34: SI | AK34: 0 | AM34: 870.73171
A35: Plataforma OLT Equipo Nuevo | B35: BBI-TV-TOIP | C35: Income | D35: Gerencia Acceso Fijo | E35: Henry Campos | F35: 2023 | G35: San Francisco | H35: Bucaramanga | J35: Yes | K35: 2 | L35: 1 | M35: 842 | N35: 0 | P35: 0 | Q35: 0 | R35: 0 | S35: DC | U35: 2 | V35: 0 | W35: 0 | X35: DC | Y35: 3 | Z35: Q2 | AC35: Se cuenta con salidad DC para los nuevos equipos. Sistema AC, DC, AA y Generación soportan el aumento de carga. Se requiere cambio de AA de otros operadores y cuartos de baterías por obsolescencia y vida útil | AD35: N3 | AE35: SI | AK35: 0 | AL35: 1 | AM35: 870.73171 | AZ35: 3 | BA35: 3 | BB35: 13526.829
A36: Plataforma Óptica | B36: BBI-TV-TOIP | C36: Income | D36: Gerencia Acceso Fijo | E36: Jorge Ivan Pérez Cardona | F36: 2023 | G36: San Francisco | H36: Bucaramanga | J36: Yes | K36: 1 | L36: 6 | M36: 475 | N36: 0 | P36: 0 | Q36: 0 | R36: 0 | S36: DC | T36: 1620.75 | U36: 2 | X36: 48 VDC | Y36: 1.5 | Z36: Q1-Q2 | AB36: Transmisores y Receptotes Ópticos | AC36: Se cuenta con salidad DC para los nuevos equipos. Sistema AC, DC, AA y Generación soportan el aumento de carga. Se requeire instalar PDB para futuras cargas. | AD36: N3 | AE36: SI | AI36: Instalación de PDB | AJ36: 1 | AK36: 1714.6341 | AL36: 1 | AM36: 870.73171 | BE36: Para la Instalación de un PDB incluyendo OBC, Eléctricas se tienen un valor promedio de 13.000.000 millones
A37: Plataforma Óptica | B37: BBI-TV-TOIP | C37: Income | D37: Gerencia Acceso Fijo | E37: Jorge Ivan Pérez Cardona | F37: 2023 | G37: Santa Barbara | H37: Sogamoso | J37: Yes | K37: 1 | L37: 6 | M37: 475 | N37: 0 | P37: 0 | Q37: 0 | R37: 0 | S37: DC | T37: 1620.75 | U37: 2 | X37: 48 VDC | Y37: 1.5 | Z37: Q1-Q2 | AB37: Transmisores y Receptotes Ópticos | AC37: Se cuenta con salidad DC para los nuevos equipos. Sistema AC, DC, AA y Generación soportan el aumento de carga. | AD37: N4 | AE37: SI | AK37: 0 | AL37: 1 | AM37: 870.73171 | AT37: 1 | AU37: 1000 | AV37: 12831.91
A38: MPLS | B38: MPLS | C38: INCOME | D38: Gerencia Cloud, IP y DC | E38: José Alejandro Arcila | F38: 2023 | G38: San Francisco | H38: Bucaramanga | J38: no | K38: 0 | L38: 0 | M38: 400 | N38: 0 | P38: 0 | Q38: 0 | R38: 0 | S38: dc | T38: 682 BTU/hour | AB38: Tarjeta 12*10G | AC38: Se cuenta con capacidad en los sitemas AC, DC, AA y Generación | AD38: N3 | AE38: SI | AK38: 0 | AL38: 0 | AM38: 0
A39: MPLS | B39: MPLS | C39: INCOME | D39: Gerencia Cloud, IP y DC | E39: José Alejandro Arcila | F39: 2023 | G39: Apartadó | H39: Apartadó | I39: NOROCCIDENTE | J39: no | K39: 0 | L39: 0 | M39: 400 | N39: 0 | P39: 0 | Q39: 0 | R39: 0 | S39: dc | T39: 682 BTU/hour | AB39: Tarjeta 2*100 | AC39: Posee doble rectif y BB, tiene MG, no requiere inversión 2023 para asumir esta carga pero está pendiente la modernización del AA del cuarto de equipos (AA de 15TR o 20TR pendiente estudio) | AE39: SI | AK39: 0 | AL39: 0 | AM39: 0
A40: MPLS | B40: MPLS | C40: INCOME | D40: Gerencia Cloud, IP y DC | E40: José Alejandro Arcila | F40: 2023 | G40: Santafé de antioquia | H40: Santafé de antioquia | J40: yes | K40: 2 | L40: 2 | M40: 3800 | N40: 0 | P40: 0 | Q40: 0 | R40: 0 | S40: dc | T40: 13290 BTU/hour | AB40: Router smalla | AC40: Posee doble rectif y BB, tiene MG, no requiere inversión 2023 para asumir esta carga | AE40: SI CONDICIONADA | AJ40: 1 | AK40: 1714.6341 | AL40: 1 | AM40: 870.73171
A41: MPLS | B41: MPLS | C41: Dismount | D41: Gerencia Cloud, IP y DC | E41: José Alejandro Arcila | F41: 2023 | G41: Santafé de antioquia | H41: Santafé de antioquia | J41: no | L41: 2 | M41: 1500 | N41: 0 | P41: 0 | Q41: 0 | R41: 0 | S41: dc | T41: 7000 BTU/hour | AB41: DEsmonte Ne40 X3 | AC41: Posee doble rectif y BB, tiene MG, no requiere inversión 2023 para asumir esta carga | AE41: SI | AK41: 0 | AL41: 0 | AM41: 0
A42: MPLS | B42: MPLS | C42: INCOME | D42: Gerencia Cloud, IP y DC | E42: José Alejandro Arcila | F42: 2023 | G42: Apartadó | H42: Apartadó | I42: NOROCCIDENTE | J42: no | K42: 0 | L42: 0 | M42: 400 | N42: 0 | P42: 0 | Q42: 0 | R42: 0 | S42: dc | T42: 682 BTU/hour | AB42: 24*10G + tarjeta 48*1G | AC42: Posee doble rectif y BB, tiene MG, no requiere inversión 2023 para asumir esta carga pero está pendiente la modernización del AA del cuarto de equipos (AA de 15TR o 20TR pendiente estudio) | AE42: SI | AJ42: 0 | AK42: 0 | AL42: 0 | AM42: 0
A43: MPLS | B43: MPLS | C43: INCOME | D43: Gerencia Cloud, IP y DC | E43: José Alejandro Arcila | F43: 2023 | G43: Copacabana | H43: Copacabana | I43: NOROCCIDENTE | J43: no | K43: 0 | L43: 0 | M43: 400 | N43: 0 | P43: 0 | Q43: 0 | R43: 0 | S43: dc | T43: 682 BTU/hour | AB43: tarjetas 48*1 | AD43: 5 | AE43: SI | AK43: 0 | AL43: 0 | AM43: 0
A44: MPLS | B44: MPLS | C44: INCOME | D44: Gerencia Cloud, IP y DC | E44: José Alejandro Arcila | F44: 2023 | G44: Montería Móvil | H44: Montería | J44: no | K44: 0 | L44: 0 | M44: 400 | N44: 0 | P44: 0 | Q44: 0 | R44: 0 | S44: dc | T44: 682 BTU/hour | AB44: 12*10G | AC44: Incluir, cableado, protecciones, tendidos, canaletas, tuberías | AD44: 4 | AE44: SI | AI44: SI | AJ44: 1 | AK44: 1714.6341 | AL44: 0 | AM44: 0
A45: MPLS | B45: MPLS | C45: INCOME | D45: Gerencia Cloud, IP y DC | E45: José Alejandro Arcila | F45: 2023 | G45: Guarne | H45: Guarne | I45: NOROCCIDENTE | J45: no | K45: 0 | L45: 0 | M45: 400 | N45: 0 | P45: 0 | Q45: 0 | R45: 0 | S45: dc | T45: 682 BTU/hour | AB45: 2 satélite | AD45: 4 | AE45: SI | AK45: 0 | AL45: 1 | AM45: 870.73171
A46: Plataforma Óptica | B46: BBI-TV-TOIP | C46: Income | D46: Gerencia Acceso Fijo | E46: Jorge Ivan Pérez Cardona | F46: 2023 | G46: Visión Colombia | H46: Bogotá | J46: Yes | K46: 1 | L46: 6 | M46: 475 | N46: 2850 | P46: =SUMIF($G$3:$G$292,G46,$N$3:$N$292) -> 2850 | Q46: =IF(N46<>0,N46/P46,"0") -> 1 | R46: =VLOOKUP(G46,#REF!,11,0)*Q46 -> #REF! | S46: DC | T46: 1620.75 | U46: 2 | X46: 48 VDC | Y46: 1.5 | Z46: Q1-Q2 | AB46: Transmisores y Receptotes Ópticos | AC46: Se niega por proeso de desmonte de sitio | AD46: N3 | AE46: NO | AH46: =IF(AG46=1,'BU FACILITIES'!$G$24,"") | AK46: =AJ46*'BU FACILITIES'!$G$21 -> 0 | AL46: 0 | AM46: =PRODUCT( AL46,'BU FACILITIES'!$G$22) -> 0 | AP46: =IF(AO46=1,'BU FACILITIES'!$G$23,"") | AS46: =IF(AR46=300,AQ46*'BU FACILITIES'!$G$4, IF(AND(AR46>300,AR46<=500), AQ46*'BU FACILITIES'!$G$5, IF(AND(AR46>500,AR46<=1250), AQ46*'BU FACILITIES'!$G$6, IF(AND(AR46>1250,AR46<=2000),AQ46*'BU FACILITIES'!$G$7, "")))) | AV46: =IF(AU46=100,AT46*'BU FACILITIES'!$G$8, IF(AND(AU46>100,AU46<=500), AT46*'BU FACILITIES'!$G$9, IF(AND(AU46>500,AU46<=800), AT46*'BU FACILITIES'!$G$10, IF(AND(AU46>800,AU46<=1000),AT46*'BU FACILITIES'!$G$11, IF(AND(AU46>1000,AU46<=1400),AT46*'BU FACILITIES'!$G$12, IF(AND(AU46>1400,AU46<=2000),AT46*'BU FACILITIES'!$G$13,"")))))) | AY46: =IF(AX46=30,AW46*'BU FACILITIES'!$G$14, IF(AX46=45, AW46*'BU FACILITIES'!$G$15, IF(AX46=450, AW46*'BU FACILITIES'!$G$16, ""))) | BB46: =IF(AND(BA46>=1,BA46<=5),'BU FACILITIES'!$G$17, IF(AND(BA46>5, BA46<=10), 'BU FACILITIES'!$G$18, IF(AND(BA46>10,BA46<=20),'BU FACILITIES'!$G$19,""))) | BD46: =IF(AND(AZ46="Modificar ductería de AA",BC46=1), 'BU FACILITIES'!$G$20, "")
A47: Plataforma Óptica | B47: BBI-TV-TOIP | C47: Income | D47: Gerencia Acceso Fijo | E47: Jorge Ivan Pérez Cardona | F47: 2023 | G47: San Benito | H47: Villavicencio | J47: Yes | K47: 1 | L47: 6 | M47: 475 | N47: 2850 | P47: =SUMIF($G$3:$G$292,G47,$N$3:$N$292) -> 2850 | Q47: =IF(N47<>0,N47/P47,"0") -> 1 | R47: =VLOOKUP(G47,#REF!,11,0)*Q47 -> #REF! | S47: DC | T47: 1620.75 | U47: 2 | X47: 48 VDC | Y47: 1.5 | Z47: Q1-Q2 | AB47: Transmisores y Receptotes Ópticos | AC47: Se tiene capacidad para instalación. | AD47: N4 | AE47: SI | AH47: =IF(AG47=1,'BU FACILITIES'!$G$24,"") | AK47: =AJ47*'BU FACILITIES'!$G$21 -> 0 | AL47: 1 | AM47: =PRODUCT( AL47,'BU FACILITIES'!$G$22) -> 870.73171 | AP47: =IF(AO47=1,'BU FACILITIES'!$G$23,"") | AS47: =IF(AR47=300,AQ47*'BU FACILITIES'!$G$4, IF(AND(AR47>300,AR47<=500), AQ47*'BU FACILITIES'!$G$5, IF(AND(AR47>500,AR47<=1250), AQ47*'BU FACILITIES'!$G$6, IF(AND(AR47>1250,AR47<=2000),AQ47*'BU FACILITIES'!$G$7, "")))) | AV47: =IF(AU47=100,AT47*'BU FACILITIES'!$G$8, IF(AND(AU47>100,AU47<=500), AT47*'BU FACILITIES'!$G$9, IF(AND(AU47>500,AU47<=800), AT47*'BU FACILITIES'!$G$10, IF(AND(AU47>800,AU47<=1000),AT47*'BU FACILITIES'!$G$11, IF(AND(AU47>1000,AU47<=1400),AT47*'BU FACILITIES'!$G$12, IF(AND(AU47>1400,AU47<=2000),AT47*'BU FACILITIES'!$G$13,"")))))) | AY47: =IF(AX47=30,AW47*'BU FACILITIES'!$G$14, IF(AX47=45, AW47*'BU FACILITIES'!$G$15, IF(AX47=450, AW47*'BU FACILITIES'!$G$16, ""))) | BB47: =IF(AND(BA47>=1,BA47<=5),'BU FACILITIES'!$G$17, IF(AND(BA47>5, BA47<=10), 'BU FACILITIES'!$G$18, IF(AND(BA47>10,BA47<=20),'BU FACILITIES'!$G$19,""))) | BD47: =IF(AND(AZ47="Modificar ductería de AA",BC47=1), 'BU FACILITIES'!$G$20, "")
A48: Plataforma Óptica | B48: BBI-TV-TOIP | C48: Income | D48: Gerencia Acceso Fijo | E48: Jorge Ivan Pérez Cardona | F48: 2023 | G48: Centro Edatel Caucasia | H48: Caucasia | I48: NOROCCIDENTE | J48: Yes | K48: 1 | L48: 6 | M48: 475 | N48: 2850 | P48: =SUMIF($G$3:$G$292,G48,$N$3:$N$292) -> 2850 | Q48: =IF(N48<>0,N48/P48,"0") -> 1 | R48: =VLOOKUP(G48,#REF!,11,0)*Q48 -> #REF! | S48: DC | T48: 1620.75 | U48: 2 | X48: 48 VDC | Y48: 1.5 | Z48: Q1-Q2 | AB48: Transmisores y Receptotes Ópticos | AC48: Posee doble rectif y BB, tiene MG, no requiere inversión 2023 para asumir esta carga | AE48: SI CONDICIONADA | AH48: =IF(AG48=1,'BU FACILITIES'!$G$24,"") | AI48: PDB | AJ48: 1 | AK48: =AJ48*'BU FACILITIES'!$G$21 -> 1714.6341 | AL48: 1 | AM48: =PRODUCT( AL48,'BU FACILITIES'!$G$22) -> 870.73171 | AP48: =IF(AO48=1,'BU FACILITIES'!$G$23,"") | AS48: =IF(AR48=300,AQ48*'BU FACILITIES'!$G$4, IF(AND(AR48>300,AR48<=500), AQ48*'BU FACILITIES'!$G$5, IF(AND(AR48>500,AR48<=1250), AQ48*'BU FACILITIES'!$G$6, IF(AND(AR48>1250,AR48<=2000),AQ48*'BU FACILITIES'!$G$7, "")))) | AV48: =IF(AU48=100,AT48*'BU FACILITIES'!$G$8, IF(AND(AU48>100,AU48<=500), AT48*'BU FACILITIES'!$G$9, IF(AND(AU48>500,AU48<=800), AT48*'BU FACILITIES'!$G$10, IF(AND(AU48>800,AU48<=1000),AT48*'BU FACILITIES'!$G$11, IF(AND(AU48>1000,AU48<=1400),AT48*'BU FACILITIES'!$G$12, IF(AND(AU48>1400,AU48<=2000),AT48*'BU FACILITIES'!$G$13,"")))))) | AY48: =IF(AX48=30,AW48*'BU FACILITIES'!$G$14, IF(AX48=45, AW48*'BU FACILITIES'!$G$15, IF(AX48=450, AW48*'BU FACILITIES'!$G$16, ""))) | BB48: =IF(AND(BA48>=1,BA48<=5),'BU FACILITIES'!$G$17, IF(AND(BA48>5, BA48<=10), 'BU FACILITIES'!$G$18, IF(AND(BA48>10,BA48<=20),'BU FACILITIES'!$G$19,""))) | BD48: =IF(AND(AZ48="Modificar ductería de AA",BC48=1), 'BU FACILITIES'!$G$20, "")
A49: Plataforma Óptica | B49: BBI-TV-TOIP | C49: Income | D49: Gerencia Acceso Fijo | E49: Jorge Ivan Pérez Cardona | F49: 2023 | G49: Girardota | H49: Girardota | I49: NOROCCIDENTE | J49: Yes | K49: 1 | L49: 6 | M49: 475 | N49: 0 | P49: =SUMIF($G$3:$G$292,G49,$N$3:$N$292) -> 1200 | Q49: =IF(N49<>0,N49/P49,"0") -> 0 | R49: =VLOOKUP(G49,#REF!,11,0)*Q49 -> #REF! | S49: DC | T49: 1620.75 | U49: 2 | X49: 48 VDC | Y49: 1.5 | Z49: Q1-Q2 | AB49: Transmisores y Receptotes Ópticos | AC49: Espacio disponible en Multinet, se requiere adecuar los ductos de AA, se requiere un PDB. | AD49: 4 | AE49: SI | AH49: =IF(AG49=1,'BU FACILITIES'!$G$24,"") | AK49: =AJ49*'BU FACILITIES'!$G$21 -> 0 | AL49: 1 | AM49: =PRODUCT( AL49,'BU FACILITIES'!$G$22) -> 870.73171 | AP49: =IF(AO49=1,'BU FACILITIES'!$G$23,"") | AS49: =IF(AR49=300,AQ49*'BU FACILITIES'!$G$4, IF(AND(AR49>300,AR49<=500), AQ49*'BU FACILITIES'!$G$5, IF(AND(AR49>500,AR49<=1250), AQ49*'BU FACILITIES'!$G$6, IF(AND(AR49>1250,AR49<=2000),AQ49*'BU FACILITIES'!$G$7, "")))) | AV49: =IF(AU49=100,AT49*'BU FACILITIES'!$G$8, IF(AND(AU49>100,AU49<=500), AT49*'BU FACILITIES'!$G$9, IF(AND(AU49>500,AU49<=800), AT49*'BU FACILITIES'!$G$10, IF(AND(AU49>800,AU49<=1000),AT49*'BU FACILITIES'!$G$11, IF(AND(AU49>1000,AU49<=1400),AT49*'BU FACILITIES'!$G$12, IF(AND(AU49>1400,AU49<=2000),AT49*'BU FACILITIES'!$G$13,"")))))) | AY49: =IF(AX49=30,AW49*'BU FACILITIES'!$G$14, IF(AX49=45, AW49*'BU FACILITIES'!$G$15, IF(AX49=450, AW49*'BU FACILITIES'!$G$16, ""))) | BB49: =IF(AND(BA49>=1,BA49<=5),'BU FACILITIES'!$G$17, IF(AND(BA49>5, BA49<=10), 'BU FACILITIES'!$G$18, IF(AND(BA49>10,BA49<=20),'BU FACILITIES'!$G$19,""))) | BD49: =IF(AND(AZ49="Modificar ductería de AA",BC49=1), 'BU FACILITIES'!$G$20, "")
A50: Plataforma Óptica | B50: BBI-TV-TOIP | C50: Income | D50: Gerencia Acceso Fijo | E50: Jorge Ivan Pérez Cardona | F50: 2023 | G50: Bello | H50: Bello | I50: NOROCCIDENTE | J50: Yes | K50: 2 | L50: 8 | M50: 475 | N50: 0 | P50: =SUMIF($G$3:$G$292,G50,$N$3:$N$292) -> 600 | Q50: =IF(N50<>0,N50/P50,"0") -> 0 | R50: =VLOOKUP(G50,#REF!,11,0)*Q50 -> #REF! | S50: DC | T50: 1620.75 | U50: 4 | X50: 48 VDC | Y50: 3 | Z50: Q1-Q2 | AB50: Transmisores y Receptotes Ópticos | AC50: Espacio disponible al lado de los CMTS | AD50: 3 | AE50: SI | AH50: =IF(AG50=1,'BU FACILITIES'!$G$24,"") | AI50: PDB | AJ50: 1 | AK50: =AJ50*'BU FACILITIES'!$G$21 -> 1714.6341 | AL50: 1 | AM50: =PRODUCT( AL50,'BU FACILITIES'!$G$22) -> 870.73171 | AP50: =IF(AO50=1,'BU FACILITIES'!$G$23,"") | AS50: =IF(AR50=300,AQ50*'BU FACILITIES'!$G$4, IF(AND(AR50>300,AR50<=500), AQ50*'BU FACILITIES'!$G$5, IF(AND(AR50>500,AR50<=1250), AQ50*'BU FACILITIES'!$G$6, IF(AND(AR50>1250,AR50<=2000),AQ50*'BU FACILITIES'!$G$7, "")))) | AV50: =IF(AU50=100,AT50*'BU FACILITIES'!$G$8, IF(AND(AU50>100,AU50<=500), AT50*'BU FACILITIES'!$G$9, IF(AND(AU50>500,AU50<=800), AT50*'BU FACILITIES'!$G$10, IF(AND(AU50>800,AU50<=1000),AT50*'BU FACILITIES'!$G$11, IF(AND(AU50>1000,AU50<=1400),AT50*'BU FACILITIES'!$G$12, IF(AND(AU50>1400,AU50<=2000),AT50*'BU FACILITIES'!$G$13,"")))))) | AY50: =IF(AX50=30,AW50*'BU FACILITIES'!$G$14, IF(AX50=45, AW50*'BU FACILITIES'!$G$15, IF(AX50=450, AW50*'BU FACILITIES'!$G$16, ""))) | AZ50: Modificar ductería de AA | BB50: =IF(AND(BA50>=1,BA50<=5),'BU FACILITIES'!$G$17, IF(AND(BA50>5, BA50<=10), 'BU FACILITIES'!$G$18, IF(AND(BA50>10,BA50<=20),'BU FACILITIES'!$G$19,""))) | BC50: 1 | BD50: =IF(AND(AZ50="Modificar ductería de AA",BC50=1), 'BU FACILITIES'!$G$20, "") -> 9756.0976 | BF50: Esto aplica para otras factibilidades
A51: Plataforma Óptica | B51: BBI-TV-TOIP | C51: Income | D51: Gerencia Acceso Fijo | E51: Jorge Ivan Pérez Cardona | F51: 2023 | G51: Berlín | H51: Medellín | I51: NOROCCIDENTE | J51: Yes | K51: 1 | L51: 6 | M51: 475 | N51: 2850 | P51: =SUMIF($G$3:$G$292,G51,$N$3:$N$292) -> 2850 | Q51: =IF(N51<>0,N51/P51,"0") -> 1 | R51: =VLOOKUP(G51,#REF!,11,0)*Q51 -> #REF! | S51: DC | T51: 1620.75 | U51: 2 | X51: 48 VDC | Y51: 1.5 | Z51: Q1-Q2 | AB51: Transmisores y Receptotes Ópticos | AC51: Existe un rack vacio de un NE40, se debe retirar. | AD51: 5 | AE51: SI | AH51: =IF(AG51=1,'BU FACILITIES'!$G$24,"") | AK51: =AJ51*'BU FACILITIES'!$G$21 -> 0 | AL51: 1 | AM51: =PRODUCT( AL51,'BU FACILITIES'!$G$22) -> 870.73171 | AP51: =IF(AO51=1,'BU FACILITIES'!$G$23,"") | AS51: =IF(AR51=300,AQ51*'BU FACILITIES'!$G$4, IF(AND(AR51>300,AR51<=500), AQ51*'BU FACILITIES'!$G$5, IF(AND(AR51>500,AR51<=1250), AQ51*'BU FACILITIES'!$G$6, IF(AND(AR51>1250,AR51<=2000),AQ51*'BU FACILITIES'!$G$7, "")))) | AV51: =IF(AU51=100,AT51*'BU FACILITIES'!$G$8, IF(AND(AU51>100,AU51<=500), AT51*'BU FACILITIES'!$G$9, IF(AND(AU51>500,AU51<=800), AT51*'BU FACILITIES'!$G$10, IF(AND(AU51>800,AU51<=1000),AT51*'BU FACILITIES'!$G$11, IF(AND(AU51>1000,AU51<=1400),AT51*'BU FACILITIES'!$G$12, IF(AND(AU51>1400,AU51<=2000),AT51*'BU FACILITIES'!$G$13,"")))))) | AY51: =IF(AX51=30,AW51*'BU FACILITIES'!$G$14, IF(AX51=45, AW51*'BU FACILITIES'!$G$15, IF(AX51=450, AW51*'BU FACILITIES'!$G$16, ""))) | BB51: =IF(AND(BA51>=1,BA51<=5),'BU FACILITIES'!$G$17, IF(AND(BA51>5, BA51<=10), 'BU FACILITIES'!$G$18, IF(AND(BA51>10,BA51<=20),'BU FACILITIES'!$G$19,""))) | BD51: =IF(AND(AZ51="Modificar ductería de AA",BC51=1), 'BU FACILITIES'!$G$20, "")
A52: Plataforma Óptica | B52: BBI-TV-TOIP | C52: Income | D52: Gerencia Acceso Fijo | E52: Jorge Ivan Pérez Cardona | F52: 2023 | G52: Bosque | H52: Medellín | I52: NOROCCIDENTE | J52: Yes | K52: 1 | L52: 6 | M52: 475 | N52: 2850 | P52: =SUMIF($G$3:$G$292,G52,$N$3:$N$292) -> 4050 | Q52: =IF(N52<>0,N52/P52,"0") -> 0.7037037 | R52: =VLOOKUP(G52,#REF!,11,0)*Q52 -> #REF! | S52: DC | T52: 1620.75 | U52: 2 | X52: 48 VDC | Y52: 1.5 | Z52: Q1-Q2 | AB52: Transmisores y Receptotes Ópticos | AD52: 4 | AE52: SI | AH52: =IF(AG52=1,'BU FACILITIES'!$G$24,"") | AK52: =AJ52*'BU FACILITIES'!$G$21 -> 0 | AL52: 1 | AM52: =PRODUCT( AL52,'BU FACILITIES'!$G$22) -> 870.73171 | AP52: =IF(AO52=1,'BU FACILITIES'!$G$23,"") | AS52: =IF(AR52=300,AQ52*'BU FACILITIES'!$G$4, IF(AND(AR52>300,AR52<=500), AQ52*'BU FACILITIES'!$G$5, IF(AND(AR52>500,AR52<=1250), AQ52*'BU FACILITIES'!$G$6, IF(AND(AR52>1250,AR52<=2000),AQ52*'BU FACILITIES'!$G$7, "")))) | AV52: =IF(AU52=100,AT52*'BU FACILITIES'!$G$8, IF(AND(AU52>100,AU52<=500), AT52*'BU FACILITIES'!$G$9, IF(AND(AU52>500,AU52<=800), AT52*'BU FACILITIES'!$G$10, IF(AND(AU52>800,AU52<=1000),AT52*'BU FACILITIES'!$G$11, IF(AND(AU52>1000,AU52<=1400),AT52*'BU FACILITIES'!$G$12, IF(AND(AU52>1400,AU52<=2000),AT52*'BU FACILITIES'!$G$13,"")))))) | AY52: =IF(AX52=30,AW52*'BU FACILITIES'!$G$14, IF(AX52=45, AW52*'BU FACILITIES'!$G$15, IF(AX52=450, AW52*'BU FACILITIES'!$G$16, ""))) | BB52: =IF(AND(BA52>=1,BA52<=5),'BU FACILITIES'!$G$17, IF(AND(BA52>5, BA52<=10), 'BU FACILITIES'!$G$18, IF(AND(BA52>10,BA52<=20),'BU FACILITIES'!$G$19,""))) | BD52: =IF(AND(AZ52="Modificar ductería de AA",BC52=1), 'BU FACILITIES'!$G$20, "")
A53: Plataforma Óptica | B53: BBI-TV-TOIP | C53: Income | D53: Gerencia Acceso Fijo | E53: Jorge Ivan Pérez Cardona | F53: 2023 | G53: Buenos Aires | H53: Medellín | I53: NOROCCIDENTE | J53: Yes | K53: 1 | L53: 6 | M53: 475 | N53: 2850 | P53: =SUMIF($G$3:$G$292,G53,$N$3:$N$292) -> 4650 | Q53: =IF(N53<>0,N53/P53,"0") -> 0.61290323 | R53: =VLOOKUP(G53,#REF!,11,0)*Q53 -> #REF! | S53: DC | T53: 1620.75 | U53: 2 | X53: 48 VDC | Y53: 1.5 | Z53: Q1-Q2 | AB53: Transmisores y Receptotes Ópticos | AC53: Condicionado al desmonte de la central Fetex que ya fue apagada. | AD53: 4 | AE53: SI CONDICIONADA | AH53: =IF(AG53=1,'BU FACILITIES'!$G$24,"") | AK53: =AJ53*'BU FACILITIES'!$G$21 -> 0 | AL53: 1 | AM53: =PRODUCT( AL53,'BU FACILITIES'!$G$22) -> 870.73171 | AP53: =IF(AO53=1,'BU FACILITIES'!$G$23,"") | AS53: =IF(AR53=300,AQ53*'BU FACILITIES'!$G$4, IF(AND(AR53>300,AR53<=500), AQ53*'BU FACILITIES'!$G$5, IF(AND(AR53>500,AR53<=1250), AQ53*'BU FACILITIES'!$G$6, IF(AND(AR53>1250,AR53<=2000),AQ53*'BU FACILITIES'!$G$7, "")))) | AV53: =IF(AU53=100,AT53*'BU FACILITIES'!$G$8, IF(AND(AU53>100,AU53<=500), AT53*'BU FACILITIES'!$G$9, IF(AND(AU53>500,AU53<=800), AT53*'BU FACILITIES'!$G$10, IF(AND(AU53>800,AU53<=1000),AT53*'BU FACILITIES'!$G$11, IF(AND(AU53>1000,AU53<=1400),AT53*'BU FACILITIES'!$G$12, IF(AND(AU53>1400,AU53<=2000),AT53*'BU FACILITIES'!$G$13,"")))))) | AY53: =IF(AX53=30,AW53*'BU FACILITIES'!$G$14, IF(AX53=45, AW53*'BU FACILITIES'!$G$15, IF(AX53=450, AW53*'BU FACILITIES'!$G$16, ""))) | BB53: =IF(AND(BA53>=1,BA53<=5),'BU FACILITIES'!$G$17, IF(AND(BA53>5, BA53<=10), 'BU FACILITIES'!$G$18, IF(AND(BA53>10,BA53<=20),'BU FACILITIES'!$G$19,""))) | BD53: =IF(AND(AZ53="Modificar ductería de AA",BC53=1), 'BU FACILITIES'!$G$20, "")
A54: Plataforma Óptica | B54: BBI-TV-TOIP | C54: Income | D54: Gerencia Acceso Fijo | E54: Jorge Ivan Pérez Cardona | F54: 2023 | G54: Caribe | H54: Medellín | I54: NOROCCIDENTE | J54: Yes | K54: 1 | L54: 6 | M54: 475 | N54: 2850 | P54: =SUMIF($G$3:$G$292,G54,$N$3:$N$292) -> 2850 | Q54: =IF(N54<>0,N54/P54,"0") -> 1 | R54: =VLOOKUP(G54,#REF!,11,0)*Q54 -> #REF! | S54: DC | T54: 1620.75 | U54: 2 | X54: 48 VDC | Y54: 1.5 | Z54: Q1-Q2 | AB54: Transmisores y Receptotes Ópticos | AC54: Sala Multinet | AD54: 4 | AE54: SI | AH54: =IF(AG54=1,'BU FACILITIES'!$G$24,"") | AK54: =AJ54*'BU FACILITIES'!$G$21 -> 0 | AL54: 1 | AM54: =PRODUCT( AL54,'BU FACILITIES'!$G$22) -> 870.73171 | AP54: =IF(AO54=1,'BU FACILITIES'!$G$23,"") | AS54: =IF(AR54=300,AQ54*'BU FACILITIES'!$G$4, IF(AND(AR54>300,AR54<=500), AQ54*'BU FACILITIES'!$G$5, IF(AND(AR54>500,AR54<=1250), AQ54*'BU FACILITIES'!$G$6, IF(AND(AR54>1250,AR54<=2000),AQ54*'BU FACILITIES'!$G$7, "")))) | AV54: =IF(AU54=100,AT54*'BU FACILITIES'!$G$8, IF(AND(AU54>100,AU54<=500), AT54*'BU FACILITIES'!$G$9, IF(AND(AU54>500,AU54<=800), AT54*'BU FACILITIES'!$G$10, IF(AND(AU54>800,AU54<=1000),AT54*'BU FACILITIES'!$G$11, IF(AND(AU54>1000,AU54<=1400),AT54*'BU FACILITIES'!$G$12, IF(AND(AU54>1400,AU54<=2000),AT54*'BU FACILITIES'!$G$13,"")))))) | AY54: =IF(AX54=30,AW54*'BU FACILITIES'!$G$14, IF(AX54=45, AW54*'BU FACILITIES'!$G$15, IF(AX54=450, AW54*'BU FACILITIES'!$G$16, ""))) | BB54: =IF(AND(BA54>=1,BA54<=5),'BU FACILITIES'!$G$17, IF(AND(BA54>5, BA54<=10), 'BU FACILITIES'!$G$18, IF(AND(BA54>10,BA54<=20),'BU FACILITIES'!$G$19,""))) | BD54: =IF(AND(AZ54="Modificar ductería de AA",BC54=1), 'BU FACILITIES'!$G$20, "")
A55: Plataforma Óptica | B55: BBI-TV-TOIP | C55: Income | D55: Gerencia Acceso Fijo | E55: Jorge Ivan Pérez Cardona | F55: 2023 | G55: Castilla | H55: Medellín | I55: NOROCCIDENTE | J55: Yes | K55: 1 | L55: 6 | M55: 475 | N55: 0 | P55: =SUMIF($G$3:$G$292,G55,$N$3:$N$292) -> 1800 | Q55: =IF(N55<>0,N55/P55,"0") -> 0 | R55: =VLOOKUP(G55,#REF!,11,0)*Q55 -> #REF! | S55: DC | T55: 1620.75 | U55: 2 | X55: 48 VDC | Y55: 1.5 | Z55: Q1-Q2 | AB55: Transmisores y Receptotes Ópticos | AD55: 4 | AE55: SI | AH55: =IF(AG55=1,'BU FACILITIES'!$G$24,"") | AK55: =AJ55*'BU FACILITIES'!$G$21 -> 0 | AL55: 1 | AM55: =PRODUCT( AL55,'BU FACILITIES'!$G$22) -> 870.73171 | AP55: =IF(AO55=1,'BU FACILITIES'!$G$23,"") | AS55: =IF(AR55=300,AQ55*'BU FACILITIES'!$G$4, IF(AND(AR55>300,AR55<=500), AQ55*'BU FACILITIES'!$G$5, IF(AND(AR55>500,AR55<=1250), AQ55*'BU FACILITIES'!$G$6, IF(AND(AR55>1250,AR55<=2000),AQ55*'BU FACILITIES'!$G$7, "")))) | AV55: =IF(AU55=100,AT55*'BU FACILITIES'!$G$8, IF(AND(AU55>100,AU55<=500), AT55*'BU FACILITIES'!$G$9, IF(AND(AU55>500,AU55<=800), AT55*'BU FACILITIES'!$G$10, IF(AND(AU55>800,AU55<=1000),AT55*'BU FACILITIES'!$G$11, IF(AND(AU55>1000,AU55<=1400),AT55*'BU FACILITIES'!$G$12, IF(AND(AU55>1400,AU55<=2000),AT55*'BU FACILITIES'!$G$13,"")))))) | AY55: =IF(AX55=30,AW55*'BU FACILITIES'!$G$14, IF(AX55=45, AW55*'BU FACILITIES'!$G$15, IF(AX55=450, AW55*'BU FACILITIES'!$G$16, ""))) | BB55: =IF(AND(BA55>=1,BA55<=5),'BU FACILITIES'!$G$17, IF(AND(BA55>5, BA55<=10), 'BU FACILITIES'!$G$18, IF(AND(BA55>10,BA55<=20),'BU FACILITIES'!$G$19,""))) | BD55: =IF(AND(AZ55="Modificar ductería de AA",BC55=1), 'BU FACILITIES'!$G$20, "")
A56: Plataforma Óptica | B56: BBI-TV-TOIP | C56: Income | D56: Gerencia Acceso Fijo | E56: Jorge Ivan Pérez Cardona | F56: 2023 | G56: La América | H56: Medellín | I56: NOROCCIDENTE | J56: Yes | K56: 2 | L56: 10 | M56: 475 | N56: 4750 | P56: =SUMIF($G$3:$G$292,G56,$N$3:$N$292) -> 4750 | Q56: =IF(N56<>0,N56/P56,"0") -> 1 | R56: =VLOOKUP(G56,#REF!,11,0)*Q56 -> #REF! | S56: DC | T56: 1620.75 | U56: 4 | X56: 48 VDC | Y56: 3 | Z56: Q1-Q2 | AB56: Transmisores y Receptotes Ópticos | AC56: Factibilidad positiva desde infraestructura, la respuesta final la entrega ingeniería | AD56: 1 | AE56: SI | AH56: =IF(AG56=1,'BU FACILITIES'!$G$24,"") | AK56: =AJ56*'BU FACILITIES'!$G$21 -> 0 | AL56: 1 | AM56: =PRODUCT( AL56,'BU FACILITIES'!$G$22) -> 870.73171 | AP56: =IF(AO56=1,'BU FACILITIES'!$G$23,"") | AS56: =IF(AR56=300,AQ56*'BU FACILITIES'!$G$4, IF(AND(AR56>300,AR56<=500), AQ56*'BU FACILITIES'!$G$5, IF(AND(AR56>500,AR56<=1250), AQ56*'BU FACILITIES'!$G$6, IF(AND(AR56>1250,AR56<=2000),AQ56*'BU FACILITIES'!$G$7, "")))) | AV56: =IF(AU56=100,AT56*'BU FACILITIES'!$G$8, IF(AND(AU56>100,AU56<=500), AT56*'BU FACILITIES'!$G$9, IF(AND(AU56>500,AU56<=800), AT56*'BU FACILITIES'!$G$10, IF(AND(AU56>800,AU56<=1000),AT56*'BU FACILITIES'!$G$11, IF(AND(AU56>1000,AU56<=1400),AT56*'BU FACILITIES'!$G$12, IF(AND(AU56>1400,AU56<=2000),AT56*'BU FACILITIES'!$G$13,"")))))) | AY56: =IF(AX56=30,AW56*'BU FACILITIES'!$G$14, IF(AX56=45, AW56*'BU FACILITIES'!$G$15, IF(AX56=450, AW56*'BU FACILITIES'!$G$16, ""))) | BB56: =IF(AND(BA56>=1,BA56<=5),'BU FACILITIES'!$G$17, IF(AND(BA56>5, BA56<=10), 'BU FACILITIES'!$G$18, IF(AND(BA56>10,BA56<=20),'BU FACILITIES'!$G$19,""))) | BD56: =IF(AND(AZ56="Modificar ductería de AA",BC56=1), 'BU FACILITIES'!$G$20, "")
A57: Plataforma Óptica | B57: BBI-TV-TOIP | C57: Income | D57: Gerencia Acceso Fijo | E57: Jorge Ivan Pérez Cardona | F57: 2023 | G57: San Bernardo | H57: Medellín | I57: NOROCCIDENTE | J57: Yes | K57: 1 | L57: 6 | M57: 475 | N57: 2850 | P57: =SUMIF($G$3:$G$292,G57,$N$3:$N$292) -> 2850 | Q57: =IF(N57<>0,N57/P57,"0") -> 1 | R57: =VLOOKUP(G57,#REF!,11,0)*Q57 -> #REF! | S57: DC | T57: 1620.75 | U57: 2 | X57: 48 VDC | Y57: 1.5 | Z57: Q1-Q2 | AB57: Transmisores y Receptotes Ópticos | AC57: Factibilidad positiva desde infraestructura, la respuesta final la entrega ingeniería | AD57: 1 | AE57: SI | AH57: =IF(AG57=1,'BU FACILITIES'!$G$24,"") | AK57: =AJ57*'BU FACILITIES'!$G$21 -> 0 | AL57: 1 | AM57: =PRODUCT( AL57,'BU FACILITIES'!$G$22) -> 870.73171 | AP57: =IF(AO57=1,'BU FACILITIES'!$G$23,"") | AS57: =IF(AR57=300,AQ57*'BU FACILITIES'!$G$4, IF(AND(AR57>300,AR57<=500), AQ57*'BU FACILITIES'!$G$5, IF(AND(AR57>500,AR57<=1250), AQ57*'BU FACILITIES'!$G$6, IF(AND(AR57>1250,AR57<=2000),AQ57*'BU FACILITIES'!$G$7, "")))) | AV57: =IF(AU57=100,AT57*'BU FACILITIES'!$G$8, IF(AND(AU57>100,AU57<=500), AT57*'BU FACILITIES'!$G$9, IF(AND(AU57>500,AU57<=800), AT57*'BU FACILITIES'!$G$10, IF(AND(AU57>800,AU57<=1000),AT57*'BU FACILITIES'!$G$11, IF(AND(AU57>1000,AU57<=1400),AT57*'BU FACILITIES'!$G$12, IF(AND(AU57>1400,AU57<=2000),AT57*'BU FACILITIES'!$G$13,"")))))) | AY57: =IF(AX57=30,AW57*'BU FACILITIES'!$G$14, IF(AX57=45, AW57*'BU FACILITIES'!$G$15, IF(AX57=450, AW57*'BU FACILITIES'!$G$16, ""))) | BB57: =IF(AND(BA57>=1,BA57<=5),'BU FACILITIES'!$G$17, IF(AND(BA57>5, BA57<=10), 'BU FACILITIES'!$G$18, IF(AND(BA57>10,BA57<=20),'BU FACILITIES'!$G$19,""))) | BD57: =IF(AND(AZ57="Modificar ductería de AA",BC57=1), 'BU FACILITIES'!$G$20, "") | BE57: Ampliación de ductos para nueva zona de ampliación.
A58: Plataforma Óptica | B58: BBI-TV-TOIP | C58: Income | D58: Gerencia Acceso Fijo | E58: Jorge Ivan Pérez Cardona | F58: 2023 | G58: San Javier | H58: Medellín | I58: NOROCCIDENTE | J58: Yes | K58: 1 | L58: 6 | M58: 475 | N58: 0 | P58: =SUMIF($G$3:$G$292,G58,$N$3:$N$292) -> 0 | Q58: =IF(N58<>0,N58/P58,"0") -> 0 | R58: =VLOOKUP(G58,#REF!,11,0)*Q58 -> #REF! | S58: DC | T58: 1620.75 | U58: 2 | X58: 48 VDC | Y58: 1.5 | Z58: Q1-Q2 | AB58: Transmisores y Receptotes Ópticos | AD58: 4 | AE58: SI | AH58: =IF(AG58=1,'BU FACILITIES'!$G$24,"") | AI58: PDB | AJ58: 1 | AK58: =AJ58*'BU FACILITIES'!$G$21 -> 1714.6341 | AL58: 1 | AM58: =PRODUCT( AL58,'BU FACILITIES'!$G$22) -> 870.73171 | AP58: =IF(AO58=1,'BU FACILITIES'!$G$23,"") | AS58: =IF(AR58=300,AQ58*'BU FACILITIES'!$G$4, IF(AND(AR58>300,AR58<=500), AQ58*'BU FACILITIES'!$G$5, IF(AND(AR58>500,AR58<=1250), AQ58*'BU FACILITIES'!$G$6, IF(AND(AR58>1250,AR58<=2000),AQ58*'BU FACILITIES'!$G$7, "")))) | AV58: =IF(AU58=100,AT58*'BU FACILITIES'!$G$8, IF(AND(AU58>100,AU58<=500), AT58*'BU FACILITIES'!$G$9, IF(AND(AU58>500,AU58<=800), AT58*'BU FACILITIES'!$G$10, IF(AND(AU58>800,AU58<=1000),AT58*'BU FACILITIES'!$G$11, IF(AND(AU58>1000,AU58<=1400),AT58*'BU FACILITIES'!$G$12, IF(AND(AU58>1400,AU58<=2000),AT58*'BU FACILITIES'!$G$13,"")))))) | AY58: =IF(AX58=30,AW58*'BU FACILITIES'!$G$14, IF(AX58=45, AW58*'BU FACILITIES'!$G$15, IF(AX58=450, AW58*'BU FACILITIES'!$G$16, ""))) | AZ58: Modificar ductería de AA | BB58: =IF(AND(BA58>=1,BA58<=5),'BU FACILITIES'!$G$17, IF(AND(BA58>5, BA58<=10), 'BU FACILITIES'!$G$18, IF(AND(BA58>10,BA58<=20),'BU FACILITIES'!$G$19,""))) | BC58: 1 | BD58: =IF(AND(AZ58="Modificar ductería de AA",BC58=1), 'BU FACILITIES'!$G$20, "") -> 9756.0976
A59: Plataforma Óptica | B59: BBI-TV-TOIP | C59: Income | D59: Gerencia Acceso Fijo | E59: Jorge Ivan Pérez Cardona | F59: 2023 | G59: Nutibara | H59: Medellín | I59: NOROCCIDENTE | J59: Yes | K59: 1 | L59: 10 | M59: 475 | N59: 4750 | P59: =SUMIF($G$3:$G$294,G59,$N$3:$N$294) -> 4750 | Q59: =IF(N59<>0,N59/P59,"0") -> 1 | R59: =VLOOKUP(G59,#REF!,11,0)*Q59 -> #REF! | S59: DC | T59: 1620.75 | U59: 2 | X59: 48 VDC | Y59: 1.5 | Z59: Q1-Q2 | AB59: Transmisores y Receptotes Ópticos | AC59: Se requiere instalar PDB | AE59: SI CONDICIONADA | AH59: =IF(AG59=1,'BU FACILITIES'!$G$24,"") | AI59: PDB | AJ59: 1 | AK59: =AJ59*'BU FACILITIES'!$G$21 -> 1714.6341 | AL59: 1 | AM59: =PRODUCT( AL59,'BU FACILITIES'!$G$22) -> 870.73171 | AP59: =IF(AO59=1,'BU FACILITIES'!$G$23,"") | AS59: =IF(AR59=300,AQ59*'BU FACILITIES'!$G$4, IF(AND(AR59>300,AR59<=500), AQ59*'BU FACILITIES'!$G$5, IF(AND(AR59>500,AR59<=1250), AQ59*'BU FACILITIES'!$G$6, IF(AND(AR59>1250,AR59<=2000),AQ59*'BU FACILITIES'!$G$7, "")))) | AV59: =IF(AU59=100,AT59*'BU FACILITIES'!$G$8, IF(AND(AU59>100,AU59<=500), AT59*'BU FACILITIES'!$G$9, IF(AND(AU59>500,AU59<=800), AT59*'BU FACILITIES'!$G$10, IF(AND(AU59>800,AU59<=1000),AT59*'BU FACILITIES'!$G$11, IF(AND(AU59>1000,AU59<=1400),AT59*'BU FACILITIES'!$G$12, IF(AND(AU59>1400,AU59<=2000),AT59*'BU FACILITIES'!$G$13,"")))))) | AY59: =IF(AX59=30,AW59*'BU FACILITIES'!$G$14, IF(AX59=45, AW59*'BU FACILITIES'!$G$15, IF(AX59=450, AW59*'BU FACILITIES'!$G$16, ""))) | BB59: =IF(AND(BA59>=1,BA59<=5),'BU FACILITIES'!$G$17, IF(AND(BA59>5, BA59<=10), 'BU FACILITIES'!$G$18, IF(AND(BA59>10,BA59<=20),'BU FACILITIES'!$G$19,""))) | BD59: =IF(AND(AZ59="Modificar ductería de AA",BC59=1), 'BU FACILITIES'!$G$20, "")
A60: Plataforma Óptica | B60: BBI-TV-TOIP | C60: Income | D60: Gerencia Acceso Fijo | E60: Jorge Ivan Pérez Cardona | F60: 2023 | G60: Los Balsos | H60: Medellín | I60: NOROCCIDENTE | J60: Yes | K60: 1 | L60: 6 | M60: 475 | N60: 2850 | P60: =SUMIF($G$3:$G$292,G60,$N$3:$N$292) -> 2850 | Q60: =IF(N60<>0,N60/P60,"0") -> 1 | R60: =VLOOKUP(G60,#REF!,11,0)*Q60 -> #REF! | S60: DC | T60: 1620.75 | U60: 2 | X60: 48 VDC | Y60: 1.5 | Z60: Q1-Q2 | AB60: Transmisores y Receptotes Ópticos | AD60: 4 | AE60: SI | AH60: =IF(AG60=1,'BU FACILITIES'!$G$24,"") | AK60: =AJ60*'BU FACILITIES'!$G$21 -> 0 | AL60: 1 | AM60: =PRODUCT( AL60,'BU FACILITIES'!$G$22) -> 870.73171 | AP60: =IF(AO60=1,'BU FACILITIES'!$G$23,"") | AS60: =IF(AR60=300,AQ60*'BU FACILITIES'!$G$4, IF(AND(AR60>300,AR60<=500), AQ60*'BU FACILITIES'!$G$5, IF(AND(AR60>500,AR60<=1250), AQ60*'BU FACILITIES'!$G$6, IF(AND(AR60>1250,AR60<=2000),AQ60*'BU FACILITIES'!$G$7, "")))) | AV60: =IF(AU60=100,AT60*'BU FACILITIES'!$G$8, IF(AND(AU60>100,AU60<=500), AT60*'BU FACILITIES'!$G$9, IF(AND(AU60>500,AU60<=800), AT60*'BU FACILITIES'!$G$10, IF(AND(AU60>800,AU60<=1000),AT60*'BU FACILITIES'!$G$11, IF(AND(AU60>1000,AU60<=1400),AT60*'BU FACILITIES'!$G$12, IF(AND(AU60>1400,AU60<=2000),AT60*'BU FACILITIES'!$G$13,"")))))) | AY60: =IF(AX60=30,AW60*'BU FACILITIES'!$G$14, IF(AX60=45, AW60*'BU FACILITIES'!$G$15, IF(AX60=450, AW60*'BU FACILITIES'!$G$16, ""))) | BB60: =IF(AND(BA60>=1,BA60<=5),'BU FACILITIES'!$G$17, IF(AND(BA60>5, BA60<=10), 'BU FACILITIES'!$G$18, IF(AND(BA60>10,BA60<=20),'BU FACILITIES'!$G$19,""))) | BD60: =IF(AND(AZ60="Modificar ductería de AA",BC60=1), 'BU FACILITIES'!$G$20, "")
A61: Plataforma Óptica | B61: BBI-TV-TOIP | C61: Income | D61: Gerencia Acceso Fijo | E61: Jorge Ivan Pérez Cardona | F61: 2023 | G61: Poblado | H61: Medellín | I61: NOROCCIDENTE | J61: Yes | K61: 1 | L61: 6 | M61: 475 | N61: 0 | P61: =SUMIF($G$3:$G$292,G61,$N$3:$N$292) -> 0 | Q61: =IF(N61<>0,N61/P61,"0") -> 0 | R61: =VLOOKUP(G61,#REF!,11,0)*Q61 -> #REF! | S61: DC | T61: 1620.75 | U61: 2 | X61: 48 VDC | Y61: 1.5 | Z61: Q1-Q2 | AB61: Transmisores y Receptotes Ópticos | AC61: En el cuarto de Multinet, no hay espacio fisico, se requiere crear un nuevo cuarto, se puede utilizar el anterior NEC, en este caso se deben intervenir los ductos de AA y tirar canastillas portacables para fibras y acometidas electricas. | AD61: 3 | AE61: SI CONDICIONADA | AF61: SI | AG61: 1 | AH61: =IF(AG61=1,'BU FACILITIES'!$G$24,"") -> 9756.0976 | AK61: =AJ61*'BU FACILITIES'!$G$21 -> 0 | AL61: 1 | AM61: =PRODUCT( AL61,'BU FACILITIES'!$G$22) -> 870.73171 | AN61: SI | AO61: 1 | AP61: 6000 | AS61: =IF(AR61=300,AQ61*'BU FACILITIES'!$G$4, IF(AND(AR61>300,AR61<=500), AQ61*'BU FACILITIES'!$G$5, IF(AND(AR61>500,AR61<=1250), AQ61*'BU FACILITIES'!$G$6, IF(AND(AR61>1250,AR61<=2000),AQ61*'BU FACILITIES'!$G$7, "")))) | AV61: =IF(AU61=100,AT61*'BU FACILITIES'!$G$8, IF(AND(AU61>100,AU61<=500), AT61*'BU FACILITIES'!$G$9, IF(AND(AU61>500,AU61<=800), AT61*'BU FACILITIES'!$G$10, IF(AND(AU61>800,AU61<=1000),AT61*'BU FACILITIES'!$G$11, IF(AND(AU61>1000,AU61<=1400),AT61*'BU FACILITIES'!$G$12, IF(AND(AU61>1400,AU61<=2000),AT61*'BU FACILITIES'!$G$13,"")))))) | AY61: =IF(AX61=30,AW61*'BU FACILITIES'!$G$14, IF(AX61=45, AW61*'BU FACILITIES'!$G$15, IF(AX61=450, AW61*'BU FACILITIES'!$G$16, ""))) | AZ61: Modificar ductería de AA | BB61: =IF(AND(BA61>=1,BA61<=5),'BU FACILITIES'!$G$17, IF(AND(BA61>5, BA61<=10), 'BU FACILITIES'!$G$18, IF(AND(BA61>10,BA61<=20),'BU FACILITIES'!$G$19,""))) | BC61: 1 | BD61: =IF(AND(AZ61="Modificar ductería de AA",BC61=1), 'BU FACILITIES'!$G$20, "") -> 9756.0976
A62: Plataforma Óptica | B62: BBI-TV-TOIP | C62: Income | D62: Gerencia Acceso Fijo | E62: Jorge Ivan Pérez Cardona | F62: 2023 | G62: Centro Medellín | H62: Medellín | I62: NOROCCIDENTE | J62: Yes | K62: 1 | L62: 6 | M62: 475 | N62: 2850 | P62: =SUMIF($G$3:$G$292,G62,$N$3:$N$292) -> 3450 | Q62: =IF(N62<>0,N62/P62,"0") -> 0.82608696 | R62: =VLOOKUP(G62,#REF!,11,0)*Q62 -> #REF! | S62: DC | T62: 1620.75 | U62: 2 | X62: 48 VDC | Y62: 1.5 | Z62: Q1-Q2 | AB62: Transmisores y Receptotes Ópticos | AC62: Se requiere instalar PDB | AD62: 2 | AE62: SI CONDICIONADA | AH62: =IF(AG62=1,'BU FACILITIES'!$G$24,"") | AI62: PDB | AJ62: 1 | AK62: =AJ62*'BU FACILITIES'!$G$21 -> 1714.6341 | AL62: 1 | AM62: =PRODUCT( AL62,'BU FACILITIES'!$G$22) -> 870.73171 | AP62: =IF(AO62=1,'BU FACILITIES'!$G$23,"") | AS62: =IF(AR62=300,AQ62*'BU FACILITIES'!$G$4, IF(AND(AR62>300,AR62<=500), AQ62*'BU FACILITIES'!$G$5, IF(AND(AR62>500,AR62<=1250), AQ62*'BU FACILITIES'!$G$6, IF(AND(AR62>1250,AR62<=2000),AQ62*'BU FACILITIES'!$G$7, "")))) | AV62: =IF(AU62=100,AT62*'BU FACILITIES'!$G$8, IF(AND(AU62>100,AU62<=500), AT62*'BU FACILITIES'!$G$9, IF(AND(AU62>500,AU62<=800), AT62*'BU FACILITIES'!$G$10, IF(AND(AU62>800,AU62<=1000),AT62*'BU FACILITIES'!$G$11, IF(AND(AU62>1000,AU62<=1400),AT62*'BU FACILITIES'!$G$12, IF(AND(AU62>1400,AU62<=2000),AT62*'BU FACILITIES'!$G$13,"")))))) | AY62: =IF(AX62=30,AW62*'BU FACILITIES'!$G$14, IF(AX62=45, AW62*'BU FACILITIES'!$G$15, IF(AX62=450, AW62*'BU FACILITIES'!$G$16, ""))) | BB62: =IF(AND(BA62>=1,BA62<=5),'BU FACILITIES'!$G$17, IF(AND(BA62>5, BA62<=10), 'BU FACILITIES'!$G$18, IF(AND(BA62>10,BA62<=20),'BU FACILITIES'!$G$19,""))) | BD62: =IF(AND(AZ62="Modificar ductería de AA",BC62=1), 'BU FACILITIES'!$G$20, "")
A63: Plataforma Óptica | B63: BBI-TV-TOIP | C63: Income | D63: Gerencia Acceso Fijo | E63: Jorge Ivan Pérez Cardona | F63: 2023 | G63: Colón | H63: Medellín | I63: NOROCCIDENTE | J63: Yes | K63: 1 | L63: 6 | M63: 475 | N63: 0 | P63: =SUMIF($G$3:$G$292,G63,$N$3:$N$292) -> 2400 | Q63: =IF(N63<>0,N63/P63,"0") -> 0 | R63: =VLOOKUP(G63,#REF!,11,0)*Q63 -> #REF! | S63: DC | T63: 1620.75 | U63: 2 | X63: 48 VDC | Y63: 1.5 | Z63: Q1-Q2 | AB63: Transmisores y Receptotes Ópticos | AD63: 3 | AE63: SI CONDICIONADA | AH63: =IF(AG63=1,'BU FACILITIES'!$G$24,"") | AK63: =AJ63*'BU FACILITIES'!$G$21 -> 0 | AL63: 1 | AM63: =PRODUCT( AL63,'BU FACILITIES'!$G$22) -> 870.73171 | AP63: =IF(AO63=1,'BU FACILITIES'!$G$23,"") | AS63: =IF(AR63=300,AQ63*'BU FACILITIES'!$G$4, IF(AND(AR63>300,AR63<=500), AQ63*'BU FACILITIES'!$G$5, IF(AND(AR63>500,AR63<=1250), AQ63*'BU FACILITIES'!$G$6, IF(AND(AR63>1250,AR63<=2000),AQ63*'BU FACILITIES'!$G$7, "")))) | AV63: =IF(AU63=100,AT63*'BU FACILITIES'!$G$8, IF(AND(AU63>100,AU63<=500), AT63*'BU FACILITIES'!$G$9, IF(AND(AU63>500,AU63<=800), AT63*'BU FACILITIES'!$G$10, IF(AND(AU63>800,AU63<=1000),AT63*'BU FACILITIES'!$G$11, IF(AND(AU63>1000,AU63<=1400),AT63*'BU FACILITIES'!$G$12, IF(AND(AU63>1400,AU63<=2000),AT63*'BU FACILITIES'!$G$13,"")))))) | AY63: =IF(AX63=30,AW63*'BU FACILITIES'!$G$14, IF(AX63=45, AW63*'BU FACILITIES'!$G$15, IF(AX63=450, AW63*'BU FACILITIES'!$G$16, ""))) | BB63: =IF(AND(BA63>=1,BA63<=5),'BU FACILITIES'!$G$17, IF(AND(BA63>5, BA63<=10), 'BU FACILITIES'!$G$18, IF(AND(BA63>10,BA63<=20),'BU FACILITIES'!$G$19,""))) | BD63: =IF(AND(AZ63="Modificar ductería de AA",BC63=1), 'BU FACILITIES'!$G$20, "")
A64: Plataforma Óptica | B64: BBI-TV-TOIP | C64: Income | D64: Gerencia Acceso Fijo | E64: Jorge Ivan Pérez Cardona | F64: 2023 | G64: Guayabal | H64: Medellín | I64: NOROCCIDENTE | J64: Yes | K64: 1 | L64: 6 | M64: 475 | N64: 2850 | P64: =SUMIF($G$3:$G$292,G64,$N$3:$N$292) -> 4050 | Q64: =IF(N64<>0,N64/P64,"0") -> 0.7037037 | R64: =VLOOKUP(G64,#REF!,11,0)*Q64 -> #REF! | S64: DC | T64: 1620.75 | U64: 12 | X64: 48 VDC | Y64: 1.5 | Z64: Q1-Q2 | AB64: Transmisores y Receptotes Ópticos | AC64: Requiere PDB | AD64: 4 | AE64: SI | AH64: =IF(AG64=1,'BU FACILITIES'!$G$24,"") | AI64: PDB | AJ64: 1 | AK64: =AJ64*'BU FACILITIES'!$G$21 -> 1714.6341 | AL64: 1 | AM64: =PRODUCT( AL64,'BU FACILITIES'!$G$22) -> 870.73171 | AP64: =IF(AO64=1,'BU FACILITIES'!$G$23,"") | AS64: =IF(AR64=300,AQ64*'BU FACILITIES'!$G$4, IF(AND(AR64>300,AR64<=500), AQ64*'BU FACILITIES'!$G$5, IF(AND(AR64>500,AR64<=1250), AQ64*'BU FACILITIES'!$G$6, IF(AND(AR64>1250,AR64<=2000),AQ64*'BU FACILITIES'!$G$7, "")))) | AV64: =IF(AU64=100,AT64*'BU FACILITIES'!$G$8, IF(AND(AU64>100,AU64<=500), AT64*'BU FACILITIES'!$G$9, IF(AND(AU64>500,AU64<=800), AT64*'BU FACILITIES'!$G$10, IF(AND(AU64>800,AU64<=1000),AT64*'BU FACILITIES'!$G$11, IF(AND(AU64>1000,AU64<=1400),AT64*'BU FACILITIES'!$G$12, IF(AND(AU64>1400,AU64<=2000),AT64*'BU FACILITIES'!$G$13,"")))))) | AY64: =IF(AX64=30,AW64*'BU FACILITIES'!$G$14, IF(AX64=45, AW64*'BU FACILITIES'!$G$15, IF(AX64=450, AW64*'BU FACILITIES'!$G$16, ""))) | BB64: =IF(AND(BA64>=1,BA64<=5),'BU FACILITIES'!$G$17, IF(AND(BA64>5, BA64<=10), 'BU FACILITIES'!$G$18, IF(AND(BA64>10,BA64<=20),'BU FACILITIES'!$G$19,""))) | BD64: =IF(AND(AZ64="Modificar ductería de AA",BC64=1), 'BU FACILITIES'!$G$20, "")
A65: Plataforma Óptica | B65: BBI-TV-TOIP | C65: Income | D65: Gerencia Acceso Fijo | E65: Jorge Ivan Pérez Cardona | F65: 2023 | G65: Miraflores | H65: Medellín | I65: NOROCCIDENTE | J65: Yes | K65: 1 | L65: 6 | M65: 475 | N65: 2850 | P65: =SUMIF($G$3:$G$292,G65,$N$3:$N$292) -> 7650 | Q65: =IF(N65<>0,N65/P65,"0") -> 0.37254902 | R65: =VLOOKUP(G65,#REF!,11,0)*Q65 -> #REF! | S65: DC | T65: 1620.75 | U65: 2 | X65: 48 VDC | Y65: 1.5 | Z65: Q1-Q2 | AB65: Transmisores y Receptotes Ópticos | AD65: 2 | AE65: SI | AH65: =IF(AG65=1,'BU FACILITIES'!$G$24,"") | AK65: =AJ65*'BU FACILITIES'!$G$21 -> 0 | AL65: 1 | AM65: =PRODUCT( AL65,'BU FACILITIES'!$G$22) -> 870.73171 | AP65: =IF(AO65=1,'BU FACILITIES'!$G$23,"") | AS65: =IF(AR65=300,AQ65*'BU FACILITIES'!$G$4, IF(AND(AR65>300,AR65<=500), AQ65*'BU FACILITIES'!$G$5, IF(AND(AR65>500,AR65<=1250), AQ65*'BU FACILITIES'!$G$6, IF(AND(AR65>1250,AR65<=2000),AQ65*'BU FACILITIES'!$G$7, "")))) | AV65: =IF(AU65=100,AT65*'BU FACILITIES'!$G$8, IF(AND(AU65>100,AU65<=500), AT65*'BU FACILITIES'!$G$9, IF(AND(AU65>500,AU65<=800), AT65*'BU FACILITIES'!$G$10, IF(AND(AU65>800,AU65<=1000),AT65*'BU FACILITIES'!$G$11, IF(AND(AU65>1000,AU65<=1400),AT65*'BU FACILITIES'!$G$12, IF(AND(AU65>1400,AU65<=2000),AT65*'BU FACILITIES'!$G$13,"")))))) | AY65: =IF(AX65=30,AW65*'BU FACILITIES'!$G$14, IF(AX65=45, AW65*'BU FACILITIES'!$G$15, IF(AX65=450, AW65*'BU FACILITIES'!$G$16, ""))) | BB65: =IF(AND(BA65>=1,BA65<=5),'BU FACILITIES'!$G$17, IF(AND(BA65>5, BA65<=10), 'BU FACILITIES'!$G$18, IF(AND(BA65>10,BA65<=20),'BU FACILITIES'!$G$19,""))) | BD65: =IF(AND(AZ65="Modificar ductería de AA",BC65=1), 'BU FACILITIES'!$G$20, "")
A66: Plataforma Óptica | B66: BBI-TV-TOIP | C66: Income | D66: Gerencia Acceso Fijo | E66: Jorge Ivan Pérez Cardona | F66: 2023 | G66: Otrabanda | H66: Medellín | I66: NOROCCIDENTE | J66: Yes | K66: 1 | L66: 6 | M66: 475 | N66: 0 | P66: =SUMIF($G$3:$G$292,G66,$N$3:$N$292) -> 1200 | Q66: =IF(N66<>0,N66/P66,"0") -> 0 | R66: =VLOOKUP(G66,#REF!,11,0)*Q66 -> #REF! | S66: DC | T66: 1620.75 | U66: 2 | X66: 48 VDC | Y66: 1.5 | Z66: Q1-Q2 | AB66: Transmisores y Receptotes Ópticos | AD66: 3 | AE66: SI CONDICIONADA | AH66: =IF(AG66=1,'BU FACILITIES'!$G$24,"") | AK66: =AJ66*'BU FACILITIES'!$G$21 -> 0 | AL66: 1 | AM66: =PRODUCT( AL66,'BU FACILITIES'!$G$22) -> 870.73171 | AP66: =IF(AO66=1,'BU FACILITIES'!$G$23,"") | AS66: =IF(AR66=300,AQ66*'BU FACILITIES'!$G$4, IF(AND(AR66>300,AR66<=500), AQ66*'BU FACILITIES'!$G$5, IF(AND(AR66>500,AR66<=1250), AQ66*'BU FACILITIES'!$G$6, IF(AND(AR66>1250,AR66<=2000),AQ66*'BU FACILITIES'!$G$7, "")))) | AV66: =IF(AU66=100,AT66*'BU FACILITIES'!$G$8, IF(AND(AU66>100,AU66<=500), AT66*'BU FACILITIES'!$G$9, IF(AND(AU66>500,AU66<=800), AT66*'BU FACILITIES'!$G$10, IF(AND(AU66>800,AU66<=1000),AT66*'BU FACILITIES'!$G$11, IF(AND(AU66>1000,AU66<=1400),AT66*'BU FACILITIES'!$G$12, IF(AND(AU66>1400,AU66<=2000),AT66*'BU FACILITIES'!$G$13,"")))))) | AY66: =IF(AX66=30,AW66*'BU FACILITIES'!$G$14, IF(AX66=45, AW66*'BU FACILITIES'!$G$15, IF(AX66=450, AW66*'BU FACILITIES'!$G$16, ""))) | AZ66: Modificar ductería de AA | BB66: =IF(AND(BA66>=1,BA66<=5),'BU FACILITIES'!$G$17, IF(AND(BA66>5, BA66<=10), 'BU FACILITIES'!$G$18, IF(AND(BA66>10,BA66<=20),'BU FACILITIES'!$G$19,""))) | BC66: 1 | BD66: =IF(AND(AZ66="Modificar ductería de AA",BC66=1), 'BU FACILITIES'!$G$20, "") -> 9756.0976
A67: Plataforma Óptica | B67: BBI-TV-TOIP | C67: Income | D67: Gerencia Acceso Fijo | E67: Jorge Ivan Pérez Cardona | F67: 2023 | G67: Villa Hermosa | H67: Medellín | I67: NOROCCIDENTE | J67: Yes | K67: 1 | L67: 6 | M67: 475 | N67: 2850 | P67: =SUMIF($G$3:$G$292,G67,$N$3:$N$292) -> 4050 | Q67: =IF(N67<>0,N67/P67,"0") -> 0.7037037 | R67: =VLOOKUP(G67,#REF!,11,0)*Q67 -> #REF! | S67: DC | T67: 1620.75 | U67: 2 | X67: 48 VDC | Y67: 1.5 | Z67: Q1-Q2 | AB67: Transmisores y Receptotes Ópticos | AC67: En sala Multinet primer piso condicionado al montaje de AA 2022 proyecto Carlos. En sala del segundo piso se desmontaron los equipos y este cuarto queda cerrado | AD67: 5 | AE67: SI CONDICIONADA | AH67: =IF(AG67=1,'BU FACILITIES'!$G$24,"") | AK67: =AJ67*'BU FACILITIES'!$G$21 -> 0 | AL67: 1 | AM67: =PRODUCT( AL67,'BU FACILITIES'!$G$22) -> 870.73171 | AP67: =IF(AO67=1,'BU FACILITIES'!$G$23,"") | AS67: =IF(AR67=300,AQ67*'BU FACILITIES'!$G$4, IF(AND(AR67>300,AR67<=500), AQ67*'BU FACILITIES'!$G$5, IF(AND(AR67>500,AR67<=1250), AQ67*'BU FACILITIES'!$G$6, IF(AND(AR67>1250,AR67<=2000),AQ67*'BU FACILITIES'!$G$7, "")))) | AV67: =IF(AU67=100,AT67*'BU FACILITIES'!$G$8, IF(AND(AU67>100,AU67<=500), AT67*'BU FACILITIES'!$G$9, IF(AND(AU67>500,AU67<=800), AT67*'BU FACILITIES'!$G$10, IF(AND(AU67>800,AU67<=1000),AT67*'BU FACILITIES'!$G$11, IF(AND(AU67>1000,AU67<=1400),AT67*'BU FACILITIES'!$G$12, IF(AND(AU67>1400,AU67<=2000),AT67*'BU FACILITIES'!$G$13,"")))))) | AY67: =IF(AX67=30,AW67*'BU FACILITIES'!$G$14, IF(AX67=45, AW67*'BU FACILITIES'!$G$15, IF(AX67=450, AW67*'BU FACILITIES'!$G$16, ""))) | BB67: =IF(AND(BA67>=1,BA67<=5),'BU FACILITIES'!$G$17, IF(AND(BA67>5, BA67<=10), 'BU FACILITIES'!$G$18, IF(AND(BA67>10,BA67<=20),'BU FACILITIES'!$G$19,""))) | BD67: =IF(AND(AZ67="Modificar ductería de AA",BC67=1), 'BU FACILITIES'!$G$20, "")
A68: Plataforma Óptica | B68: BBI-TV-TOIP | C68: Income | D68: Gerencia Acceso Fijo | E68: Jorge Ivan Pérez Cardona | F68: 2023 | G68: San Antonio de Prado | H68: Medellín | I68: NOROCCIDENTE | J68: Yes | K68: 1 | L68: 6 | M68: 475 | N68: 2850 | P68: =SUMIF($G$3:$G$292,G68,$N$3:$N$292) -> 2850 | Q68: =IF(N68<>0,N68/P68,"0") -> 1 | R68: =VLOOKUP(G68,#REF!,11,0)*Q68 -> #REF! | S68: DC | T68: 1620.75 | U68: 2 | X68: 48 VDC | Y68: 1.5 | Z68: Q1-Q2 | AB68: Transmisores y Receptotes Ópticos | AE68: SI | AH68: =IF(AG68=1,'BU FACILITIES'!$G$24,"") | AK68: =AJ68*'BU FACILITIES'!$G$21 -> 0 | AL68: 1 | AM68: =PRODUCT( AL68,'BU FACILITIES'!$G$22) -> 870.73171 | AP68: =IF(AO68=1,'BU FACILITIES'!$G$23,"") | AS68: =IF(AR68=300,AQ68*'BU FACILITIES'!$G$4, IF(AND(AR68>300,AR68<=500), AQ68*'BU FACILITIES'!$G$5, IF(AND(AR68>500,AR68<=1250), AQ68*'BU FACILITIES'!$G$6, IF(AND(AR68>1250,AR68<=2000),AQ68*'BU FACILITIES'!$G$7, "")))) | AV68: =IF(AU68=100,AT68*'BU FACILITIES'!$G$8, IF(AND(AU68>100,AU68<=500), AT68*'BU FACILITIES'!$G$9, IF(AND(AU68>500,AU68<=800), AT68*'BU FACILITIES'!$G$10, IF(AND(AU68>800,AU68<=1000),AT68*'BU FACILITIES'!$G$11, IF(AND(AU68>1000,AU68<=1400),AT68*'BU FACILITIES'!$G$12, IF(AND(AU68>1400,AU68<=2000),AT68*'BU FACILITIES'!$G$13,"")))))) | AY68: =IF(AX68=30,AW68*'BU FACILITIES'!$G$14, IF(AX68=45, AW68*'BU FACILITIES'!$G$15, IF(AX68=450, AW68*'BU FACILITIES'!$G$16, ""))) | BB68: =IF(AND(BA68>=1,BA68<=5),'BU FACILITIES'!$G$17, IF(AND(BA68>5, BA68<=10), 'BU FACILITIES'!$G$18, IF(AND(BA68>10,BA68<=20),'BU FACILITIES'!$G$19,""))) | BD68: =IF(AND(AZ68="Modificar ductería de AA",BC68=1), 'BU FACILITIES'!$G$20, "")
A69: Plataforma Óptica | B69: BBI-TV-TOIP | C69: Income | D69: Gerencia Acceso Fijo | E69: Jorge Ivan Pérez Cardona | F69: 2023 | G69: Caldas | H69: Caldas | I69: NOROCCIDENTE | J69: Yes | K69: 1 | L69: 6 | M69: 475 | N69: 2850 | P69: =SUMIF($G$3:$G$292,G69,$N$3:$N$292) -> 2850 | Q69: =IF(N69<>0,N69/P69,"0") -> 1 | R69: =VLOOKUP(G69,#REF!,11,0)*Q69 -> #REF! | S69: DC | T69: 1620.75 | U69: 12 | X69: 48 VDC | Y69: 1.5 | Z69: Q1-Q2 | AB69: Transmisores y Receptotes Ópticos | AC69: Condicionado, requiere montar PBD | AD69: 5 | AE69: SI CONDICIONADA | AH69: =IF(AG69=1,'BU FACILITIES'!$G$24,"") | AI69: PDB | AJ69: 1 | AK69: =AJ69*'BU FACILITIES'!$G$21 -> 1714.6341 | AL69: 1 | AM69: =PRODUCT( AL69,'BU FACILITIES'!$G$22) -> 870.73171 | AP69: =IF(AO69=1,'BU FACILITIES'!$G$23,"") | AS69: =IF(AR69=300,AQ69*'BU FACILITIES'!$G$4, IF(AND(AR69>300,AR69<=500), AQ69*'BU FACILITIES'!$G$5, IF(AND(AR69>500,AR69<=1250), AQ69*'BU FACILITIES'!$G$6, IF(AND(AR69>1250,AR69<=2000),AQ69*'BU FACILITIES'!$G$7, "")))) | AV69: =IF(AU69=100,AT69*'BU FACILITIES'!$G$8, IF(AND(AU69>100,AU69<=500), AT69*'BU FACILITIES'!$G$9, IF(AND(AU69>500,AU69<=800), AT69*'BU FACILITIES'!$G$10, IF(AND(AU69>800,AU69<=1000),AT69*'BU FACILITIES'!$G$11, IF(AND(AU69>1000,AU69<=1400),AT69*'BU FACILITIES'!$G$12, IF(AND(AU69>1400,AU69<=2000),AT69*'BU FACILITIES'!$G$13,"")))))) | AY69: =IF(AX69=30,AW69*'BU FACILITIES'!$G$14, IF(AX69=45, AW69*'BU FACILITIES'!$G$15, IF(AX69=450, AW69*'BU FACILITIES'!$G$16, ""))) | BB69: =IF(AND(BA69>=1,BA69<=5),'BU FACILITIES'!$G$17, IF(AND(BA69>5, BA69<=10), 'BU FACILITIES'!$G$18, IF(AND(BA69>10,BA69<=20),'BU FACILITIES'!$G$19,""))) | BD69: =IF(AND(AZ69="Modificar ductería de AA",BC69=1), 'BU FACILITIES'!$G$20, "")
A70: Plataforma Óptica | B70: BBI-TV-TOIP | C70: Income | D70: Gerencia Acceso Fijo | E70: Jorge Ivan Pérez Cardona | F70: 2023 | G70: El Retiro | H70: El Retiro | I70: NOROCCIDENTE | J70: Yes | K70: 1 | L70: 6 | M70: 475 | N70: 2850 | P70: =SUMIF($G$3:$G$292,G70,$N$3:$N$292) -> 2850 | Q70: =IF(N70<>0,N70/P70,"0") -> 1 | R70: =VLOOKUP(G70,#REF!,11,0)*Q70 -> #REF! | S70: DC | T70: 1620.75 | U70: 2 | X70: 48 VDC | Y70: 1.5 | Z70: Q1-Q2 | AB70: Transmisores y Receptotes Ópticos | AC70: Se requiene instalar PDB | AD70: 5 | AE70: SI CONDICIONADA | AH70: =IF(AG70=1,'BU FACILITIES'!$G$24,"") | AI70: PDB | AJ70: 1 | AK70: =AJ70*'BU FACILITIES'!$G$21 -> 1714.6341 | AL70: 1 | AM70: =PRODUCT( AL70,'BU FACILITIES'!$G$22) -> 870.73171 | AP70: =IF(AO70=1,'BU FACILITIES'!$G$23,"") | AS70: =IF(AR70=300,AQ70*'BU FACILITIES'!$G$4, IF(AND(AR70>300,AR70<=500), AQ70*'BU FACILITIES'!$G$5, IF(AND(AR70>500,AR70<=1250), AQ70*'BU FACILITIES'!$G$6, IF(AND(AR70>1250,AR70<=2000),AQ70*'BU FACILITIES'!$G$7, "")))) | AV70: =IF(AU70=100,AT70*'BU FACILITIES'!$G$8, IF(AND(AU70>100,AU70<=500), AT70*'BU FACILITIES'!$G$9, IF(AND(AU70>500,AU70<=800), AT70*'BU FACILITIES'!$G$10, IF(AND(AU70>800,AU70<=1000),AT70*'BU FACILITIES'!$G$11, IF(AND(AU70>1000,AU70<=1400),AT70*'BU FACILITIES'!$G$12, IF(AND(AU70>1400,AU70<=2000),AT70*'BU FACILITIES'!$G$13,"")))))) | AY70: =IF(AX70=30,AW70*'BU FACILITIES'!$G$14, IF(AX70=45, AW70*'BU FACILITIES'!$G$15, IF(AX70=450, AW70*'BU FACILITIES'!$G$16, ""))) | BB70: =IF(AND(BA70>=1,BA70<=5),'BU FACILITIES'!$G$17, IF(AND(BA70>5, BA70<=10), 'BU FACILITIES'!$G$18, IF(AND(BA70>10,BA70<=20),'BU FACILITIES'!$G$19,""))) | BD70: =IF(AND(AZ70="Modificar ductería de AA",BC70=1), 'BU FACILITIES'!$G$20, "")
A71: Plataforma Óptica | B71: BBI-TV-TOIP | C71: Income | D71: Gerencia Acceso Fijo | E71: Jorge Ivan Pérez Cardona | F71: 2023 | G71: Envigado | H71: Envigado | I71: NOROCCIDENTE | J71: Yes | K71: 2 | L71: 10 | M71: 475 | N71: 0 | P71: =SUMIF($G$3:$G$292,G71,$N$3:$N$292) -> 1200 | Q71: =IF(N71<>0,N71/P71,"0") -> 0 | R71: =VLOOKUP(G71,#REF!,11,0)*Q71 -> #REF! | S71: DC | T71: 1620.75 | U71: 4 | X71: 48 VDC | Y71: 3 | Z71: Q1-Q2 | AB71: Transmisores y Receptotes Ópticos | AC71: Espacio dsiponible en multinet primer piso, condicionado al desmonte de la central NEC que se apago en el proyecto de desmonte de centrales. Se requiere acondicionar ductería AA. Se requiere montar PBD | AD71: 3 | AE71: SI CONDICIONADA | AH71: =IF(AG71=1,'BU FACILITIES'!$G$24,"") | AI71: PDB | AJ71: 1 | AK71: =AJ71*'BU FACILITIES'!$G$21 -> 1714.6341 | AL71: 1 | AM71: =PRODUCT( AL71,'BU FACILITIES'!$G$22) -> 870.73171 | AP71: =IF(AO71=1,'BU FACILITIES'!$G$23,"") | AS71: =IF(AR71=300,AQ71*'BU FACILITIES'!$G$4, IF(AND(AR71>300,AR71<=500), AQ71*'BU FACILITIES'!$G$5, IF(AND(AR71>500,AR71<=1250), AQ71*'BU FACILITIES'!$G$6, IF(AND(AR71>1250,AR71<=2000),AQ71*'BU FACILITIES'!$G$7, "")))) | AV71: =IF(AU71=100,AT71*'BU FACILITIES'!$G$8, IF(AND(AU71>100,AU71<=500), AT71*'BU FACILITIES'!$G$9, IF(AND(AU71>500,AU71<=800), AT71*'BU FACILITIES'!$G$10, IF(AND(AU71>800,AU71<=1000),AT71*'BU FACILITIES'!$G$11, IF(AND(AU71>1000,AU71<=1400),AT71*'BU FACILITIES'!$G$12, IF(AND(AU71>1400,AU71<=2000),AT71*'BU FACILITIES'!$G$13,"")))))) | AY71: =IF(AX71=30,AW71*'BU FACILITIES'!$G$14, IF(AX71=45, AW71*'BU FACILITIES'!$G$15, IF(AX71=450, AW71*'BU FACILITIES'!$G$16, ""))) | AZ71: Modificar ductería de AA | BB71: =IF(AND(BA71>=1,BA71<=5),'BU FACILITIES'!$G$17, IF(AND(BA71>5, BA71<=10), 'BU FACILITIES'!$G$18, IF(AND(BA71>10,BA71<=20),'BU FACILITIES'!$G$19,""))) | BC71: 1 | BD71: =IF(AND(AZ71="Modificar ductería de AA",BC71=1), 'BU FACILITIES'!$G$20, "") -> 9756.0976
A72: Plataforma Óptica | B72: BBI-TV-TOIP | C72: Income | D72: Gerencia Acceso Fijo | E72: Jorge Ivan Pérez Cardona | F72: 2023 | G72: Itagui | H72: Itagui | I72: NOROCCIDENTE | J72: Yes | K72: 1 | L72: 6 | M72: 475 | N72: 2850 | P72: =SUMIF($G$3:$G$292,G72,$N$3:$N$292) -> 3450 | Q72: =IF(N72<>0,N72/P72,"0") -> 0.82608696 | R72: =VLOOKUP(G72,#REF!,11,0)*Q72 -> #REF! | S72: DC | T72: 1620.75 | U72: 2 | X72: 48 VDC | Y72: 1.5 | Z72: Q1-Q2 | AB72: Transmisores y Receptotes Ópticos | AD72: 3 | AE72: SI | AH72: =IF(AG72=1,'BU FACILITIES'!$G$24,"") | AK72: =AJ72*'BU FACILITIES'!$G$21 -> 0 | AL72: 1 | AM72: =PRODUCT( AL72,'BU FACILITIES'!$G$22) -> 870.73171 | AP72: =IF(AO72=1,'BU FACILITIES'!$G$23,"") | AS72: =IF(AR72=300,AQ72*'BU FACILITIES'!$G$4, IF(AND(AR72>300,AR72<=500), AQ72*'BU FACILITIES'!$G$5, IF(AND(AR72>500,AR72<=1250), AQ72*'BU FACILITIES'!$G$6, IF(AND(AR72>1250,AR72<=2000),AQ72*'BU FACILITIES'!$G$7, "")))) | AV72: =IF(AU72=100,AT72*'BU FACILITIES'!$G$8, IF(AND(AU72>100,AU72<=500), AT72*'BU FACILITIES'!$G$9, IF(AND(AU72>500,AU72<=800), AT72*'BU FACILITIES'!$G$10, IF(AND(AU72>800,AU72<=1000),AT72*'BU FACILITIES'!$G$11, IF(AND(AU72>1000,AU72<=1400),AT72*'BU FACILITIES'!$G$12, IF(AND(AU72>1400,AU72<=2000),AT72*'BU FACILITIES'!$G$13,"")))))) | AY72: =IF(AX72=30,AW72*'BU FACILITIES'!$G$14, IF(AX72=45, AW72*'BU FACILITIES'!$G$15, IF(AX72=450, AW72*'BU FACILITIES'!$G$16, ""))) | BB72: =IF(AND(BA72>=1,BA72<=5),'BU FACILITIES'!$G$17, IF(AND(BA72>5, BA72<=10), 'BU FACILITIES'!$G$18, IF(AND(BA72>10,BA72<=20),'BU FACILITIES'!$G$19,""))) | BD72: =IF(AND(AZ72="Modificar ductería de AA",BC72=1), 'BU FACILITIES'!$G$20, "")
A73: Plataforma Óptica | B73: BBI-TV-TOIP | C73: Income | D73: Gerencia Acceso Fijo | E73: Jorge Ivan Pérez Cardona | F73: 2023 | G73: La Ceja | H73: La Ceja | I73: NOROCCIDENTE | J73: Yes | K73: 1 | L73: 6 | M73: 475 | N73: 2850 | P73: =SUMIF($G$3:$G$292,G73,$N$3:$N$292) -> 4050 | Q73: =IF(N73<>0,N73/P73,"0") -> 0.7037037 | R73: =VLOOKUP(G73,#REF!,11,0)*Q73 -> #REF! | S73: DC | T73: 1620.75 | U73: 2 | X73: 48 VDC | Y73: 1.5 | Z73: Q1-Q2 | AB73: Transmisores y Receptotes Ópticos | AD73: 4 | AE73: SI | AH73: =IF(AG73=1,'BU FACILITIES'!$G$24,"") | AK73: =AJ73*'BU FACILITIES'!$G$21 -> 0 | AL73: 1 | AM73: =PRODUCT( AL73,'BU FACILITIES'!$G$22) -> 870.73171 | AP73: =IF(AO73=1,'BU FACILITIES'!$G$23,"") | AS73: =IF(AR73=300,AQ73*'BU FACILITIES'!$G$4, IF(AND(AR73>300,AR73<=500), AQ73*'BU FACILITIES'!$G$5, IF(AND(AR73>500,AR73<=1250), AQ73*'BU FACILITIES'!$G$6, IF(AND(AR73>1250,AR73<=2000),AQ73*'BU FACILITIES'!$G$7, "")))) | AV73: =IF(AU73=100,AT73*'BU FACILITIES'!$G$8, IF(AND(AU73>100,AU73<=500), AT73*'BU FACILITIES'!$G$9, IF(AND(AU73>500,AU73<=800), AT73*'BU FACILITIES'!$G$10, IF(AND(AU73>800,AU73<=1000),AT73*'BU FACILITIES'!$G$11, IF(AND(AU73>1000,AU73<=1400),AT73*'BU FACILITIES'!$G$12, IF(AND(AU73>1400,AU73<=2000),AT73*'BU FACILITIES'!$G$13,"")))))) | AY73: =IF(AX73=30,AW73*'BU FACILITIES'!$G$14, IF(AX73=45, AW73*'BU FACILITIES'!$G$15, IF(AX73=450, AW73*'BU FACILITIES'!$G$16, ""))) | BB73: =IF(AND(BA73>=1,BA73<=5),'BU FACILITIES'!$G$17, IF(AND(BA73>5, BA73<=10), 'BU FACILITIES'!$G$18, IF(AND(BA73>10,BA73<=20),'BU FACILITIES'!$G$19,""))) | BD73: =IF(AND(AZ73="Modificar ductería de AA",BC73=1), 'BU FACILITIES'!$G$20, "")
A74: Plataforma Óptica | B74: BBI-TV-TOIP | C74: Income | D74: Gerencia Acceso Fijo | E74: Jorge Ivan Pérez Cardona | F74: 2023 | G74: La Estrella | H74: La Estrella | I74: NOROCCIDENTE | J74: Yes | K74: 1 | L74: 6 | M74: 475 | N74: 2850 | P74: =SUMIF($G$3:$G$292,G74,$N$3:$N$292) -> 4050 | Q74: =IF(N74<>0,N74/P74,"0") -> 0.7037037 | R74: =VLOOKUP(G74,#REF!,11,0)*Q74 -> #REF! | S74: DC | T74: 1620.75 | U74: 2 | X74: 48 VDC | Y74: 1.5 | Z74: Q1-Q2 | AB74: Transmisores y Receptotes Ópticos | AC74: Requiere PBD | AE74: SI CONDICIONADA | AH74: =IF(AG74=1,'BU FACILITIES'!$G$24,"") | AI74: PDB | AJ74: 1 | AK74: =AJ74*'BU FACILITIES'!$G$21 -> 1714.6341 | AL74: 1 | AM74: =PRODUCT( AL74,'BU FACILITIES'!$G$22) -> 870.73171 | AP74: =IF(AO74=1,'BU FACILITIES'!$G$23,"") | AS74: =IF(AR74=300,AQ74*'BU FACILITIES'!$G$4, IF(AND(AR74>300,AR74<=500), AQ74*'BU FACILITIES'!$G$5, IF(AND(AR74>500,AR74<=1250), AQ74*'BU FACILITIES'!$G$6, IF(AND(AR74>1250,AR74<=2000),AQ74*'BU FACILITIES'!$G$7, "")))) | AV74: =IF(AU74=100,AT74*'BU FACILITIES'!$G$8, IF(AND(AU74>100,AU74<=500), AT74*'BU FACILITIES'!$G$9, IF(AND(AU74>500,AU74<=800), AT74*'BU FACILITIES'!$G$10, IF(AND(AU74>800,AU74<=1000),AT74*'BU FACILITIES'!$G$11, IF(AND(AU74>1000,AU74<=1400),AT74*'BU FACILITIES'!$G$12, IF(AND(AU74>1400,AU74<=2000),AT74*'BU FACILITIES'!$G$13,"")))))) | AY74: =IF(AX74=30,AW74*'BU FACILITIES'!$G$14, IF(AX74=45, AW74*'BU FACILITIES'!$G$15, IF(AX74=450, AW74*'BU FACILITIES'!$G$16, ""))) | BB74: =IF(AND(BA74>=1,BA74<=5),'BU FACILITIES'!$G$17, IF(AND(BA74>5, BA74<=10), 'BU FACILITIES'!$G$18, IF(AND(BA74>10,BA74<=20),'BU FACILITIES'!$G$19,""))) | BD74: =IF(AND(AZ74="Modificar ductería de AA",BC74=1), 'BU FACILITIES'!$G$20, "")
A75: Plataforma Óptica | B75: BBI-TV-TOIP | C75: Income | D75: Gerencia Acceso Fijo | E75: Jorge Ivan Pérez Cardona | F75: 2023 | G75: Sabaneta | H75: Sabaneta | I75: NOROCCIDENTE | J75: Yes | K75: 1 | L75: 6 | M75: 475 | N75: 2850 | P75: =SUMIF($G$3:$G$292,G75,$N$3:$N$292) -> 4650 | Q75: =IF(N75<>0,N75/P75,"0") -> 0.61290323 | R75: =VLOOKUP(G75,#REF!,11,0)*Q75 -> #REF! | S75: DC | T75: 1620.75 | U75: 2 | X75: 48 VDC | Y75: 1.5 | Z75: Q1-Q2 | AB75: Transmisores y Receptotes Ópticos | AC75: Confinar area para AA | AD75: 4 | AE75: SI | AH75: =IF(AG75=1,'BU FACILITIES'!$G$24,"") | AK75: =AJ75*'BU FACILITIES'!$G$21 -> 0 | AL75: 1 | AM75: =PRODUCT( AL75,'BU FACILITIES'!$G$22) -> 870.73171 | AP75: =IF(AO75=1,'BU FACILITIES'!$G$23,"") | AS75: =IF(AR75=300,AQ75*'BU FACILITIES'!$G$4, IF(AND(AR75>300,AR75<=500), AQ75*'BU FACILITIES'!$G$5, IF(AND(AR75>500,AR75<=1250), AQ75*'BU FACILITIES'!$G$6, IF(AND(AR75>1250,AR75<=2000),AQ75*'BU FACILITIES'!$G$7, "")))) | AV75: =IF(AU75=100,AT75*'BU FACILITIES'!$G$8, IF(AND(AU75>100,AU75<=500), AT75*'BU FACILITIES'!$G$9, IF(AND(AU75>500,AU75<=800), AT75*'BU FACILITIES'!$G$10, IF(AND(AU75>800,AU75<=1000),AT75*'BU FACILITIES'!$G$11, IF(AND(AU75>1000,AU75<=1400),AT75*'BU FACILITIES'!$G$12, IF(AND(AU75>1400,AU75<=2000),AT75*'BU FACILITIES'!$G$13,"")))))) | AY75: =IF(AX75=30,AW75*'BU FACILITIES'!$G$14, IF(AX75=45, AW75*'BU FACILITIES'!$G$15, IF(AX75=450, AW75*'BU FACILITIES'!$G$16, ""))) | BB75: =IF(AND(BA75>=1,BA75<=5),'BU FACILITIES'!$G$17, IF(AND(BA75>5, BA75<=10), 'BU FACILITIES'!$G$18, IF(AND(BA75>10,BA75<=20),'BU FACILITIES'!$G$19,""))) | BD75: =IF(AND(AZ75="Modificar ductería de AA",BC75=1), 'BU FACILITIES'!$G$20, "")
A76: Plataforma Óptica | B76: BBI-TV-TOIP | C76: Income | D76: Gerencia Acceso Fijo | E76: Jorge Ivan Pérez Cardona | F76: 2023 | G76: Rionegro | H76: Rionegro | I76: NOROCCIDENTE | J76: Yes | K76: 1 | L76: 6 | M76: 475 | N76: 0 | P76: =SUMIF($G$3:$G$292,G76,$N$3:$N$292) -> 0 | Q76: =IF(N76<>0,N76/P76,"0") -> 0 | R76: =VLOOKUP(G76,#REF!,11,0)*Q76 -> #REF! | S76: DC | T76: 1620.75 | U76: 2 | X76: 48 VDC | Y76: 1.5 | Z76: Q1-Q2 | AB76: Transmisores y Receptotes Ópticos | AC76: Se condiciona a la posibilidad de acdecuar un nuevo espacio, en las actuales salas no hay capacidad fisica para nuevos racks, como opción verificar si hay racks que ya no esten en servicio. Solo tiene rectificadores Shindenguen y Ericsson, cambio por obsolescencia. | AD76: 3 | AE76: SI CONDICIONADA | AF76: Iluminación | AG76: 1 | AH76: =IF(AG76=1,'BU FACILITIES'!$G$24,"") -> 9756.0976 | AI76: PDB | AJ76: 1 | AK76: =AJ76*'BU FACILITIES'!$G$21 -> 1714.6341 | AL76: 1 | AM76: =PRODUCT( AL76,'BU FACILITIES'!$G$22) -> 870.73171 | AN76: Adecuar nuevo espacio | AO76: 1 | AP76: =IF(AO76=1,'BU FACILITIES'!$G$23,"") -> 24390.244 | AQ76: 0.2 | AR76: 2000 | AS76: =IF(AR76=300,AQ76*'BU FACILITIES'!$G$4, IF(AND(AR76>300,AR76<=500), AQ76*'BU FACILITIES'!$G$5, IF(AND(AR76>500,AR76<=1250), AQ76*'BU FACILITIES'!$G$6, IF(AND(AR76>1250,AR76<=2000),AQ76*'BU FACILITIES'!$G$7, "")))) -> 4772.4976 | AT76: 2.5 | AU76: 2000 | AV76: =IF(AU76=100,AT76*'BU FACILITIES'!$G$8, IF(AND(AU76>100,AU76<=500), AT76*'BU FACILITIES'!$G$9, IF(AND(AU76>500,AU76<=800), AT76*'BU FACILITIES'!$G$10, IF(AND(AU76>800,AU76<=1000),AT76*'BU FACILITIES'!$G$11, IF(AND(AU76>1000,AU76<=1400),AT76*'BU FACILITIES'!$G$12, IF(AND(AU76>1400,AU76<=2000),AT76*'BU FACILITIES'!$G$13,"")))))) -> 53630.016 | AY76: =IF(AX76=30,AW76*'BU FACILITIES'!$G$14, IF(AX76=45, AW76*'BU FACILITIES'!$G$15, IF(AX76=450, AW76*'BU FACILITIES'!$G$16, ""))) | AZ76: Modificar ductería de AA | BB76: =IF(AND(BA76>=1,BA76<=5),'BU FACILITIES'!$G$17, IF(AND(BA76>5, BA76<=10), 'BU FACILITIES'!$G$18, IF(AND(BA76>10,BA76<=20),'BU FACILITIES'!$G$19,""))) | BC76: 1 | BD76: =IF(AND(AZ76="Modificar ductería de AA",BC76=1), 'BU FACILITIES'!$G$20, "") -> 9756.0976
A77: Plataforma Óptica | B77: BBI-TV-TOIP | C77: Income | D77: Gerencia Acceso Fijo | E77: Jorge Ivan Pérez Cardona | F77: 2023 | G77: Prado Office center | H77: Barranquilla | J77: Yes | K77: 3 | L77: 8 | M77: 475 | N77: 3800 | P77: =SUMIF($G$3:$G$292,G77,$N$3:$N$292) -> 3800 | Q77: =IF(N77<>0,N77/P77,"0") -> 1 | R77: =VLOOKUP(G77,#REF!,11,0)*Q77 -> #REF! | S77: DC | T77: 1620.75 | U77: 6 | X77: 48 VDC | Y77: 4.5 | Z77: Q1-Q2 | AB77: Transmisores y Receptotes Ópticos | AC77: Incluir cableado, protecciones, tendidos, canaletas, tuberías, etc | AD77: 4 | AE77: SI | AH77: =IF(AG77=1,'BU FACILITIES'!$G$24,"") | AI77: SI | AJ77: 1 | AK77: =AJ77*'BU FACILITIES'!$G$21 -> 1714.6341 | AL77: 1 | AM77: =PRODUCT( AL77,'BU FACILITIES'!$G$22) -> 870.73171 | AP77: =IF(AO77=1,'BU FACILITIES'!$G$23,"") | AS77: =IF(AR77=300,AQ77*'BU FACILITIES'!$G$4, IF(AND(AR77>300,AR77<=500), AQ77*'BU FACILITIES'!$G$5, IF(AND(AR77>500,AR77<=1250), AQ77*'BU FACILITIES'!$G$6, IF(AND(AR77>1250,AR77<=2000),AQ77*'BU FACILITIES'!$G$7, "")))) | AV77: =IF(AU77=100,AT77*'BU FACILITIES'!$G$8, IF(AND(AU77>100,AU77<=500), AT77*'BU FACILITIES'!$G$9, IF(AND(AU77>500,AU77<=800), AT77*'BU FACILITIES'!$G$10, IF(AND(AU77>800,AU77<=1000),AT77*'BU FACILITIES'!$G$11, IF(AND(AU77>1000,AU77<=1400),AT77*'BU FACILITIES'!$G$12, IF(AND(AU77>1400,AU77<=2000),AT77*'BU FACILITIES'!$G$13,"")))))) | AY77: =IF(AX77=30,AW77*'BU FACILITIES'!$G$14, IF(AX77=45, AW77*'BU FACILITIES'!$G$15, IF(AX77=450, AW77*'BU FACILITIES'!$G$16, ""))) | BB77: =IF(AND(BA77>=1,BA77<=5),'BU FACILITIES'!$G$17, IF(AND(BA77>5, BA77<=10), 'BU FACILITIES'!$G$18, IF(AND(BA77>10,BA77<=20),'BU FACILITIES'!$G$19,""))) | BD77: =IF(AND(AZ77="Modificar ductería de AA",BC77=1), 'BU FACILITIES'!$G$20, "")
A78: Plataforma Óptica | B78: BBI-TV-TOIP | C78: Income | D78: Gerencia Acceso Fijo | E78: Jorge Ivan Pérez Cardona | F78: 2023 | G78: Simon Bolivar Bquilla | H78: Barranquilla | J78: Yes | K78: 2 | L78: 6 | M78: 475 | N78: 2850 | P78: =SUMIF($G$3:$G$292,G78,$N$3:$N$292) -> 2850 | Q78: =IF(N78<>0,N78/P78,"0") -> 1 | R78: =VLOOKUP(G78,#REF!,11,0)*Q78 -> #REF! | S78: DC | T78: 1620.75 | U78: 4 | X78: 48 VDC | Y78: 3 | Z78: Q1-Q2 | AB78: Transmisores y Receptotes Ópticos | AC78: Incluir cableado, protecciones, tendidos, canaletas, tuberías, etc | AD78: 3 | AE78: SI | AH78: =IF(AG78=1,'BU FACILITIES'!$G$24,"") | AI78: SI | AJ78: 1 | AK78: =AJ78*'BU FACILITIES'!$G$21 -> 1714.6341 | AL78: 1 | AM78: =PRODUCT( AL78,'BU FACILITIES'!$G$22) -> 870.73171 | AP78: =IF(AO78=1,'BU FACILITIES'!$G$23,"") | AS78: =IF(AR78=300,AQ78*'BU FACILITIES'!$G$4, IF(AND(AR78>300,AR78<=500), AQ78*'BU FACILITIES'!$G$5, IF(AND(AR78>500,AR78<=1250), AQ78*'BU FACILITIES'!$G$6, IF(AND(AR78>1250,AR78<=2000),AQ78*'BU FACILITIES'!$G$7, "")))) | AV78: =IF(AU78=100,AT78*'BU FACILITIES'!$G$8, IF(AND(AU78>100,AU78<=500), AT78*'BU FACILITIES'!$G$9, IF(AND(AU78>500,AU78<=800), AT78*'BU FACILITIES'!$G$10, IF(AND(AU78>800,AU78<=1000),AT78*'BU FACILITIES'!$G$11, IF(AND(AU78>1000,AU78<=1400),AT78*'BU FACILITIES'!$G$12, IF(AND(AU78>1400,AU78<=2000),AT78*'BU FACILITIES'!$G$13,"")))))) | AY78: =IF(AX78=30,AW78*'BU FACILITIES'!$G$14, IF(AX78=45, AW78*'BU FACILITIES'!$G$15, IF(AX78=450, AW78*'BU FACILITIES'!$G$16, ""))) | BB78: =IF(AND(BA78>=1,BA78<=5),'BU FACILITIES'!$G$17, IF(AND(BA78>5, BA78<=10), 'BU FACILITIES'!$G$18, IF(AND(BA78>10,BA78<=20),'BU FACILITIES'!$G$19,""))) | BD78: =IF(AND(AZ78="Modificar ductería de AA",BC78=1), 'BU FACILITIES'!$G$20, "") | BE78: Ampliación de ductos para nueva zona de ampliación.
A79: Plataforma Óptica | B79: BBI-TV-TOIP | C79: Income | D79: Gerencia Acceso Fijo | E79: Jorge Ivan Pérez Cardona | F79: 2023 | G79: Nogales | H79: Barranquilla | J79: Yes | K79: 1 | L79: 2 | M79: 475 | N79: 950 | P79: =SUMIF($G$3:$G$292,G79,$N$3:$N$292) -> 950 | Q79: =IF(N79<>0,N79/P79,"0") -> 1 | R79: =VLOOKUP(G79,#REF!,11,0)*Q79 -> #REF! | S79: DC | T79: 1620.75 | U79: 2 | X79: 48 VDC | Y79: 1.5 | Z79: Q1-Q2 | AB79: Transmisores y Receptotes Ópticos | AC79: Incluir cableado, protecciones, tendidos, canaletas, tuberías, etc | AD79: 5 | AE79: SI | AH79: =IF(AG79=1,'BU FACILITIES'!$G$24,"") | AI79: SI | AJ79: 1 | AK79: =AJ79*'BU FACILITIES'!$G$21 -> 1714.6341 | AL79: 1 | AM79: =PRODUCT( AL79,'BU FACILITIES'!$G$22) -> 870.73171 | AP79: =IF(AO79=1,'BU FACILITIES'!$G$23,"") | AS79: =IF(AR79=300,AQ79*'BU FACILITIES'!$G$4, IF(AND(AR79>300,AR79<=500), AQ79*'BU FACILITIES'!$G$5, IF(AND(AR79>500,AR79<=1250), AQ79*'BU FACILITIES'!$G$6, IF(AND(AR79>1250,AR79<=2000),AQ79*'BU FACILITIES'!$G$7, "")))) | AV79: =IF(AU79=100,AT79*'BU FACILITIES'!$G$8, IF(AND(AU79>100,AU79<=500), AT79*'BU FACILITIES'!$G$9, IF(AND(AU79>500,AU79<=800), AT79*'BU FACILITIES'!$G$10, IF(AND(AU79>800,AU79<=1000),AT79*'BU FACILITIES'!$G$11, IF(AND(AU79>1000,AU79<=1400),AT79*'BU FACILITIES'!$G$12, IF(AND(AU79>1400,AU79<=2000),AT79*'BU FACILITIES'!$G$13,"")))))) | AY79: =IF(AX79=30,AW79*'BU FACILITIES'!$G$14, IF(AX79=45, AW79*'BU FACILITIES'!$G$15, IF(AX79=450, AW79*'BU FACILITIES'!$G$16, ""))) | BB79: =IF(AND(BA79>=1,BA79<=5),'BU FACILITIES'!$G$17, IF(AND(BA79>5, BA79<=10), 'BU FACILITIES'!$G$18, IF(AND(BA79>10,BA79<=20),'BU FACILITIES'!$G$19,""))) | BD79: =IF(AND(AZ79="Modificar ductería de AA",BC79=1), 'BU FACILITIES'!$G$20, "") | BE79: Ampliación de ductos para nueva zona de ampliación.
A80: Plataforma Óptica | B80: BBI-TV-TOIP | C80: Income | D80: Gerencia Acceso Fijo | E80: Jorge Ivan Pérez Cardona | F80: 2023 | G80: Turbaco | H80: Cartagena | J80: Yes | K80: 1 | L80: 2 | M80: 475 | N80: 950 | P80: =SUMIF($G$3:$G$292,G80,$N$3:$N$292) -> 950 | Q80: =IF(N80<>0,N80/P80,"0") -> 1 | R80: =VLOOKUP(G80,#REF!,11,0)*Q80 -> #REF! | S80: DC | T80: 1620.75 | U80: 2 | X80: 48 VDC | Y80: 1.5 | Z80: Q1-Q2 | AB80: Transmisores y Receptotes Ópticos | AC80: Incluir cableado, protecciones, tendidos, canaletas, tuberías, etc | AD80: 3 | AE80: SI | AH80: =IF(AG80=1,'BU FACILITIES'!$G$24,"") | AI80: SI | AJ80: 1 | AK80: =AJ80*'BU FACILITIES'!$G$21 -> 1714.6341 | AL80: 1 | AM80: =PRODUCT( AL80,'BU FACILITIES'!$G$22) -> 870.73171 | AP80: =IF(AO80=1,'BU FACILITIES'!$G$23,"") | AS80: =IF(AR80=300,AQ80*'BU FACILITIES'!$G$4, IF(AND(AR80>300,AR80<=500), AQ80*'BU FACILITIES'!$G$5, IF(AND(AR80>500,AR80<=1250), AQ80*'BU FACILITIES'!$G$6, IF(AND(AR80>1250,AR80<=2000),AQ80*'BU FACILITIES'!$G$7, "")))) | AV80: =IF(AU80=100,AT80*'BU FACILITIES'!$G$8, IF(AND(AU80>100,AU80<=500), AT80*'BU FACILITIES'!$G$9, IF(AND(AU80>500,AU80<=800), AT80*'BU FACILITIES'!$G$10, IF(AND(AU80>800,AU80<=1000),AT80*'BU FACILITIES'!$G$11, IF(AND(AU80>1000,AU80<=1400),AT80*'BU FACILITIES'!$G$12, IF(AND(AU80>1400,AU80<=2000),AT80*'BU FACILITIES'!$G$13,"")))))) | AY80: =IF(AX80=30,AW80*'BU FACILITIES'!$G$14, IF(AX80=45, AW80*'BU FACILITIES'!$G$15, IF(AX80=450, AW80*'BU FACILITIES'!$G$16, ""))) | BB80: =IF(AND(BA80>=1,BA80<=5),'BU FACILITIES'!$G$17, IF(AND(BA80>5, BA80<=10), 'BU FACILITIES'!$G$18, IF(AND(BA80>10,BA80<=20),'BU FACILITIES'!$G$19,""))) | BD80: =IF(AND(AZ80="Modificar ductería de AA",BC80=1), 'BU FACILITIES'!$G$20, "")
A81: Plataforma Óptica | B81: BBI-TV-TOIP | C81: Income | D81: Gerencia Acceso Fijo | E81: Jorge Ivan Pérez Cardona | F81: 2023 | G81: Centro Edatel Montería | H81: Montería | J81: Yes | K81: 1 | L81: 6 | M81: 475 | N81: 2850 | P81: =SUMIF($G$3:$G$292,G81,$N$3:$N$292) -> 2850 | Q81: =IF(N81<>0,N81/P81,"0") -> 1 | R81: =VLOOKUP(G81,#REF!,11,0)*Q81 -> #REF! | S81: DC | T81: 1620.75 | U81: 2 | X81: 48 VDC | Y81: 1.5 | Z81: Q1-Q2 | AB81: Transmisores y Receptotes Ópticos | AC81: Posee doble rectif y BB, tiene MG, no requiere inversión 2023 para asumir esta carga | AE81: SI | AH81: =IF(AG81=1,'BU FACILITIES'!$G$24,"") | AI81: PBD | AJ81: 0 | AK81: =AJ81*'BU FACILITIES'!$G$21 -> 0 | AL81: 0 | AM81: =PRODUCT( AL81,'BU FACILITIES'!$G$22) -> 0 | AP81: =IF(AO81=1,'BU FACILITIES'!$G$23,"") | AS81: =IF(AR81=300,AQ81*'BU FACILITIES'!$G$4, IF(AND(AR81>300,AR81<=500), AQ81*'BU FACILITIES'!$G$5, IF(AND(AR81>500,AR81<=1250), AQ81*'BU FACILITIES'!$G$6, IF(AND(AR81>1250,AR81<=2000),AQ81*'BU FACILITIES'!$G$7, "")))) | AV81: =IF(AU81=100,AT81*'BU FACILITIES'!$G$8, IF(AND(AU81>100,AU81<=500), AT81*'BU FACILITIES'!$G$9, IF(AND(AU81>500,AU81<=800), AT81*'BU FACILITIES'!$G$10, IF(AND(AU81>800,AU81<=1000),AT81*'BU FACILITIES'!$G$11, IF(AND(AU81>1000,AU81<=1400),AT81*'BU FACILITIES'!$G$12, IF(AND(AU81>1400,AU81<=2000),AT81*'BU FACILITIES'!$G$13,"")))))) | AY81: =IF(AX81=30,AW81*'BU FACILITIES'!$G$14, IF(AX81=45, AW81*'BU FACILITIES'!$G$15, IF(AX81=450, AW81*'BU FACILITIES'!$G$16, ""))) | BB81: =IF(AND(BA81>=1,BA81<=5),'BU FACILITIES'!$G$17, IF(AND(BA81>5, BA81<=10), 'BU FACILITIES'!$G$18, IF(AND(BA81>10,BA81<=20),'BU FACILITIES'!$G$19,""))) | BD81: =IF(AND(AZ81="Modificar ductería de AA",BC81=1), 'BU FACILITIES'!$G$20, "")
A82: Plataforma Óptica | B82: BBI-TV-TOIP | C82: Income | D82: Gerencia Acceso Fijo | E82: Jorge Ivan Pérez Cardona | F82: 2023 | G82: Centro Edatel Sincelejo | H82: Sincelejo | J82: Yes | K82: 1 | L82: 6 | M82: 475 | N82: 2850 | P82: =SUMIF($G$3:$G$292,G82,$N$3:$N$292) -> 2850 | Q82: =IF(N82<>0,N82/P82,"0") -> 1 | R82: =VLOOKUP(G82,#REF!,11,0)*Q82 -> #REF! | S82: DC | T82: 1620.75 | U82: 2 | X82: 48 VDC | Y82: 1.5 | Z82: Q1-Q2 | AB82: Transmisores y Receptotes Ópticos | AC82: Posee doble rectif y BB, tiene MG, no requiere inversión 2023 para asumir esta carga | AE82: SI | AH82: =IF(AG82=1,'BU FACILITIES'!$G$24,"") | AI82: PBD | AJ82: 1 | AK82: =AJ82*'BU FACILITIES'!$G$21 -> 1714.6341 | AL82: 1 | AM82: =PRODUCT( AL82,'BU FACILITIES'!$G$22) -> 870.73171 | AP82: =IF(AO82=1,'BU FACILITIES'!$G$23,"") | AS82: =IF(AR82=300,AQ82*'BU FACILITIES'!$G$4, IF(AND(AR82>300,AR82<=500), AQ82*'BU FACILITIES'!$G$5, IF(AND(AR82>500,AR82<=1250), AQ82*'BU FACILITIES'!$G$6, IF(AND(AR82>1250,AR82<=2000),AQ82*'BU FACILITIES'!$G$7, "")))) | AV82: =IF(AU82=100,AT82*'BU FACILITIES'!$G$8, IF(AND(AU82>100,AU82<=500), AT82*'BU FACILITIES'!$G$9, IF(AND(AU82>500,AU82<=800), AT82*'BU FACILITIES'!$G$10, IF(AND(AU82>800,AU82<=1000),AT82*'BU FACILITIES'!$G$11, IF(AND(AU82>1000,AU82<=1400),AT82*'BU FACILITIES'!$G$12, IF(AND(AU82>1400,AU82<=2000),AT82*'BU FACILITIES'!$G$13,"")))))) | AY82: =IF(AX82=30,AW82*'BU FACILITIES'!$G$14, IF(AX82=45, AW82*'BU FACILITIES'!$G$15, IF(AX82=450, AW82*'BU FACILITIES'!$G$16, ""))) | BB82: =IF(AND(BA82>=1,BA82<=5),'BU FACILITIES'!$G$17, IF(AND(BA82>5, BA82<=10), 'BU FACILITIES'!$G$18, IF(AND(BA82>10,BA82<=20),'BU FACILITIES'!$G$19,""))) | BD82: =IF(AND(AZ82="Modificar ductería de AA",BC82=1), 'BU FACILITIES'!$G$20, "")
A83: Plataforma Óptica | B83: BBI-TV-TOIP | C83: Income | D83: Gerencia Acceso Fijo | E83: Jorge Ivan Pérez Cardona | F83: 2023 | G83: Centro Edatel Valledupar | H83: Valledupar | J83: Yes | K83: 1 | L83: 6 | M83: 475 | N83: 2850 | P83: =SUMIF($G$3:$G$292,G83,$N$3:$N$292) -> 2850 | Q83: =IF(N83<>0,N83/P83,"0") -> 1 | R83: =VLOOKUP(G83,#REF!,11,0)*Q83 -> #REF! | S83: DC | T83: 1620.75 | U83: 2 | X83: 48 VDC | Y83: 1.5 | Z83: Q1-Q2 | AB83: Transmisores y Receptotes Ópticos | AC83: Posee doble rectif y BB, tiene MG, no requiere inversión 2023 para asumir esta carga | AE83: SI | AH83: =IF(AG83=1,'BU FACILITIES'!$G$24,"") | AI83: PBD | AJ83: 0 | AK83: =AJ83*'BU FACILITIES'!$G$21 -> 0 | AL83: 0 | AM83: =PRODUCT( AL83,'BU FACILITIES'!$G$22) -> 0 | AP83: =IF(AO83=1,'BU FACILITIES'!$G$23,"") | AS83: =IF(AR83=300,AQ83*'BU FACILITIES'!$G$4, IF(AND(AR83>300,AR83<=500), AQ83*'BU FACILITIES'!$G$5, IF(AND(AR83>500,AR83<=1250), AQ83*'BU FACILITIES'!$G$6, IF(AND(AR83>1250,AR83<=2000),AQ83*'BU FACILITIES'!$G$7, "")))) | AV83: =IF(AU83=100,AT83*'BU FACILITIES'!$G$8, IF(AND(AU83>100,AU83<=500), AT83*'BU FACILITIES'!$G$9, IF(AND(AU83>500,AU83<=800), AT83*'BU FACILITIES'!$G$10, IF(AND(AU83>800,AU83<=1000),AT83*'BU FACILITIES'!$G$11, IF(AND(AU83>1000,AU83<=1400),AT83*'BU FACILITIES'!$G$12, IF(AND(AU83>1400,AU83<=2000),AT83*'BU FACILITIES'!$G$13,"")))))) | AY83: =IF(AX83=30,AW83*'BU FACILITIES'!$G$14, IF(AX83=45, AW83*'BU FACILITIES'!$G$15, IF(AX83=450, AW83*'BU FACILITIES'!$G$16, ""))) | BB83: =IF(AND(BA83>=1,BA83<=5),'BU FACILITIES'!$G$17, IF(AND(BA83>5, BA83<=10), 'BU FACILITIES'!$G$18, IF(AND(BA83>10,BA83<=20),'BU FACILITIES'!$G$19,""))) | BD83: =IF(AND(AZ83="Modificar ductería de AA",BC83=1), 'BU FACILITIES'!$G$20, "")
A84: Plataforma Óptica | B84: BBI-TV-TOIP | C84: Income | D84: Gerencia Acceso Fijo | E84: Jorge Ivan Pérez Cardona | F84: 2023 | G84: Nuevo Hub | H84: Armenia | J84: Yes | K84: 3 | L84: 10 | M84: 475 | N84: 4750 | P84: =SUMIF($G$3:$G$292,G84,$N$3:$N$292) -> 4750 | Q84: =IF(N84<>0,N84/P84,"0") -> 1 | R84: =VLOOKUP(G84,#REF!,11,0)*Q84 -> #REF! | S84: DC | T84: 1620.75 | U84: 6 | X84: 48 VDC | Y84: 4.5 | Z84: Q1-Q2 | AB84: Transmisores y Receptotes Ópticos | AC84: Deben incluir el rack | AD84: 4 | AE84: Si | AH84: =IF(AG84=1,'BU FACILITIES'!$G$24,"") | AI84: Si | AJ84: 1 | AK84: =AJ84*'BU FACILITIES'!$G$21 -> 1714.6341 | AL84: 1 | AM84: =PRODUCT( AL84,'BU FACILITIES'!$G$22) -> 870.73171 | AP84: =IF(AO84=1,'BU FACILITIES'!$G$23,"") | AS84: =IF(AR84=300,AQ84*'BU FACILITIES'!$G$4, IF(AND(AR84>300,AR84<=500), AQ84*'BU FACILITIES'!$G$5, IF(AND(AR84>500,AR84<=1250), AQ84*'BU FACILITIES'!$G$6, IF(AND(AR84>1250,AR84<=2000),AQ84*'BU FACILITIES'!$G$7, "")))) | AV84: =IF(AU84=100,AT84*'BU FACILITIES'!$G$8, IF(AND(AU84>100,AU84<=500), AT84*'BU FACILITIES'!$G$9, IF(AND(AU84>500,AU84<=800), AT84*'BU FACILITIES'!$G$10, IF(AND(AU84>800,AU84<=1000),AT84*'BU FACILITIES'!$G$11, IF(AND(AU84>1000,AU84<=1400),AT84*'BU FACILITIES'!$G$12, IF(AND(AU84>1400,AU84<=2000),AT84*'BU FACILITIES'!$G$13,"")))))) | AY84: =IF(AX84=30,AW84*'BU FACILITIES'!$G$14, IF(AX84=45, AW84*'BU FACILITIES'!$G$15, IF(AX84=450, AW84*'BU FACILITIES'!$G$16, ""))) | BB84: =IF(AND(BA84>=1,BA84<=5),'BU FACILITIES'!$G$17, IF(AND(BA84>5, BA84<=10), 'BU FACILITIES'!$G$18, IF(AND(BA84>10,BA84<=20),'BU FACILITIES'!$G$19,""))) | BD84: =IF(AND(AZ84="Modificar ductería de AA",BC84=1), 'BU FACILITIES'!$G$20, "")
A85: Plataforma Óptica | B85: BBI-TV-TOIP | C85: Income | D85: Gerencia Acceso Fijo | E85: Jorge Ivan Pérez Cardona | F85: 2023 | G85: Belén | H85: Manizales | J85: Yes | K85: 1 | L85: 6 | M85: 475 | N85: 2850 | P85: =SUMIF($G$3:$G$292,G85,$N$3:$N$292) -> 2850 | Q85: =IF(N85<>0,N85/P85,"0") -> 1 | R85: =VLOOKUP(G85,#REF!,11,0)*Q85 -> #REF! | S85: DC | T85: 1620.75 | U85: 2 | X85: 48 VDC | Y85: 1.5 | Z85: Q1-Q2 | AB85: Transmisores y Receptotes Ópticos | AC85: Deben incluir el rack | AD85: 4 | AE85: Si | AH85: =IF(AG85=1,'BU FACILITIES'!$G$24,"") | AI85: Si | AJ85: 1 | AK85: =AJ85*'BU FACILITIES'!$G$21 -> 1714.6341 | AL85: 1 | AM85: =PRODUCT( AL85,'BU FACILITIES'!$G$22) -> 870.73171 | AP85: =IF(AO85=1,'BU FACILITIES'!$G$23,"") | AS85: =IF(AR85=300,AQ85*'BU FACILITIES'!$G$4, IF(AND(AR85>300,AR85<=500), AQ85*'BU FACILITIES'!$G$5, IF(AND(AR85>500,AR85<=1250), AQ85*'BU FACILITIES'!$G$6, IF(AND(AR85>1250,AR85<=2000),AQ85*'BU FACILITIES'!$G$7, "")))) | AV85: =IF(AU85=100,AT85*'BU FACILITIES'!$G$8, IF(AND(AU85>100,AU85<=500), AT85*'BU FACILITIES'!$G$9, IF(AND(AU85>500,AU85<=800), AT85*'BU FACILITIES'!$G$10, IF(AND(AU85>800,AU85<=1000),AT85*'BU FACILITIES'!$G$11, IF(AND(AU85>1000,AU85<=1400),AT85*'BU FACILITIES'!$G$12, IF(AND(AU85>1400,AU85<=2000),AT85*'BU FACILITIES'!$G$13,"")))))) | AY85: =IF(AX85=30,AW85*'BU FACILITIES'!$G$14, IF(AX85=45, AW85*'BU FACILITIES'!$G$15, IF(AX85=450, AW85*'BU FACILITIES'!$G$16, ""))) | BB85: =IF(AND(BA85>=1,BA85<=5),'BU FACILITIES'!$G$17, IF(AND(BA85>5, BA85<=10), 'BU FACILITIES'!$G$18, IF(AND(BA85>10,BA85<=20),'BU FACILITIES'!$G$19,""))) | BD85: =IF(AND(AZ85="Modificar ductería de AA",BC85=1), 'BU FACILITIES'!$G$20, "")
A86: Plataforma Óptica | B86: BBI-TV-TOIP | C86: Income | D86: Gerencia Acceso Fijo | E86: Jorge Ivan Pérez Cardona | F86: 2023 | G86: Centro manizales | H86: Manizales | J86: Yes | K86: 2 | L86: 10 | M86: 475 | N86: 4750 | P86: =SUMIF($G$3:$G$292,G86,$N$3:$N$292) -> 5950 | Q86: =IF(N86<>0,N86/P86,"0") -> 0.79831933 | R86: =VLOOKUP(G86,#REF!,11,0)*Q86 -> #REF! | S86: DC | T86: 1620.75 | U86: 4 | X86: 48 VDC | Y86: 3 | Z86: Q1-Q2 | AB86: Transmisores y Receptotes Ópticos | AC86: Deben incluir el rack | AD86: 3 | AE86: Si | AH86: =IF(AG86=1,'BU FACILITIES'!$G$24,"") | AI86: Si | AJ86: 1 | AK86: =AJ86*'BU FACILITIES'!$G$21 -> 1714.6341 | AL86: 1 | AM86: =PRODUCT( AL86,'BU FACILITIES'!$G$22) -> 870.73171 | AP86: =IF(AO86=1,'BU FACILITIES'!$G$23,"") | AS86: =IF(AR86=300,AQ86*'BU FACILITIES'!$G$4, IF(AND(AR86>300,AR86<=500), AQ86*'BU FACILITIES'!$G$5, IF(AND(AR86>500,AR86<=1250), AQ86*'BU FACILITIES'!$G$6, IF(AND(AR86>1250,AR86<=2000),AQ86*'BU FACILITIES'!$G$7, "")))) | AV86: =IF(AU86=100,AT86*'BU FACILITIES'!$G$8, IF(AND(AU86>100,AU86<=500), AT86*'BU FACILITIES'!$G$9, IF(AND(AU86>500,AU86<=800), AT86*'BU FACILITIES'!$G$10, IF(AND(AU86>800,AU86<=1000),AT86*'BU FACILITIES'!$G$11, IF(AND(AU86>1000,AU86<=1400),AT86*'BU FACILITIES'!$G$12, IF(AND(AU86>1400,AU86<=2000),AT86*'BU FACILITIES'!$G$13,"")))))) | AY86: =IF(AX86=30,AW86*'BU FACILITIES'!$G$14, IF(AX86=45, AW86*'BU FACILITIES'!$G$15, IF(AX86=450, AW86*'BU FACILITIES'!$G$16, ""))) | BB86: =IF(AND(BA86>=1,BA86<=5),'BU FACILITIES'!$G$17, IF(AND(BA86>5, BA86<=10), 'BU FACILITIES'!$G$18, IF(AND(BA86>10,BA86<=20),'BU FACILITIES'!$G$19,""))) | BD86: =IF(AND(AZ86="Modificar ductería de AA",BC86=1), 'BU FACILITIES'!$G$20, "")
A87: Plataforma Óptica | B87: BBI-TV-TOIP | C87: Income | D87: Gerencia Acceso Fijo | E87: Jorge Ivan Pérez Cardona | F87: 2023 | G87: Jardin | H87: Ibagué | J87: Yes | K87: 1 | L87: 6 | M87: 475 | N87: 2850 | P87: =SUMIF($G$3:$G$292,G87,$N$3:$N$292) -> 2850 | Q87: =IF(N87<>0,N87/P87,"0") -> 1 | R87: =VLOOKUP(G87,#REF!,11,0)*Q87 -> #REF! | S87: DC | T87: 1620.75 | U87: 2 | X87: 48 VDC | Y87: 1.5 | Z87: Q1-Q2 | AB87: Transmisores y Receptotes Ópticos | AC87: Deben incluir el rack | AD87: Urbano | AE87: Si | AH87: =IF(AG87=1,'BU FACILITIES'!$G$24,"") | AI87: Si | AJ87: 1 | AK87: =AJ87*'BU FACILITIES'!$G$21 -> 1714.6341 | AL87: 1 | AM87: =PRODUCT( AL87,'BU FACILITIES'!$G$22) -> 870.73171 | AP87: =IF(AO87=1,'BU FACILITIES'!$G$23,"") | AS87: =IF(AR87=300,AQ87*'BU FACILITIES'!$G$4, IF(AND(AR87>300,AR87<=500), AQ87*'BU FACILITIES'!$G$5, IF(AND(AR87>500,AR87<=1250), AQ87*'BU FACILITIES'!$G$6, IF(AND(AR87>1250,AR87<=2000),AQ87*'BU FACILITIES'!$G$7, "")))) | AV87: =IF(AU87=100,AT87*'BU FACILITIES'!$G$8, IF(AND(AU87>100,AU87<=500), AT87*'BU FACILITIES'!$G$9, IF(AND(AU87>500,AU87<=800), AT87*'BU FACILITIES'!$G$10, IF(AND(AU87>800,AU87<=1000),AT87*'BU FACILITIES'!$G$11, IF(AND(AU87>1000,AU87<=1400),AT87*'BU FACILITIES'!$G$12, IF(AND(AU87>1400,AU87<=2000),AT87*'BU FACILITIES'!$G$13,"")))))) | AY87: =IF(AX87=30,AW87*'BU FACILITIES'!$G$14, IF(AX87=45, AW87*'BU FACILITIES'!$G$15, IF(AX87=450, AW87*'BU FACILITIES'!$G$16, ""))) | BB87: =IF(AND(BA87>=1,BA87<=5),'BU FACILITIES'!$G$17, IF(AND(BA87>5, BA87<=10), 'BU FACILITIES'!$G$18, IF(AND(BA87>10,BA87<=20),'BU FACILITIES'!$G$19,""))) | BD87: =IF(AND(AZ87="Modificar ductería de AA",BC87=1), 'BU FACILITIES'!$G$20, "")
A88: Plataforma Óptica | B88: BBI-TV-TOIP | C88: Income | D88: Gerencia Acceso Fijo | E88: Jorge Ivan Pérez Cardona | F88: 2023 | G88: Camelia | H88: Pereira | J88: Yes | K88: 1 | L88: 6 | M88: 475 | N88: 2850 | P88: =SUMIF($G$3:$G$292,G88,$N$3:$N$292) -> 2850 | Q88: =IF(N88<>0,N88/P88,"0") -> 1 | R88: =VLOOKUP(G88,#REF!,11,0)*Q88 -> #REF! | S88: DC | T88: 1620.75 | U88: 2 | X88: 48 VDC | Y88: 1.5 | Z88: Q1-Q2 | AB88: Transmisores y Receptotes Ópticos | AC88: Deben incluir el rack | AD88: Urbano | AE88: Si | AH88: =IF(AG88=1,'BU FACILITIES'!$G$24,"") | AI88: Si | AJ88: 1 | AK88: =AJ88*'BU FACILITIES'!$G$21 -> 1714.6341 | AL88: 1 | AM88: =PRODUCT( AL88,'BU FACILITIES'!$G$22) -> 870.73171 | AP88: =IF(AO88=1,'BU FACILITIES'!$G$23,"") | AS88: =IF(AR88=300,AQ88*'BU FACILITIES'!$G$4, IF(AND(AR88>300,AR88<=500), AQ88*'BU FACILITIES'!$G$5, IF(AND(AR88>500,AR88<=1250), AQ88*'BU FACILITIES'!$G$6, IF(AND(AR88>1250,AR88<=2000),AQ88*'BU FACILITIES'!$G$7, "")))) | AV88: =IF(AU88=100,AT88*'BU FACILITIES'!$G$8, IF(AND(AU88>100,AU88<=500), AT88*'BU FACILITIES'!$G$9, IF(AND(AU88>500,AU88<=800), AT88*'BU FACILITIES'!$G$10, IF(AND(AU88>800,AU88<=1000),AT88*'BU FACILITIES'!$G$11, IF(AND(AU88>1000,AU88<=1400),AT88*'BU FACILITIES'!$G$12, IF(AND(AU88>1400,AU88<=2000),AT88*'BU FACILITIES'!$G$13,"")))))) | AY88: =IF(AX88=30,AW88*'BU FACILITIES'!$G$14, IF(AX88=45, AW88*'BU FACILITIES'!$G$15, IF(AX88=450, AW88*'BU FACILITIES'!$G$16, ""))) | BB88: =IF(AND(BA88>=1,BA88<=5),'BU FACILITIES'!$G$17, IF(AND(BA88>5, BA88<=10), 'BU FACILITIES'!$G$18, IF(AND(BA88>10,BA88<=20),'BU FACILITIES'!$G$19,""))) | BD88: =IF(AND(AZ88="Modificar ductería de AA",BC88=1), 'BU FACILITIES'!$G$20, "")
A89: Plataforma Óptica | B89: BBI-TV-TOIP | C89: Income | D89: Gerencia Acceso Fijo | E89: Jorge Ivan Pérez Cardona | F89: 2023 | G89: Centro Pereira | H89: Pereira | J89: Yes | K89: 2 | L89: 8 | M89: 475 | N89: 3800 | P89: =SUMIF($G$3:$G$292,G89,$N$3:$N$292) -> 3800 | Q89: =IF(N89<>0,N89/P89,"0") -> 1 | R89: =VLOOKUP(G89,#REF!,11,0)*Q89 -> #REF! | S89: DC | T89: 1620.75 | U89: 4 | X89: 48 VDC | Y89: 3 | Z89: Q1-Q2 | AB89: Transmisores y Receptotes Ópticos | AC89: Deben incluir el rack | AD89: Urbano | AE89: Si | AH89: =IF(AG89=1,'BU FACILITIES'!$G$24,"") | AI89: Si | AJ89: 1 | AK89: =AJ89*'BU FACILITIES'!$G$21 -> 1714.6341 | AL89: 1 | AM89: =PRODUCT( AL89,'BU FACILITIES'!$G$22) -> 870.73171 | AP89: =IF(AO89=1,'BU FACILITIES'!$G$23,"") | AS89: =IF(AR89=300,AQ89*'BU FACILITIES'!$G$4, IF(AND(AR89>300,AR89<=500), AQ89*'BU FACILITIES'!$G$5, IF(AND(AR89>500,AR89<=1250), AQ89*'BU FACILITIES'!$G$6, IF(AND(AR89>1250,AR89<=2000),AQ89*'BU FACILITIES'!$G$7, "")))) | AV89: =IF(AU89=100,AT89*'BU FACILITIES'!$G$8, IF(AND(AU89>100,AU89<=500), AT89*'BU FACILITIES'!$G$9, IF(AND(AU89>500,AU89<=800), AT89*'BU FACILITIES'!$G$10, IF(AND(AU89>800,AU89<=1000),AT89*'BU FACILITIES'!$G$11, IF(AND(AU89>1000,AU89<=1400),AT89*'BU FACILITIES'!$G$12, IF(AND(AU89>1400,AU89<=2000),AT89*'BU FACILITIES'!$G$13,"")))))) | AY89: =IF(AX89=30,AW89*'BU FACILITIES'!$G$14, IF(AX89=45, AW89*'BU FACILITIES'!$G$15, IF(AX89=450, AW89*'BU FACILITIES'!$G$16, ""))) | BB89: =IF(AND(BA89>=1,BA89<=5),'BU FACILITIES'!$G$17, IF(AND(BA89>5, BA89<=10), 'BU FACILITIES'!$G$18, IF(AND(BA89>10,BA89<=20),'BU FACILITIES'!$G$19,""))) | BD89: =IF(AND(AZ89="Modificar ductería de AA",BC89=1), 'BU FACILITIES'!$G$20, "")
A90: Plataforma Óptica | B90: BBI-TV-TOIP | C90: Income | D90: Gerencia Acceso Fijo | E90: Jorge Ivan Pérez Cardona | F90: 2023 | G90: BUGA | H90: Buga | J90: Yes | K90: 1 | L90: 6 | M90: 475 | N90: 0 | P90: =SUMIF($G$3:$G$292,G90,$N$3:$N$292) -> 0 | Q90: =IF(N90<>0,N90/P90,"0") -> 0 | R90: =VLOOKUP(G90,#REF!,11,0)*Q90 -> #REF! | S90: DC | T90: 1620.75 | U90: 2 | X90: 48 VDC | Y90: 1.5 | Z90: Q1-Q2 | AB90: Transmisores y Receptotes Ópticos | AC90: Se debe re utilizar espacios existetnes en los racks del sitio | AD90: 4 | AE90: SI | AH90: =IF(AG90=1,'BU FACILITIES'!$G$24,"") | AK90: =AJ90*'BU FACILITIES'!$G$21 -> 0 | AL90: 1 | AM90: =PRODUCT( AL90,'BU FACILITIES'!$G$22) -> 870.73171 | AP90: =IF(AO90=1,'BU FACILITIES'!$G$23,"") | AQ90: 0 | AR90: 0 | AS90: =IF(AR90=300,AQ90*'BU FACILITIES'!$G$4, IF(AND(AR90>300,AR90<=500), AQ90*'BU FACILITIES'!$G$5, IF(AND(AR90>500,AR90<=1250), AQ90*'BU FACILITIES'!$G$6, IF(AND(AR90>1250,AR90<=2000),AQ90*'BU FACILITIES'!$G$7, "")))) | AT90: 0 | AU90: 0 | AV90: =IF(AU90=100,AT90*'BU FACILITIES'!$G$8, IF(AND(AU90>100,AU90<=500), AT90*'BU FACILITIES'!$G$9, IF(AND(AU90>500,AU90<=800), AT90*'BU FACILITIES'!$G$10, IF(AND(AU90>800,AU90<=1000),AT90*'BU FACILITIES'!$G$11, IF(AND(AU90>1000,AU90<=1400),AT90*'BU FACILITIES'!$G$12, IF(AND(AU90>1400,AU90<=2000),AT90*'BU FACILITIES'!$G$13,"")))))) | AW90: 0 | AX90: 0 | AY90: =IF(AX90=30,AW90*'BU FACILITIES'!$G$14, IF(AX90=45, AW90*'BU FACILITIES'!$G$15, IF(AX90=450, AW90*'BU FACILITIES'!$G$16, ""))) | AZ90: 0 | BA90: 0 | BB90: =IF(AND(BA90>=1,BA90<=5),'BU FACILITIES'!$G$17, IF(AND(BA90>5, BA90<=10), 'BU FACILITIES'!$G$18, IF(AND(BA90>10,BA90<=20),'BU FACILITIES'!$G$19,""))) | BD90: =IF(AND(AZ90="Modificar ductería de AA",BC90=1), 'BU FACILITIES'!$G$20, "")
A91: Plataforma Óptica | B91: BBI-TV-TOIP | C91: Income | D91: Gerencia Acceso Fijo | E91: Jorge Ivan Pérez Cardona | F91: 2023 | G91: Limonar | H91: Cali | J91: Yes | K91: 2 | L91: 10 | M91: 475 | N91: 4750 | P91: =SUMIF($G$3:$G$292,G91,$N$3:$N$292) -> 4750 | Q91: =IF(N91<>0,N91/P91,"0") -> 1 | R91: =VLOOKUP(G91,#REF!,11,0)*Q91 -> #REF! | S91: DC | T91: 1620.75 | U91: 4 | X91: 48 VDC | Y91: 3 | Z91: Q1-Q2 | AB91: Transmisores y Receptotes Ópticos | AC91: Existe espacio para los nuevos racks, capacidad en AA, capacidad en rectificadores. Se recomendará usar rack existente donde se des instaló la misma plataforma en 2021, Aunque hay capacidad física para las solicitudes del año se copa el sitio al 95%, se debe proyectar ampliación del sitio | AD91: 3 | AE91: SI | AH91: =IF(AG91=1,'BU FACILITIES'!$G$24,"") | AK91: =AJ91*'BU FACILITIES'!$G$21 -> 0 | AL91: 1 | AM91: =PRODUCT( AL91,'BU FACILITIES'!$G$22) -> 870.73171 | AP91: =IF(AO91=1,'BU FACILITIES'!$G$23,"") | AQ91: 0 | AR91: 0 | AS91: =IF(AR91=300,AQ91*'BU FACILITIES'!$G$4, IF(AND(AR91>300,AR91<=500), AQ91*'BU FACILITIES'!$G$5, IF(AND(AR91>500,AR91<=1250), AQ91*'BU FACILITIES'!$G$6, IF(AND(AR91>1250,AR91<=2000),AQ91*'BU FACILITIES'!$G$7, "")))) | AT91: 0 | AU91: 0 | AV91: =IF(AU91=100,AT91*'BU FACILITIES'!$G$8, IF(AND(AU91>100,AU91<=500), AT91*'BU FACILITIES'!$G$9, IF(AND(AU91>500,AU91<=800), AT91*'BU FACILITIES'!$G$10, IF(AND(AU91>800,AU91<=1000),AT91*'BU FACILITIES'!$G$11, IF(AND(AU91>1000,AU91<=1400),AT91*'BU FACILITIES'!$G$12, IF(AND(AU91>1400,AU91<=2000),AT91*'BU FACILITIES'!$G$13,"")))))) | AY91: =IF(AX91=30,AW91*'BU FACILITIES'!$G$14, IF(AX91=45, AW91*'BU FACILITIES'!$G$15, IF(AX91=450, AW91*'BU FACILITIES'!$G$16, ""))) | AZ91: 0 | BA91: 0 | BB91: =IF(AND(BA91>=1,BA91<=5),'BU FACILITIES'!$G$17, IF(AND(BA91>5, BA91<=10), 'BU FACILITIES'!$G$18, IF(AND(BA91>10,BA91<=20),'BU FACILITIES'!$G$19,""))) | BD91: =IF(AND(AZ91="Modificar ductería de AA",BC91=1), 'BU FACILITIES'!$G$20, "")
A92: Plataforma Óptica | B92: BBI-TV-TOIP | C92: Income | D92: Gerencia Acceso Fijo | E92: Jorge Ivan Pérez Cardona | F92: 2023 | G92: Vásquez Cobo | H92: Cali | J92: Yes | K92: 2 | L92: 8 | M92: 475 | N92: 3800 | P92: =SUMIF($G$3:$G$292,G92,$N$3:$N$292) -> 4400 | Q92: =IF(N92<>0,N92/P92,"0") -> 0.86363636 | R92: =VLOOKUP(G92,#REF!,11,0)*Q92 -> #REF! | S92: DC | T92: 1620.75 | U92: 4 | X92: 48 VDC | Y92: 3 | Z92: Q1-Q2 | AB92: Transmisores y Receptotes Ópticos | AC92: Se tiene disponibilidad de espacio, AA y rectificadores para soportar la nueva carga | AD92: 2 | AE92: SI | AH92: =IF(AG92=1,'BU FACILITIES'!$G$24,"") | AI92: Acometidas para equipos: 150 metros cable #6AWG para OLT, 320 metros cable 3x14 AWG para plataforma óptica, 150m cable 1/0 AWG para equipos IAP, 150 m cable 6 AWG para equipos DWDM. | AK92: =AJ92*'BU FACILITIES'!$G$21 -> 0 | AL92: 1 | AM92: =PRODUCT( AL92,'BU FACILITIES'!$G$22) -> 870.73171 | AP92: =IF(AO92=1,'BU FACILITIES'!$G$23,"") | AQ92: 0 | AR92: 0 | AS92: =IF(AR92=300,AQ92*'BU FACILITIES'!$G$4, IF(AND(AR92>300,AR92<=500), AQ92*'BU FACILITIES'!$G$5, IF(AND(AR92>500,AR92<=1250), AQ92*'BU FACILITIES'!$G$6, IF(AND(AR92>1250,AR92<=2000),AQ92*'BU FACILITIES'!$G$7, "")))) | AT92: 0 | AU92: 0 | AV92: =IF(AU92=100,AT92*'BU FACILITIES'!$G$8, IF(AND(AU92>100,AU92<=500), AT92*'BU FACILITIES'!$G$9, IF(AND(AU92>500,AU92<=800), AT92*'BU FACILITIES'!$G$10, IF(AND(AU92>800,AU92<=1000),AT92*'BU FACILITIES'!$G$11, IF(AND(AU92>1000,AU92<=1400),AT92*'BU FACILITIES'!$G$12, IF(AND(AU92>1400,AU92<=2000),AT92*'BU FACILITIES'!$G$13,"")))))) | AW92: 0 | AX92: 0 | AY92: =IF(AX92=30,AW92*'BU FACILITIES'!$G$14, IF(AX92=45, AW92*'BU FACILITIES'!$G$15, IF(AX92=450, AW92*'BU FACILITIES'!$G$16, ""))) | AZ92: 0 | BA92: 0 | BB92: =IF(AND(BA92>=1,BA92<=5),'BU FACILITIES'!$G$17, IF(AND(BA92>5, BA92<=10), 'BU FACILITIES'!$G$18, IF(AND(BA92>10,BA92<=20),'BU FACILITIES'!$G$19,""))) | BD92: =IF(AND(AZ92="Modificar ductería de AA",BC92=1), 'BU FACILITIES'!$G$20, "")
A93: Plataforma Óptica | B93: BBI-TV-TOIP | C93: Income | D93: Gerencia Acceso Fijo | E93: Jorge Ivan Pérez Cardona | F93: 2023 | G93: Velez Soto | H93: Palmira | J93: Yes | K93: 1 | L93: 6 | M93: 475 | N93: 2850 | P93: =SUMIF($G$3:$G$292,G93,$N$3:$N$292) -> 2850 | Q93: =IF(N93<>0,N93/P93,"0") -> 1 | R93: =VLOOKUP(G93,#REF!,11,0)*Q93 -> #REF! | S93: DC | T93: 1620.75 | U93: 2 | X93: 48 VDC | Y93: 1.5 | Z93: Q1-Q2 | AB93: Transmisores y Receptotes Ópticos | AC93: No se tiene espacio en sito para la instalación de rack nuevo, debe hacerse TSS para desmonte de equipos no usados o verificar espacios existentes en los racks del sitio. | AD93: 4 | AE93: SI, condicionado | AH93: =IF(AG93=1,'BU FACILITIES'!$G$24,"") | AI93: Sitio nuevo | AK93: =AJ93*'BU FACILITIES'!$G$21 -> 0 | AL93: 1 | AM93: =PRODUCT( AL93,'BU FACILITIES'!$G$22) -> 870.73171 | AP93: =IF(AO93=1,'BU FACILITIES'!$G$23,"") | AS93: =IF(AR93=300,AQ93*'BU FACILITIES'!$G$4, IF(AND(AR93>300,AR93<=500), AQ93*'BU FACILITIES'!$G$5, IF(AND(AR93>500,AR93<=1250), AQ93*'BU FACILITIES'!$G$6, IF(AND(AR93>1250,AR93<=2000),AQ93*'BU FACILITIES'!$G$7, "")))) | AV93: =IF(AU93=100,AT93*'BU FACILITIES'!$G$8, IF(AND(AU93>100,AU93<=500), AT93*'BU FACILITIES'!$G$9, IF(AND(AU93>500,AU93<=800), AT93*'BU FACILITIES'!$G$10, IF(AND(AU93>800,AU93<=1000),AT93*'BU FACILITIES'!$G$11, IF(AND(AU93>1000,AU93<=1400),AT93*'BU FACILITIES'!$G$12, IF(AND(AU93>1400,AU93<=2000),AT93*'BU FACILITIES'!$G$13,"")))))) | AY93: =IF(AX93=30,AW93*'BU FACILITIES'!$G$14, IF(AX93=45, AW93*'BU FACILITIES'!$G$15, IF(AX93=450, AW93*'BU FACILITIES'!$G$16, ""))) | BB93: =IF(AND(BA93>=1,BA93<=5),'BU FACILITIES'!$G$17, IF(AND(BA93>5, BA93<=10), 'BU FACILITIES'!$G$18, IF(AND(BA93>10,BA93<=20),'BU FACILITIES'!$G$19,""))) | BD93: =IF(AND(AZ93="Modificar ductería de AA",BC93=1), 'BU FACILITIES'!$G$20, "")
A94: Plataforma Óptica | B94: BBI-TV-TOIP | C94: Income | D94: Gerencia Acceso Fijo | E94: Jorge Ivan Pérez Cardona | F94: 2023 | G94: La Floresta | H94: Pasto | J94: Yes | K94: 1 | L94: 6 | M94: 475 | N94: 2850 | P94: =SUMIF($G$3:$G$292,G94,$N$3:$N$292) -> 2850 | Q94: =IF(N94<>0,N94/P94,"0") -> 1 | R94: =VLOOKUP(G94,#REF!,11,0)*Q94 -> #REF! | S94: DC | T94: 1620.75 | U94: 2 | X94: 48 VDC | Y94: 1.5 | Z94: Q1-Q2 | AB94: Transmisores y Receptotes Ópticos | AC94: Se tiene capacidad en rectificadores, AA y espacio físico, no se requieren obras civiles para la instalación. | AD94: 3 | AE94: SI | AH94: =IF(AG94=1,'BU FACILITIES'!$G$24,"") | AI94: Se requieren aproximadamente 252m de cable 3x14 AWG y 12 breakers de 10A para PDB | AJ94: 1 | AK94: =AJ94*'BU FACILITIES'!$G$21 -> 1714.6341 | AL94: 1 | AM94: =PRODUCT( AL94,'BU FACILITIES'!$G$22) -> 870.73171 | AP94: =IF(AO94=1,'BU FACILITIES'!$G$23,"") | AQ94: 0 | AR94: 0 | AS94: =IF(AR94=300,AQ94*'BU FACILITIES'!$G$4, IF(AND(AR94>300,AR94<=500), AQ94*'BU FACILITIES'!$G$5, IF(AND(AR94>500,AR94<=1250), AQ94*'BU FACILITIES'!$G$6, IF(AND(AR94>1250,AR94<=2000),AQ94*'BU FACILITIES'!$G$7, "")))) | AT94: 0 | AU94: 0 | AV94: =IF(AU94=100,AT94*'BU FACILITIES'!$G$8, IF(AND(AU94>100,AU94<=500), AT94*'BU FACILITIES'!$G$9, IF(AND(AU94>500,AU94<=800), AT94*'BU FACILITIES'!$G$10, IF(AND(AU94>800,AU94<=1000),AT94*'BU FACILITIES'!$G$11, IF(AND(AU94>1000,AU94<=1400),AT94*'BU FACILITIES'!$G$12, IF(AND(AU94>1400,AU94<=2000),AT94*'BU FACILITIES'!$G$13,"")))))) | AW94: 0 | AX94: 0 | AY94: =IF(AX94=30,AW94*'BU FACILITIES'!$G$14, IF(AX94=45, AW94*'BU FACILITIES'!$G$15, IF(AX94=450, AW94*'BU FACILITIES'!$G$16, ""))) | AZ94: 0 | BA94: 0 | BB94: =IF(AND(BA94>=1,BA94<=5),'BU FACILITIES'!$G$17, IF(AND(BA94>5, BA94<=10), 'BU FACILITIES'!$G$18, IF(AND(BA94>10,BA94<=20),'BU FACILITIES'!$G$19,""))) | BD94: =IF(AND(AZ94="Modificar ductería de AA",BC94=1), 'BU FACILITIES'!$G$20, "")
A95: Plataforma Óptica | B95: BBI-TV-TOIP | C95: Income | D95: Gerencia Acceso Fijo | E95: Jorge Ivan Pérez Cardona | F95: 2023 | G95: Prados del Norte | H95: Popayán | J95: Yes | K95: 1 | L95: 6 | M95: 475 | N95: 2850 | P95: =SUMIF($G$3:$G$292,G95,$N$3:$N$292) -> 2850 | Q95: =IF(N95<>0,N95/P95,"0") -> 1 | R95: =VLOOKUP(G95,#REF!,11,0)*Q95 -> #REF! | S95: DC | T95: 1620.75 | U95: 2 | X95: 48 VDC | Y95: 1.5 | Z95: Q1-Q2 | AB95: Transmisores y Receptotes Ópticos | AC95: El sitio cuenta con capacidad en DC, AA y espacio para el nuevo rack, no requiere obras civiles | AD95: 4 | AE95: SI | AF95: 0 | AH95: =IF(AG95=1,'BU FACILITIES'!$G$24,"") | AI95: Se requieren aproximadamente 310m de cable 3x14 AWG y 12 breakers 10 A para PDB | AJ95: 1 | AK95: =AJ95*'BU FACILITIES'!$G$21 -> 1714.6341 | AL95: 1 | AM95: =PRODUCT( AL95,'BU FACILITIES'!$G$22) -> 870.73171 | AN95: 0 | AP95: =IF(AO95=1,'BU FACILITIES'!$G$23,"") | AQ95: 0 | AR95: 0 | AS95: =IF(AR95=300,AQ95*'BU FACILITIES'!$G$4, IF(AND(AR95>300,AR95<=500), AQ95*'BU FACILITIES'!$G$5, IF(AND(AR95>500,AR95<=1250), AQ95*'BU FACILITIES'!$G$6, IF(AND(AR95>1250,AR95<=2000),AQ95*'BU FACILITIES'!$G$7, "")))) | AT95: 0 | AU95: 0 | AV95: =IF(AU95=100,AT95*'BU FACILITIES'!$G$8, IF(AND(AU95>100,AU95<=500), AT95*'BU FACILITIES'!$G$9, IF(AND(AU95>500,AU95<=800), AT95*'BU FACILITIES'!$G$10, IF(AND(AU95>800,AU95<=1000),AT95*'BU FACILITIES'!$G$11, IF(AND(AU95>1000,AU95<=1400),AT95*'BU FACILITIES'!$G$12, IF(AND(AU95>1400,AU95<=2000),AT95*'BU FACILITIES'!$G$13,"")))))) | AW95: 0 | AX95: 0 | AY95: =IF(AX95=30,AW95*'BU FACILITIES'!$G$14, IF(AX95=45, AW95*'BU FACILITIES'!$G$15, IF(AX95=450, AW95*'BU FACILITIES'!$G$16, ""))) | AZ95: 0 | BA95: 0 | BB95: =IF(AND(BA95>=1,BA95<=5),'BU FACILITIES'!$G$17, IF(AND(BA95>5, BA95<=10), 'BU FACILITIES'!$G$18, IF(AND(BA95>10,BA95<=20),'BU FACILITIES'!$G$19,""))) | BD95: =IF(AND(AZ95="Modificar ductería de AA",BC95=1), 'BU FACILITIES'!$G$20, "")
A96: Plataforma Óptica | B96: BBI-TV-TOIP | C96: Income | D96: Gerencia Acceso Fijo | E96: Jorge Ivan Pérez Cardona | F96: 2023 | G96: Campiña | H96: Tuluá | J96: Yes | K96: 1 | L96: 6 | M96: 475 | N96: 2850 | P96: =SUMIF($G$3:$G$292,G96,$N$3:$N$292) -> 2850 | Q96: =IF(N96<>0,N96/P96,"0") -> 1 | R96: =VLOOKUP(G96,#REF!,11,0)*Q96 -> #REF! | S96: DC | T96: 1620.75 | U96: 2 | X96: 48 VDC | Y96: 1.5 | Z96: Q1-Q2 | AB96: Transmisores y Receptotes Ópticos | AC96: El sitio cuenta con espacio, capacidad de rectificadores y AA para soportar la carga | AD96: 4 | AE96: SI | AH96: =IF(AG96=1,'BU FACILITIES'!$G$24,"") | AI96: Se requiere cableado 3X14 AWG aproximadamente 170m y 6 breakers 10A para PDB | AJ96: 1 | AK96: =AJ96*'BU FACILITIES'!$G$21 -> 1714.6341 | AL96: 1 | AM96: =PRODUCT( AL96,'BU FACILITIES'!$G$22) -> 870.73171 | AN96: 0 | AP96: =IF(AO96=1,'BU FACILITIES'!$G$23,"") | AQ96: 0 | AR96: 0 | AS96: =IF(AR96=300,AQ96*'BU FACILITIES'!$G$4, IF(AND(AR96>300,AR96<=500), AQ96*'BU FACILITIES'!$G$5, IF(AND(AR96>500,AR96<=1250), AQ96*'BU FACILITIES'!$G$6, IF(AND(AR96>1250,AR96<=2000),AQ96*'BU FACILITIES'!$G$7, "")))) | AT96: 0 | AU96: 0 | AV96: =IF(AU96=100,AT96*'BU FACILITIES'!$G$8, IF(AND(AU96>100,AU96<=500), AT96*'BU FACILITIES'!$G$9, IF(AND(AU96>500,AU96<=800), AT96*'BU FACILITIES'!$G$10, IF(AND(AU96>800,AU96<=1000),AT96*'BU FACILITIES'!$G$11, IF(AND(AU96>1000,AU96<=1400),AT96*'BU FACILITIES'!$G$12, IF(AND(AU96>1400,AU96<=2000),AT96*'BU FACILITIES'!$G$13,"")))))) | AW96: 0 | AX96: 0 | AY96: =IF(AX96=30,AW96*'BU FACILITIES'!$G$14, IF(AX96=45, AW96*'BU FACILITIES'!$G$15, IF(AX96=450, AW96*'BU FACILITIES'!$G$16, ""))) | AZ96: 0 | BA96: 0 | BB96: =IF(AND(BA96>=1,BA96<=5),'BU FACILITIES'!$G$17, IF(AND(BA96>5, BA96<=10), 'BU FACILITIES'!$G$18, IF(AND(BA96>10,BA96<=20),'BU FACILITIES'!$G$19,""))) | BD96: =IF(AND(AZ96="Modificar ductería de AA",BC96=1), 'BU FACILITIES'!$G$20, "")
A97: MPLS | B97: MPLS | C97: INCOME | D97: Gerencia Cloud, IP y DC | E97: José Alejandro Arcila | F97: 2023 | G97: Miraflores | H97: Medellín | I97: NOROCCIDENTE | J97: no | K97: 0 | L97: 0 | M97: 400 | N97: =600+400 -> 1000 | P97: =SUMIF($G$3:$G$292,G97,$N$3:$N$292) -> 7650 | Q97: =IF(N97<>0,N97/P97,"0") -> 0.13071895 | R97: =VLOOKUP(G97,#REF!,11,0)*Q97 -> #REF! | S97: dc | T97: 682 BTU/hour | AB97: Tarjeta 2*100 | AD97: 2 | AE97: SI | AH97: =IF(AG97=1,'BU FACILITIES'!$G$24,"") | AK97: =AJ97*'BU FACILITIES'!$G$21 -> 0 | AL97: 0 | AM97: =PRODUCT( AL97,'BU FACILITIES'!$G$22) -> 0 | AP97: =IF(AO97=1,'BU FACILITIES'!$G$23,"") | AS97: =IF(AR97=300,AQ97*'BU FACILITIES'!$G$4, IF(AND(AR97>300,AR97<=500), AQ97*'BU FACILITIES'!$G$5, IF(AND(AR97>500,AR97<=1250), AQ97*'BU FACILITIES'!$G$6, IF(AND(AR97>1250,AR97<=2000),AQ97*'BU FACILITIES'!$G$7, "")))) | AV97: =IF(AU97=100,AT97*'BU FACILITIES'!$G$8, IF(AND(AU97>100,AU97<=500), AT97*'BU FACILITIES'!$G$9, IF(AND(AU97>500,AU97<=800), AT97*'BU FACILITIES'!$G$10, IF(AND(AU97>800,AU97<=1000),AT97*'BU FACILITIES'!$G$11, IF(AND(AU97>1000,AU97<=1400),AT97*'BU FACILITIES'!$G$12, IF(AND(AU97>1400,AU97<=2000),AT97*'BU FACILITIES'!$G$13,"")))))) | AY97: =IF(AX97=30,AW97*'BU FACILITIES'!$G$14, IF(AX97=45, AW97*'BU FACILITIES'!$G$15, IF(AX97=450, AW97*'BU FACILITIES'!$G$16, ""))) | BB97: =IF(AND(BA97>=1,BA97<=5),'BU FACILITIES'!$G$17, IF(AND(BA97>5, BA97<=10), 'BU FACILITIES'!$G$18, IF(AND(BA97>10,BA97<=20),'BU FACILITIES'!$G$19,""))) | BD97: =IF(AND(AZ97="Modificar ductería de AA",BC97=1), 'BU FACILITIES'!$G$20, "")
A98: MPLS | B98: MPLS | C98: INCOME | D98: Gerencia Cloud, IP y DC | E98: José Alejandro Arcila | F98: 2023 | G98: Montería | H98: Montería | J98: no | K98: 0 | L98: 0 | M98: 400 | N98: 600 | P98: =SUMIF($G$3:$G$292,G98,$N$3:$N$292) -> 1200 | Q98: =IF(N98<>0,N98/P98,"0") -> 0.5 | R98: =VLOOKUP(G98,#REF!,11,0)*Q98 -> #REF! | S98: dc | T98: 682 BTU/hour | AB98: Tarjeta 24*10 | AC98: Posee doble rectif y BB, tiene MG, no requiere inversión 2023 para asumir esta carga | AD98: 4 | AE98: SI | AH98: =IF(AG98=1,'BU FACILITIES'!$G$24,"") | AK98: =AJ98*'BU FACILITIES'!$G$21 -> 0 | AL98: 0 | AM98: =PRODUCT( AL98,'BU FACILITIES'!$G$22) -> 0 | AP98: =IF(AO98=1,'BU FACILITIES'!$G$23,"") | AS98: =IF(AR98=300,AQ98*'BU FACILITIES'!$G$4, IF(AND(AR98>300,AR98<=500), AQ98*'BU FACILITIES'!$G$5, IF(AND(AR98>500,AR98<=1250), AQ98*'BU FACILITIES'!$G$6, IF(AND(AR98>1250,AR98<=2000),AQ98*'BU FACILITIES'!$G$7, "")))) | AV98: =IF(AU98=100,AT98*'BU FACILITIES'!$G$8, IF(AND(AU98>100,AU98<=500), AT98*'BU FACILITIES'!$G$9, IF(AND(AU98>500,AU98<=800), AT98*'BU FACILITIES'!$G$10, IF(AND(AU98>800,AU98<=1000),AT98*'BU FACILITIES'!$G$11, IF(AND(AU98>1000,AU98<=1400),AT98*'BU FACILITIES'!$G$12, IF(AND(AU98>1400,AU98<=2000),AT98*'BU FACILITIES'!$G$13,"")))))) | AY98: =IF(AX98=30,AW98*'BU FACILITIES'!$G$14, IF(AX98=45, AW98*'BU FACILITIES'!$G$15, IF(AX98=450, AW98*'BU FACILITIES'!$G$16, ""))) | BB98: =IF(AND(BA98>=1,BA98<=5),'BU FACILITIES'!$G$17, IF(AND(BA98>5, BA98<=10), 'BU FACILITIES'!$G$18, IF(AND(BA98>10,BA98<=20),'BU FACILITIES'!$G$19,""))) | BD98: =IF(AND(AZ98="Modificar ductería de AA",BC98=1), 'BU FACILITIES'!$G$20, "")
A99: MPLS | B99: MPLS | C99: INCOME | D99: Gerencia Cloud, IP y DC | E99: José Alejandro Arcila | F99: 2023 | G99: Bello | H99: Bello | I99: NOROCCIDENTE | J99: no | K99: 0 | L99: 0 | M99: 400 | N99: 600 | P99: =SUMIF($G$3:$G$292,G99,$N$3:$N$292) -> 600 | Q99: =IF(N99<>0,N99/P99,"0") -> 1 | R99: =VLOOKUP(G99,#REF!,11,0)*Q99 -> #REF! | S99: dc | T99: 682 BTU/hour | AB99: Tarjeta 2*100G | AC99: Espacio disponible al lado de los CMTS | AD99: 3 | AE99: SI | AH99: =IF(AG99=1,'BU FACILITIES'!$G$24,"") | AK99: =AJ99*'BU FACILITIES'!$G$21 -> 0 | AL99: 0 | AM99: =PRODUCT( AL99,'BU FACILITIES'!$G$22) -> 0 | AP99: =IF(AO99=1,'BU FACILITIES'!$G$23,"") | AS99: =IF(AR99=300,AQ99*'BU FACILITIES'!$G$4, IF(AND(AR99>300,AR99<=500), AQ99*'BU FACILITIES'!$G$5, IF(AND(AR99>500,AR99<=1250), AQ99*'BU FACILITIES'!$G$6, IF(AND(AR99>1250,AR99<=2000),AQ99*'BU FACILITIES'!$G$7, "")))) | AV99: =IF(AU99=100,AT99*'BU FACILITIES'!$G$8, IF(AND(AU99>100,AU99<=500), AT99*'BU FACILITIES'!$G$9, IF(AND(AU99>500,AU99<=800), AT99*'BU FACILITIES'!$G$10, IF(AND(AU99>800,AU99<=1000),AT99*'BU FACILITIES'!$G$11, IF(AND(AU99>1000,AU99<=1400),AT99*'BU FACILITIES'!$G$12, IF(AND(AU99>1400,AU99<=2000),AT99*'BU FACILITIES'!$G$13,"")))))) | AY99: =IF(AX99=30,AW99*'BU FACILITIES'!$G$14, IF(AX99=45, AW99*'BU FACILITIES'!$G$15, IF(AX99=450, AW99*'BU FACILITIES'!$G$16, ""))) | BB99: =IF(AND(BA99>=1,BA99<=5),'BU FACILITIES'!$G$17, IF(AND(BA99>5, BA99<=10), 'BU FACILITIES'!$G$18, IF(AND(BA99>10,BA99<=20),'BU FACILITIES'!$G$19,""))) | BD99: =IF(AND(AZ99="Modificar ductería de AA",BC99=1), 'BU FACILITIES'!$G$20, "")
A100: MPLS | B100: MPLS | C100: INCOME | D100: Gerencia Cloud, IP y DC | E100: José Alejandro Arcila | F100: 2023 | G100: Engativá | H100: Bogotá | J100: no | K100: 0 | L100: 0 | M100: 400 | N100: 600 | P100: =SUMIF($G$3:$G$292,G100,$N$3:$N$292) -> 1800 | Q100: =IF(N100<>0,N100/P100,"0") -> 0.33333333 | R100: =VLOOKUP(G100,#REF!,11,0)*Q100 -> #REF! | S100: dc | T100: 682 BTU/hour | AB100: Tarjeta 2*100G | AC100: Se aprueba el requerimiento | AD100: N4 | AE100: SI | AH100: =IF(AG100=1,'BU FACILITIES'!$G$24,"") | AK100: =AJ100*'BU FACILITIES'!$G$21 -> 0 | AL100: 0 | AM100: =PRODUCT( AL100,'BU FACILITIES'!$G$22) -> 0 | AP100: =IF(AO100=1,'BU FACILITIES'!$G$23,"") | AS100: =IF(AR100=300,AQ100*'BU FACILITIES'!$G$4, IF(AND(AR100>300,AR100<=500), AQ100*'BU FACILITIES'!$G$5, IF(AND(AR100>500,AR100<=1250), AQ100*'BU FACILITIES'!$G$6, IF(AND(AR100>1250,AR100<=2000),AQ100*'BU FACILITIES'!$G$7, "")))) | AV100: =IF(AU100=100,AT100*'BU FACILITIES'!$G$8, IF(AND(AU100>100,AU100<=500), AT100*'BU FACILITIES'!$G$9, IF(AND(AU100>500,AU100<=800), AT100*'BU FACILITIES'!$G$10, IF(AND(AU100>800,AU100<=1000),AT100*'BU FACILITIES'!$G$11, IF(AND(AU100>1000,AU100<=1400),AT100*'BU FACILITIES'!$G$12, IF(AND(AU100>1400,AU100<=2000),AT100*'BU FACILITIES'!$G$13,"")))))) | AY100: =IF(AX100=30,AW100*'BU FACILITIES'!$G$14, IF(AX100=45, AW100*'BU FACILITIES'!$G$15, IF(AX100=450, AW100*'BU FACILITIES'!$G$16, ""))) | BB100: =IF(AND(BA100>=1,BA100<=5),'BU FACILITIES'!$G$17, IF(AND(BA100>5, BA100<=10), 'BU FACILITIES'!$G$18, IF(AND(BA100>10,BA100<=20),'BU FACILITIES'!$G$19,""))) | BD100: =IF(AND(AZ100="Modificar ductería de AA",BC100=1), 'BU FACILITIES'!$G$20, "")
...

Sheet Datos transformados
B2: INFORMACIÓN IMPORTANTE
